Workbook

Sheet 合并采购清单
A2: Microduck 鸭子用料与制作工具采购清单
A3: 2026-10-13 | HAT-V5（含后续用料记录）+ IMU-TO-DLX-V2
A4: HAT块数 | B4: 1 | C4: IMU块数 | D4: 1 | F4: 器件总数 | H4: =SUM(F9:F54) -> 109
A5: 修改块数可重算用量。单套：HAT 84 个器件 + IMU 25 个器件。
A6: 采购商品由作者确认已实测可用。按列明的商品型号和订单款式购买。
A7: R33按0Ω采购；TH1可使用原村田PRG18BB101MB1RB（100Ω PTC，0603）。原工程属性保留在位号表。
A8: 类别 | B8: 工程型号 / 当前用料 | C8: 封装与关键规格 | D8: HAT单板(个) | E8: IMU单板(个) | F8: 本次需求(个) | G8: HAT位号 | H8: IMU位号 | I8: 订单店铺 | J8: 订单商品链接 | K8: 必须选择的订单款式 | L8: 每拍含量(个) | M8: 按此款式最少拍数 | N8: 工程型号参考链接 | O8: 购买说明
A9: 电容 | B9: CC0603KRX5R9BB105 | C9: 0603；1uF / ±10% / 50V / X5R | D9: 15 | E9: 0 | F9: =D9*$B$4+E9*$D$4 -> 15 | G9: C1, C2, C3, C4, C6, C10, C27, C29, C31, C33, C35, C40, C41, C42, C43 | I9: 深圳市宏宸电子 | J9: =HYPERLINK("https://item.taobao.com/item.htm?id=630712731066","打开订单商品") -> 打开订单商品 | K9: 0603 1uF ±10% X7R;50V | L9: 1 | M9: =ROUNDUP(F9/L9,0) -> 15 | N9: =HYPERLINK("https://www.lcsc.com/product-detail/C128624.html","查看工程型号") -> 查看工程型号 | O9: 实际采购：0603 / 1uF / ±10% / 50V / X7R。
A10: 电容 | B10: C1608X5R1A106KT000E | C10: 0603；10uF / ±10% / 10V / X5R | D10: 5 | E10: 0 | F10: =D10*$B$4+E10*$D$4 -> 5 | G10: C5, C7, C12, C13, C37 | I10: 深圳市宏宸电子 | J10: =HYPERLINK("https://item.taobao.com/item.htm?id=630712731066","打开订单商品") -> 打开订单商品 | K10: 0603 10uF ±10% X5R;10V | L10: 1 | M10: =ROUNDUP(F10/L10,0) -> 5 | N10: =HYPERLINK("https://item.szlcsc.com/77735.html","查看工程型号") -> 查看工程型号 | O10: 实际采购：0603 / 10uF / ±10% / 10V / X5R。
A11: 电容 | B11: 0603CG221J500NT | C11: 0603；220pF / ±5% / 50V / C0G | D11: 2 | E11: 0 | F11: =D11*$B$4+E11*$D$4 -> 2 | G11: C8, C9 | I11: 深圳市宏宸电子 | J11: =HYPERLINK("https://item.taobao.com/item.htm?id=1005108810412","打开订单商品") -> 打开订单商品 | K11: 0603 220pF ±5% NPO/COG;50V;100个 | L11: 100 | M11: =ROUNDUP(F11/L11,0) -> 1 | N11: =HYPERLINK("https://item.szlcsc.com/167743.html","查看工程型号") -> 查看工程型号 | O11: 选 220pF、50V、C0G(NPO)、±5%、0603；同页其他容量分别选购。
A12: 电容 | B12: CC0603KRX7R9BB104 | C12: 0603；100nF / ±10% / 50V / X7R | D12: 13 | E12: 0 | F12: =D12*$B$4+E12*$D$4 -> 13 | G12: C11, C14, C16, C17, C18, C20, C26, C28, C30, C32, C36, C38, C39 | I12: 深圳市宏宸电子 | J12: =HYPERLINK("https://item.taobao.com/item.htm?id=731471380840","打开订单商品") -> 打开订单商品 | K12: 0603 100nF ±10% X7R;50V;100个 | L12: 100 | M12: =ROUNDUP(F12/L12,0) -> 1 | N12: =HYPERLINK("https://item.szlcsc.com/15331.html","查看工程型号") -> 查看工程型号 | O12: 实际采购：0603 / 100nF / ±10% / 50V / X7R。
A13: 电容 | B13: C3216X7R1V106KT000E | C13: 1206；10uF / ±10% / 35V / X7R | D13: 1 | E13: 0 | F13: =D13*$B$4+E13*$D$4 -> 1 | G13: C15 | I13: 深圳市宏宸电子 | J13: =HYPERLINK("https://item.taobao.com/item.htm?id=730407108775","打开订单商品") -> 打开订单商品 | K13: 1206 10UF ±10% X7R;35V | L13: 1 | M13: =ROUNDUP(F13/L13,0) -> 1 | N13: =HYPERLINK("https://item.szlcsc.com/77793.html","查看工程型号") -> 查看工程型号 | O13: C15 使用 1206、10uF、35V、X7R 款式。
A14: 电容 | B14: GRM188R61A226ME15D | C14: 0603；22uF / ±20% / 10V / X5R | D14: 2 | E14: 0 | F14: =D14*$B$4+E14*$D$4 -> 2 | G14: C21, C22 | I14: 优好电子 | J14: =HYPERLINK("https://item.taobao.com/item.htm?id=993202872551","打开订单商品") -> 打开订单商品 | K14: 22UF 226K 10% X5R;10V;0603=100个 | L14: 100 | M14: =ROUNDUP(F14/L14,0) -> 1 | N14: =HYPERLINK("https://item.szlcsc.com/85589.html","查看工程型号") -> 查看工程型号 | O14: 实际采购：0603 / 22uF / ±10% / 10V / X5R。
A15: 电容 | B15: CC0603KRX7R9BB103 | C15: 0603；10nF / ±10% / 50V / X7R | D15: 1 | E15: 0 | F15: =D15*$B$4+E15*$D$4 -> 1 | G15: C34 | I15: 欧贝顿旗舰店 | J15: =HYPERLINK("https://item.taobao.com/item.htm?id=610558214623","打开订单商品") -> 打开订单商品 | K15: 0603 10NF 50V 10% 100个 | L15: 100 | M15: =ROUNDUP(F15/L15,0) -> 1 | N15: =HYPERLINK("https://item.szlcsc.com/101256.html","查看工程型号") -> 查看工程型号 | O15: 实际采购：0603 / 10nF / ±10% / 50V / X7R。
A16: 半导体 | B16: BAT54SW,115 | C16: SOT-323；二极管配置:1对串联式；正向压降(Vf):800mV@100mA；直流反向耐压(Vr):30V；整流电流:200mA | D16: 1 | E16: 0 | F16: =D16*$B$4+E16*$D$4 -> 1 | G16: D1 | I16: 深圳市乐桥微科技 | J16: =HYPERLINK("https://item.taobao.com/item.htm?id=793455311175","打开订单商品") -> 打开订单商品 | K16: BAT54SW 印字44t（20只） | L16: 20 | M16: =ROUNDUP(F16/L16,0) -> 1 | N16: =HYPERLINK("https://item.szlcsc.com/79742.html","查看工程型号") -> 查看工程型号 | O16: 选择 BAT54SW / SOT-323 款式。
A17: 半导体 | B17: BZT52C5V1S-7-F | C17: SOD-323；二极管配置:1个独立式；稳压值(标称值):5.1V；稳压值(范围值):4.8V~5.4V；耗散功率(Pd):200mW | D17: 1 | E17: 0 | F17: =D17*$B$4+E17*$D$4 -> 1 | G17: D4 | I17: 稳泊仕旗舰店 | J17: =HYPERLINK("https://item.taobao.com/item.htm?id=943185002457","打开订单商品") -> 打开订单商品 | K17: BZT52C5V1S W8 SOD-323 (50个) | L17: 50 | M17: =ROUNDUP(F17/L17,0) -> 1 | N17: =HYPERLINK("https://item.szlcsc.com/162688.html","查看工程型号") -> 查看工程型号 | O17: 选择 BZT52C5V1S / 5.1V / SOD-323 款式。
A18: 磁珠 | B18: BLM18KG601SN1D | C18: 0603；±25% / 600Ω@100MHz / 1.3A | D18: 1 | E18: 0 | F18: =D18*$B$4+E18*$D$4 -> 1 | G18: FB1 | I18: 科芯奇旗舰店 | J18: =HYPERLINK("https://item.taobao.com/item.htm?id=931081429973","打开订单商品") -> 打开订单商品 | K18: 0603_600R_1.3A_±25%【100只】 | L18: 100 | M18: =ROUNDUP(F18/L18,0) -> 1 | N18: =HYPERLINK("https://item.szlcsc.com/87009.html","查看工程型号") -> 查看工程型号 | O18: 实际采购：0603 / 600Ω@100MHz / 1.3A / ±25%。
A19: 磁珠 | B19: PE-0603PFB121ST | C19: 0603；±25% / 120Ω@100MHz / 2A | D19: 2 | E19: 0 | F19: =D19*$B$4+E19*$D$4 -> 2 | G19: FB2, FB3 | I19: 科芯奇旗舰店 | J19: =HYPERLINK("https://item.taobao.com/item.htm?id=931081429973","打开订单商品") -> 打开订单商品 | K19: 0603_120R_2A_±25%【100只】 | L19: 100 | M19: =ROUNDUP(F19/L19,0) -> 1 | N19: =HYPERLINK("https://item.szlcsc.com/2753383.html","查看工程型号") -> 查看工程型号 | O19: 实际采购：0603 / 120Ω@100MHz / 2A / ±25%。
A20: 连接器 | B20: B2B-EH-A(LF)(SN) | C20: 插件,P=2.5mm；250V / 3A | D20: 3 | E20: 0 | F20: =D20*$B$4+E20*$D$4 -> 3 | G20: J1, J2, J9 | I20: 启色数码旗舰店 | J20: =HYPERLINK("https://item.taobao.com/item.htm?id=832569969546","打开订单商品") -> 打开订单商品 | K20: EH2.5MM 2P直针座（50个） | L20: 50 | M20: =ROUNDUP(F20/L20,0) -> 1 | N20: =HYPERLINK("https://item.szlcsc.com/171642.html","查看工程型号") -> 查看工程型号 | O20: EH 2P 直针座；按 EH2.5MM 2P 直针座选项购买。
A21: 连接器 | B21: FH-00339 | C21: SMD,P=2.54mm；3A | D21: 1 | E21: 0 | F21: =D21*$B$4+E21*$D$4 -> 1 | G21: J4 | I21: 海雀数码专营店 | J21: =HYPERLINK("https://item.taobao.com/item.htm?id=533725557959","打开订单商品") -> 打开订单商品 | K21: 2*20P 贴片排母【2个】 | L21: 2 | M21: =ROUNDUP(F21/L21,0) -> 1 | N21: =HYPERLINK("https://item.szlcsc.com/2784386.html","查看工程型号") -> 查看工程型号 | O21: 双排 2×20P、2.54mm、贴片排母，安装在 HAT 底面。
A22: 连接器 | B22: BM04B-SRSS-TB(LF)(SN) | C22: SMD,P=1mm；50V / 1A | D22: 1 | E22: 0 | F22: =D22*$B$4+E22*$D$4 -> 1 | G22: J5 | I22: 信容芯旗舰店 | J22: =HYPERLINK("https://item.taobao.com/item.htm?id=920058690376","打开订单商品") -> 打开订单商品 | K22: 4P立贴（15个） | L22: 15 | M22: =ROUNDUP(F22/L22,0) -> 1 | N22: =HYPERLINK("https://item.szlcsc.com/171770.html","查看工程型号") -> 查看工程型号 | O22: SH1.0 / 4P / 立贴，按“4P立贴（15个）”选项购买。
A23: 连接器 | B23: B3B-EH-A(LF)(SN) | C23: 插件,P=2.5mm；250V / 3A | D23: 2 | E23: 1 | F23: =D23*$B$4+E23*$D$4 -> 3 | G23: J13, J14 | H23: J1 | I23: 启色数码旗舰店 | J23: =HYPERLINK("https://item.taobao.com/item.htm?id=832569969546","打开订单商品") -> 打开订单商品 | K23: EH2.5MM 3P直针座（50个） | L23: 50 | M23: =ROUNDUP(F23/L23,0) -> 1 | N23: =HYPERLINK("https://item.szlcsc.com/171639.html","查看工程型号") -> 查看工程型号 | O23: EH 3P 直针座，HAT 两只、IMU 一只。
A24: 电感 | B24: SWPA6045S6R8MT | C24: SMD,6x6mm；6.8uH / ±20% / 3A | D24: 1 | E24: 0 | F24: =D24*$B$4+E24*$D$4 -> 1 | G24: L4 | I24: 迪林旗舰店 | J24: =HYPERLINK("https://item.taobao.com/item.htm?id=598174251748","打开订单商品") -> 打开订单商品 | K24: 合金0630 6.8UH 印6R8 10个 6A 一体 | L24: 10 | M24: =ROUNDUP(F24/L24,0) -> 1 | N24: =HYPERLINK("https://item.szlcsc.com/58286.html","查看工程型号") -> 查看工程型号 | O24: 实际使用：合金0630、6.8uH、6A一体成型电感（订单标称）。
A25: 麦克风 | B25: LMA2718T421-OA5-2 | C25: SMD-4P,2.8x1.9mm；指向性:全指向；信噪比:55dB；灵敏度:-42dB；阻抗:300Ω | D25: 1 | E25: 0 | F25: =D25*$B$4+E25*$D$4 -> 1 | G25: MK1 | I25: 深圳市华源芯电子有限公司 电子元器件配单 | J25: =HYPERLINK("https://item.taobao.com/item.htm?id=996702312391","打开订单商品") -> 打开订单商品 | K25: 2718 上进音 硅麦克风【2个】 | L25: 2 | M25: =ROUNDUP(F25/L25,0) -> 1 | N25: =HYPERLINK("https://item.szlcsc.com/8705873.html","查看工程型号") -> 查看工程型号 | O25: 实际使用：2718 上进音模拟 MEMS 麦克风，按“2718 上进音 硅麦克风【2个】”购买。
A26: 半导体 | B26: MMBT3906 | C26: SOT-23；晶体管类型:PNP；集电极电流(Ic):200mA；集射极击穿电压(Vceo):40V；耗散功率(Pd):200mW；直流电流增益(hFE):100@10mA,1V | D26: 1 | E26: 0 | F26: =D26*$B$4+E26*$D$4 -> 1 | G26: Q1 | I26: 稳泊仕旗舰店 | J26: =HYPERLINK("https://item.taobao.com/item.htm?id=944306254140","打开订单商品") -> 打开订单商品 | K26: MMBT3906 丝印2A SOT-23(50个) | L26: 50 | M26: =ROUNDUP(F26/L26,0) -> 1 | N26: =HYPERLINK("https://item.szlcsc.com/774233.html","查看工程型号") -> 查看工程型号 | O26: 选择 MMBT3906 / PNP / SOT-23 款式。
A27: 半导体 | B27: SI2312CDS-T1-GE3 | C27: SOT-23；数量:1个N沟道；漏源电压(Vdss):20V；连续漏极电流(Id):6A；导通电阻(RDS(on)):41.4mΩ@1.8V,5.6A；耗散功率(Pd):2.1W；阈值电压(Vgs(th)):1V@250uA | D27: 1 | E27: 0 | F27: =D27*$B$4+E27*$D$4 -> 1 | G27: Q2 | I27: 一芯向上电子 | J27: =HYPERLINK("https://item.taobao.com/item.htm?id=909264246006","打开订单商品") -> 打开订单商品 | K27: SI2312DS（AE9T）N沟道（20只） | L27: 20 | M27: =ROUNDUP(F27/L27,0) -> 1 | N27: =HYPERLINK("https://item.szlcsc.com/153849.html","查看工程型号") -> 查看工程型号 | O27: 实际使用：SI2312DS（AE9T）N沟道，20只包装。
A28: 电阻 | B28: RC0603FR-0710KL | C28: 0603；10kΩ / ±1% / ±100ppm/℃ / 100mW | D28: 12 | E28: 3 | F28: =D28*$B$4+E28*$D$4 -> 15 | G28: R1, R2, R6, R12, R13, R22, R23, R26, R27, R29, R31, R32 | H28: R2, R4, R5 | I28: 深圳市永芯泰电子企业店 | J28: =HYPERLINK("https://item.taobao.com/item.htm?id=947267344247","打开订单商品") -> 打开订单商品 | K28: 10K;0603 1%（100个） | L28: 100 | M28: =ROUNDUP(F28/L28,0) -> 1 | N28: =HYPERLINK("https://item.szlcsc.com/99429.html","查看工程型号") -> 查看工程型号 | O28: 10kΩ / ±1% / 0603；HAT 十二只、IMU 三只。
A29: 电阻 | B29: 0603WAF0000T5E | C29: 0603；0Ω / ±1% / 0603 | D29: 5 | E29: 1 | F29: =D29*$B$4+E29*$D$4 -> 6 | G29: R3, R4, R5, R7, R33 | H29: R1 | I29: 深圳市永芯泰电子企业店 | J29: =HYPERLINK("https://item.taobao.com/item.htm?id=947267344247","打开订单商品") -> 打开订单商品 | K29: 0R/0欧;0603 1%（100个） | L29: 100 | M29: =ROUNDUP(F29/L29,0) -> 1 | N29: =HYPERLINK("https://item.szlcsc.com/21903.html","查看工程型号") -> 查看工程型号 | O29: 0Ω / 0603；HAT R33 按后续 0Ω / C21189 补丁计入。
A30: 电阻 | B30: 0603WAF1000T5E | C30: 0603；100Ω / ±1% / ±200ppm/℃ / 100mW | D30: 1 | E30: 0 | F30: =D30*$B$4+E30*$D$4 -> 1 | G30: R8 | I30: 深圳市永芯泰电子企业店 | J30: =HYPERLINK("https://item.taobao.com/item.htm?id=947267344247","打开订单商品") -> 打开订单商品 | K30: 100R/100欧;0603 1%（100个） | L30: 100 | M30: =ROUNDUP(F30/L30,0) -> 1 | N30: =HYPERLINK("https://www.lcsc.com/product-detail/C22775.html","查看工程型号") -> 查看工程型号 | O30: 100Ω / ±1% / 0603，用于 HAT R8。
A31: 电阻 | B31: 0603WAF2002T5E | C31: 0603；20kΩ / ±1% / ±100ppm/℃ / 100mW | D31: 1 | E31: 0 | F31: =D31*$B$4+E31*$D$4 -> 1 | G31: R28 | I31: 深圳市永芯泰电子企业店 | J31: =HYPERLINK("https://item.taobao.com/item.htm?id=947267344247","打开订单商品") -> 打开订单商品 | K31: 20K;0603 1%（100个） | L31: 100 | M31: =ROUNDUP(F31/L31,0) -> 1 | N31: =HYPERLINK("https://item.szlcsc.com/4591.html","查看工程型号") -> 查看工程型号 | O31: 20kΩ / ±1% / 0603。
A32: 热敏电阻 | B32: PRG18BB101MB1RB | C32: 0603；100Ω / PTC / 村田 | D32: 1 | E32: 0 | F32: =D32*$B$4+E32*$D$4 -> 1 | G32: TH1 | I32: 贤辉亿芯 | J32: =HYPERLINK("https://item.taobao.com/item.htm?id=582129955778","打开订单商品") -> 打开订单商品 | K32: 100R PRG18BB101MB1RB | L32: 1 | M32: =ROUNDUP(F32/L32,0) -> 1 | N32: =HYPERLINK("https://item.szlcsc.com/984022.html","查看工程型号") -> 查看工程型号 | O32: TH1可使用原村田PRG18BB101MB1RB（100Ω PTC，0603），按原订单100R款式采购；R33使用0Ω。
A33: 半导体 | B33: PAM8406DR | C33: SOIC-16；功放类型:AB类功放；D类功放；扬声器通道数:双声道；输出功率:5Wx2@2Ω；静态电流(Iq):10mA | D33: 1 | E33: 0 | F33: =D33*$B$4+E33*$D$4 -> 1 | G33: U1 | I33: 深圳市远大芯程科技 | J33: =HYPERLINK("https://item.taobao.com/item.htm?id=808484505787","打开订单商品") -> 打开订单商品 | K33: PAM8406DR | L33: 1 | M33: =ROUNDUP(F33/L33,0) -> 1 | N33: =HYPERLINK("https://item.szlcsc.com/87446.html","查看工程型号") -> 查看工程型号 | O33: 实际使用：PAM8406DR，订单标注 SOP16。
A34: 半导体 | B34: TLV320AIC3104IRHBR | C34: HVQFN-32-EP(5x5)；类型:编解码器；接口类型:I2S；I2C；采样率:8kHz~96kHz | D34: 1 | E34: 0 | F34: =D34*$B$4+E34*$D$4 -> 1 | G34: U2 | I34: 淼鑫电子科技 | J34: =HYPERLINK("https://item.taobao.com/item.htm?id=908248360601","打开订单商品") -> 打开订单商品 | K34: 商品无选项，按商品标题完整型号购买 | L34: 1 | M34: =ROUNDUP(F34/L34,0) -> 1 | N34: =HYPERLINK("https://www.lcsc.com/product-detail/C181753.html","查看工程型号") -> 查看工程型号 | O34: TLV320AIC3104IRHBR，按商品完整型号购买。
A35: 半导体 | B35: XC6206P182MR | C35: SOT-23；输出极性:正极；工作电压:8V；输出电压:1.8V；输出电流:250mA；电源纹波抑制比(PSRR):40dB@(1kHz)；输出类型:固定 | D35: 1 | E35: 0 | F35: =D35*$B$4+E35*$D$4 -> 1 | G35: U3 | I35: 启色数码旗舰店 | J35: =HYPERLINK("https://item.taobao.com/item.htm?id=762173333947","打开订单商品") -> 打开订单商品 | K35: XC6206P182MR 65K5 SOT-23 (20个) | L35: 20 | M35: =ROUNDUP(F35/L35,0) -> 1 | N35: =HYPERLINK("https://item.szlcsc.com/324033.html","查看工程型号") -> 查看工程型号 | O35: XC6206P182MR / 1.8V / SOT-23，20个包装。
A36: 半导体 | B36: SN74LVC1G08DBVR | C36: SOT-23-5；逻辑类型:与门；通道数:1；工作电压:1.65V~5.5V；静态电流(Iq):10uA；传播延迟(tpd):4ns@5V,50pF | D36: 1 | E36: 0 | F36: =D36*$B$4+E36*$D$4 -> 1 | G36: U5 | I36: 深圳市德明电子贸易商城 | J36: =HYPERLINK("https://item.taobao.com/item.htm?id=902117985110","打开订单商品") -> 打开订单商品 | K36: SN74LVC1G08DBVR;5个全国包邮 | L36: 5 | M36: =ROUNDUP(F36/L36,0) -> 1 | N36: =HYPERLINK("https://www.lcsc.com/product-detail/C7666.html","查看工程型号") -> 查看工程型号 | O36: SN74LVC1G08DBVR / SOT-23-5 与门，按同页对应型号选项购买。
A37: 半导体 | B37: SN74LVC1G125DBVR-TP | C37: SOT-23-5；输入类型:-；工作电压:1.65V~5.5V；元件数:1；每个元件位数:-；灌电流(IOL):24mA；拉电流(IOH):24mA | D37: 1 | E37: 0 | F37: =D37*$B$4+E37*$D$4 -> 1 | G37: U6 | I37: 深圳市德明电子贸易商城 | J37: =HYPERLINK("https://item.taobao.com/item.htm?id=902117985110","打开订单商品") -> 打开订单商品 | K37: SN74LVC1G125DBVR;5个全国包邮 | L37: 5 | M37: =ROUNDUP(F37/L37,0) -> 1 | N37: =HYPERLINK("https://item.szlcsc.com/3597950.html","查看工程型号") -> 查看工程型号 | O37: 实际使用：SN74LVC1G125DBVR / SOT-23-5，5个包装。
A38: 半导体 | B38: SN74LVC1G126DBVR | C38: SOT-23-5；输入类型:-；工作电压:1.65V~5.5V；元件数:1；每个元件位数:1；灌电流(IOL):32mA；拉电流(IOH):32mA | D38: 1 | E38: 0 | F38: =D38*$B$4+E38*$D$4 -> 1 | G38: U7 | I38: 深圳市德明电子贸易商城 | J38: =HYPERLINK("https://item.taobao.com/item.htm?id=902117985110","打开订单商品") -> 打开订单商品 | K38: SN74LVC1G126DBVR;5个全国包邮 | L38: 5 | M38: =ROUNDUP(F38/L38,0) -> 1 | N38: =HYPERLINK("https://www.lcsc.com/product-detail/C7834.html","查看工程型号") -> 查看工程型号 | O38: 实际使用：SN74LVC1G126DBVR / SOT-23-5，5个包装。
A39: 半导体 | B39: AP63205WU-7 | C39: TSOT-23-6；功能类型:降压型；工作电压:3.8V~32V；输出电压:5V；输出电流:2A；输出类型:固定 | D39: 1 | E39: 0 | F39: =D39*$B$4+E39*$D$4 -> 1 | G39: U9 | I39: 深圳市远大芯程科技 | J39: =HYPERLINK("https://item.taobao.com/item.htm?id=969642590399","打开订单商品") -> 打开订单商品 | K39: AP63205WU-7 | L39: 1 | M39: =ROUNDUP(F39/L39,0) -> 1 | N39: =HYPERLINK("https://item.szlcsc.com/2162639.html","查看工程型号") -> 查看工程型号 | O39: AP63205WU-7，固定5V降压芯片，按对应完整型号购买。
A40: 半导体 | B40: LM5050MKX-1/NOPB | C40: TSOT-23-6；LM5050-1 5V 至 75V、400uA IQ ORing FET 控制器 | D40: 1 | E40: 0 | F40: =D40*$B$4+E40*$D$4 -> 1 | G40: U10 | I40: 深圳市安芯选电子 | J40: =HYPERLINK("https://item.taobao.com/item.htm?id=1013388982214","打开订单商品") -> 打开订单商品 | K40: SOT-23;LM5050MKX-1/NOPB 原装正品 | L40: 1 | M40: =ROUNDUP(F40/L40,0) -> 1 | N40: =HYPERLINK("https://www.lcsc.com/product-detail/C473393.html","查看工程型号") -> 查看工程型号 | O40: LM5050MKX-1/NOPB，按完整型号购买。
A41: 晶振 | B41: OT3EL89CJI-111YLC-12M | C41: SMD2520-4P；12MHz | D41: 1 | E41: 0 | F41: =D41*$B$4+E41*$D$4 -> 1 | G41: Y1 | I41: 深圳市晶诺源电子 | J41: =HYPERLINK("https://item.taobao.com/item.htm?id=944053669860","打开订单商品") -> 打开订单商品 | K41: 12MHZ 1.2V~3.36V宽压[高精度10PPM];SMD2520-4P CMOS输出 | L41: 1 | M41: =ROUNDUP(F41/L41,0) -> 1 | N41: =HYPERLINK("https://item.szlcsc.com/8414369.html","查看工程型号") -> 查看工程型号 | O41: 实际使用：12MHz、2520-4P、CMOS输出有源晶振，宽压1.2V~3.36V（订单标称）。
A42: 电容 | B42: CL21A475KAQNNNE | C42: 0805；4.7uF / ±10% / 25V / X5R | D42: 0 | E42: 2 | F42: =D42*$B$4+E42*$D$4 -> 2 | H42: C1, C3 | I42: 深圳市宏宸电子 | J42: =HYPERLINK("https://item.taobao.com/item.htm?id=977236759812","打开订单商品") -> 打开订单商品 | K42: 0805 4.7UF ±10% X7R;25V | L42: 1 | M42: =ROUNDUP(F42/L42,0) -> 2 | N42: =HYPERLINK("https://www.lcsc.com/product-detail/C1779.html","查看工程型号") -> 查看工程型号 | O42: 实际采购：0805 / 4.7uF / ±10% / 25V / X7R。
A43: 电容 | B43: CL10B104JB8NNNC | C43: 0603；100nF / ±5% / 50V / X7R | D43: 0 | E43: 6 | F43: =D43*$B$4+E43*$D$4 -> 6 | H43: C2, C4, C5, C7, C8, C10 | I43: 深圳市宏宸电子 | J43: =HYPERLINK("https://item.taobao.com/item.htm?id=731471380840","打开订单商品") -> 打开订单商品 | K43: 0603 100nF ±10% X7R;50V;100个 | L43: 100 | M43: =ROUNDUP(F43/L43,0) -> 1 | N43: =HYPERLINK("https://item.szlcsc.com/25192.html","查看工程型号") -> 查看工程型号 | O43: 实际采购：0603 / 100nF / ±10% / 50V / X7R。
A44: 电容 | B44: CL10A105KB8NNNC | C44: 0603；1uF / ±10% / 50V / X5R | D44: 0 | E44: 2 | F44: =D44*$B$4+E44*$D$4 -> 2 | H44: C6, C9 | I44: 深圳市宏宸电子 | J44: =HYPERLINK("https://item.taobao.com/item.htm?id=630712731066","打开订单商品") -> 打开订单商品 | K44: 0603 1uF ±10% X7R;50V | L44: 1 | M44: =ROUNDUP(F44/L44,0) -> 2 | N44: =HYPERLINK("https://item.szlcsc.com/16531.html","查看工程型号") -> 查看工程型号 | O44: 实际采购：0603 / 1uF / ±10% / 50V / X7R。
A45: 半导体 | B45: PESD5V0S1BA | C45: SOD-323；反向截止电压(Vrwm):5V@Max；最大钳位电压:10V；峰值脉冲电流(Ipp)@10/1000us:5A@8/20us；击穿电压:5.8V | D45: 0 | E45: 1 | F45: =D45*$B$4+E45*$D$4 -> 1 | H45: D1 | I45: 深圳市优信电子科技有限公司 | J45: =HYPERLINK("https://item.taobao.com/item.htm?id=891785167202","打开订单商品") -> 打开订单商品 | K45: 商品无选项，按商品标题完整型号购买 | L45: 1 | M45: =ROUNDUP(F45/L45,0) -> 1 | N45: =HYPERLINK("https://www.lcsc.com/product-detail/C330094.html","查看工程型号") -> 查看工程型号 | O45: PESD5V0S1BA / SOD-323 双向TVS，按商品完整型号购买。
A46: 半导体 | B46: 19-217/GHC-YR1S2/3T | C46: 0603；110mW | D46: 0 | E46: 1 | F46: =D46*$B$4+E46*$D$4 -> 1 | H46: D2 | I46: 泰辰电子 | J46: =HYPERLINK("https://item.taobao.com/item.htm?id=1025817117811","打开订单商品") -> 打开订单商品 | K46: 0603 蓝色=100个 | L46: 100 | M46: =ROUNDUP(F46/L46,0) -> 1 | N46: =HYPERLINK("https://www.lcsc.com/product-detail/Light-Emitting-Diodes-LED_Everlight-Elec-19-217-GHC-YR1S2-3T_C72043.html","查看工程型号") -> 查看工程型号 | O46: 实际采购：0603 蓝色LED，100个包装。
A47: 连接器 | B47: PZ254V-11-05P | C47: 插件,P=2.54mm；3A | D47: 0 | E47: 1 | F47: =D47*$B$4+E47*$D$4 -> 1 | H47: J2 | I47: zxin旗舰店 | J47: =HYPERLINK("https://item.taobao.com/item.htm?id=606816197525","打开订单商品") -> 打开订单商品 | K47: 1*5P直针 铜（30条） | L47: 30 | M47: =ROUNDUP(F47/L47,0) -> 1 | N47: =HYPERLINK("https://item.szlcsc.com/502960.html","查看工程型号") -> 查看工程型号 | O47: 1×5P / 2.54mm 直排针，用于SWD烧录口。
A48: 电阻 | B48: RC0603FR-07100KL | C48: 0603；100kΩ / ±1% / ±100ppm/℃ / 100mW | D48: 0 | E48: 1 | F48: =D48*$B$4+E48*$D$4 -> 1 | H48: R3 | I48: 深圳市永芯泰电子企业店 | J48: =HYPERLINK("https://item.taobao.com/item.htm?id=947267344247","打开订单商品") -> 打开订单商品 | K48: 100K;0603 1%（100个） | L48: 100 | M48: =ROUNDUP(F48/L48,0) -> 1 | N48: =HYPERLINK("https://item.szlcsc.com/15343.html","查看工程型号") -> 查看工程型号 | O48: 100kΩ / ±1% / 0603。
A49: 电阻 | B49: 0603WAF330JT5E | C49: 0603；33Ω / ±1% / ±100ppm/℃ / 100mW | D49: 0 | E49: 1 | F49: =D49*$B$4+E49*$D$4 -> 1 | H49: R6 | I49: 深圳市永芯泰电子企业店 | J49: =HYPERLINK("https://item.taobao.com/item.htm?id=947267344247","打开订单商品") -> 打开订单商品 | K49: 33R/33欧;0603 1%（100个） | L49: 100 | M49: =ROUNDUP(F49/L49,0) -> 1 | N49: =HYPERLINK("https://item.szlcsc.com/23867.html","查看工程型号") -> 查看工程型号 | O49: 33Ω / ±1% / 0603，用于IMU R6。
A50: 电阻 | B50: 0603WAF1001T5E | C50: 0603；1kΩ / ±1% / ±100ppm/℃ / 100mW | D50: 0 | E50: 1 | F50: =D50*$B$4+E50*$D$4 -> 1 | H50: R7 | I50: 深圳市永芯泰电子企业店 | J50: =HYPERLINK("https://item.taobao.com/item.htm?id=947267344247","打开订单商品") -> 打开订单商品 | K50: 1K;0603 1%（100个） | L50: 100 | M50: =ROUNDUP(F50/L50,0) -> 1 | N50: =HYPERLINK("https://item.szlcsc.com/21904.html","查看工程型号") -> 查看工程型号 | O50: 1kΩ / ±1% / 0603，八月备料订单。
A51: 半导体 | B51: STM32G031F8P6 | C51: TSSOP-20；CPU内核:ARM Cortex-M0+；CPU最大主频:64MHz；CPU位数:32 Bit | D51: 0 | E51: 1 | F51: =D51*$B$4+E51*$D$4 -> 1 | H51: U1 | I51: 深圳市新纶电子 | J51: =HYPERLINK("https://item.taobao.com/item.htm?id=726808419708","打开订单商品") -> 打开订单商品 | K51: 全新原装 | L51: 1 | M51: =ROUNDUP(F51/L51,0) -> 1 | N51: =HYPERLINK("https://item.szlcsc.com/549612.html","查看工程型号") -> 查看工程型号 | O51: STM32G031F8P6 / TSSOP-20，按商品完整型号购买。
A52: 半导体 | B52: LSM6DSV16XTR | C52: LGA-14(2.5x3)；传感器类型:IMU(加速度计+陀螺仪)；接口类型:I2C；SPI | D52: 0 | E52: 1 | F52: =D52*$B$4+E52*$D$4 -> 1 | H52: U2 | I52: 深圳市RTC电子 | J52: =HYPERLINK("https://item.taobao.com/item.htm?id=640391703111","打开订单商品") -> 打开订单商品 | K52: LSM6DSV16XTR | L52: 1 | M52: =ROUNDUP(F52/L52,0) -> 1 | N52: =HYPERLINK("https://item.szlcsc.com/5993815.html","查看工程型号") -> 查看工程型号 | O52: LSM6DSV16XTR / LGA-14，在多型号商品页选择 LSM6DSV16XTR。
A53: 半导体 | B53: TLV70433DBVR | C53: SOT-23-5；输出极性:正极；工作电压:24V；输出电压:3.3V；输出电流:150mA；电源纹波抑制比(PSRR):60dB@(100kHz)；输出类型:固定 | D53: 0 | E53: 1 | F53: =D53*$B$4+E53*$D$4 -> 1 | H53: U3 | I53: 深圳市恒芯科创电子 | J53: =HYPERLINK("https://item.taobao.com/item.htm?id=747094785928","打开订单商品") -> 打开订单商品 | K53: TLV70433DBVR | L53: 1 | M53: =ROUNDUP(F53/L53,0) -> 1 | N53: =HYPERLINK("https://www.lcsc.com/product-detail/C94917.html","查看工程型号") -> 查看工程型号 | O53: TLV70433DBVR / 3.3V / SOT-23-5。
A54: 半导体 | B54: SN74LVC2G125DCUR | C54: VSSOP-8；输入类型:-；工作电压:1.65V~5.5V；元件数:2；每个元件位数:1；灌电流(IOL):32mA；拉电流(IOH):32mA | D54: 0 | E54: 1 | F54: =D54*$B$4+E54*$D$4 -> 1 | H54: U4 | I54: 深圳市垚鑫电子科技 | J54: =HYPERLINK("https://item.taobao.com/item.htm?id=705642638300","打开订单商品") -> 打开订单商品 | K54: 商品无选项，按商品标题完整型号购买 | L54: 1 | M54: =ROUNDUP(F54/L54,0) -> 1 | N54: =HYPERLINK("https://www.lcsc.com/product-detail/C21404.html","查看工程型号") -> 查看工程型号 | O54: SN74LVC2G125DCUR / VSSOP-8，按商品完整型号购买。

Sheet HAT位号BOM
A2: HAT 位号 BOM
A3: 源：HAT-V5.epro2 / PCB2；84 个器件，工程原始属性保留。
A4: R33：采购0Ω / C21189，保留原工程属性。TH1可使用原村田PRG18BB101MB1RB，100Ω PTC / 0603。
A5: C8/C9 为 220pF（已修正）；C15 为 1206 / 10uF / 35V。
A6: 器件用量按实际位号统计，采购商品已在作者实机验证可用。
A7: 位号 | B7: 用途 / 位号原文 | C7: 工程完整型号 | D7: 工程立创料号 | E7: 工程封装 | F7: 工程关键参数 | G7: 当前采购规格 / 订单款式 | H7: 订单商品链接 | I7: 工程BOM型号链接 | J7: 用料说明 | K7: 工程来源
A8: C1 | B8: 1uF / left AC coupling | C8: CC0603KRX5R9BB105 | D8: C128624 | E8: 0603 | F8: 1uF / ±10% / 50V / X5R | G8: 0603 1uF ±10% X7R;50V | H8: =HYPERLINK("https://item.taobao.com/item.htm?id=630712731066","打开订单商品") -> 打开订单商品 | I8: =HYPERLINK("https://www.lcsc.com/product-detail/C128624.html","查看工程型号") -> 查看工程型号 | J8: 实际采购：0603 / 1uF / ±10% / 50V / X7R。 | K8: HAT-V5.epro2 / PCB2
A9: C2 | B9: 1uF / right AC coupling | C9: CC0603KRX5R9BB105 | D9: C128624 | E9: 0603 | F9: 1uF / ±10% / 50V / X5R | G9: 0603 1uF ±10% X7R;50V | H9: =HYPERLINK("https://item.taobao.com/item.htm?id=630712731066","打开订单商品") -> 打开订单商品 | I9: =HYPERLINK("https://www.lcsc.com/product-detail/C128624.html","查看工程型号") -> 查看工程型号 | J9: 实际采购：0603 / 1uF / ±10% / 50V / X7R。 | K9: HAT-V5.epro2 / PCB2
A10: C3 | B10: 1uF / VREF | C10: CC0603KRX5R9BB105 | D10: C128624 | E10: 0603 | F10: 1uF / ±10% / 50V / X5R | G10: 0603 1uF ±10% X7R;50V | H10: =HYPERLINK("https://item.taobao.com/item.htm?id=630712731066","打开订单商品") -> 打开订单商品 | I10: =HYPERLINK("https://www.lcsc.com/product-detail/C128624.html","查看工程型号") -> 查看工程型号 | J10: 实际采购：0603 / 1uF / ±10% / 50V / X7R。 | K10: HAT-V5.epro2 / PCB2
A11: C4 | B11: 1uF | C11: CC0603KRX5R9BB105 | D11: C128624 | E11: 0603 | F11: 1uF / ±10% / 50V / X5R | G11: 0603 1uF ±10% X7R;50V | H11: =HYPERLINK("https://item.taobao.com/item.htm?id=630712731066","打开订单商品") -> 打开订单商品 | I11: =HYPERLINK("https://www.lcsc.com/product-detail/C128624.html","查看工程型号") -> 查看工程型号 | J11: 实际采购：0603 / 1uF / ±10% / 50V / X7R。 | K11: HAT-V5.epro2 / PCB2
A12: C5 | B12: 10uF | C12: C1608X5R1A106KT000E | D12: C76608 | E12: 0603 | F12: 10uF / ±10% / 10V / X5R | G12: 0603 10uF ±10% X5R;10V | H12: =HYPERLINK("https://item.taobao.com/item.htm?id=630712731066","打开订单商品") -> 打开订单商品 | I12: =HYPERLINK("https://item.szlcsc.com/77735.html","查看工程型号") -> 查看工程型号 | J12: 实际采购：0603 / 10uF / ±10% / 10V / X5R。 | K12: HAT-V5.epro2 / PCB2
A13: C6 | B13: 1uF | C13: CC0603KRX5R9BB105 | D13: C128624 | E13: 0603 | F13: 1uF / ±10% / 50V / X5R | G13: 0603 1uF ±10% X7R;50V | H13: =HYPERLINK("https://item.taobao.com/item.htm?id=630712731066","打开订单商品") -> 打开订单商品 | I13: =HYPERLINK("https://www.lcsc.com/product-detail/C128624.html","查看工程型号") -> 查看工程型号 | J13: 实际采购：0603 / 1uF / ±10% / 50V / X7R。 | K13: HAT-V5.epro2 / PCB2
A14: C7 | B14: 10uF | C14: C1608X5R1A106KT000E | D14: C76608 | E14: 0603 | F14: 10uF / ±10% / 10V / X5R | G14: 0603 10uF ±10% X5R;10V | H14: =HYPERLINK("https://item.taobao.com/item.htm?id=630712731066","打开订单商品") -> 打开订单商品 | I14: =HYPERLINK("https://item.szlcsc.com/77735.html","查看工程型号") -> 查看工程型号 | J14: 实际采购：0603 / 10uF / ±10% / 10V / X5R。 | K14: HAT-V5.epro2 / PCB2
A15: C8 | B15: 0603CG221J500NT | C15: 0603CG221J500NT | D15: C156398 | E15: 0603 | F15: 220pF / ±5% / 50V / C0G | G15: 0603 220pF ±5% NPO/COG;50V;100个 | H15: =HYPERLINK("https://item.taobao.com/item.htm?id=1005108810412","打开订单商品") -> 打开订单商品 | I15: =HYPERLINK("https://item.szlcsc.com/167743.html","查看工程型号") -> 查看工程型号 | J15: 选 220pF、50V、C0G(NPO)、±5%、0603；同页其他容量分别选购。 | K15: HAT-V5.epro2 / PCB2
A16: C9 | B16: 0603CG221J500NT | C16: 0603CG221J500NT | D16: C156398 | E16: 0603 | F16: 220pF / ±5% / 50V / C0G | G16: 0603 220pF ±5% NPO/COG;50V;100个 | H16: =HYPERLINK("https://item.taobao.com/item.htm?id=1005108810412","打开订单商品") -> 打开订单商品 | I16: =HYPERLINK("https://item.szlcsc.com/167743.html","查看工程型号") -> 查看工程型号 | J16: 选 220pF、50V、C0G(NPO)、±5%、0603；同页其他容量分别选购。 | K16: HAT-V5.epro2 / PCB2
A17: C10 | B17: 1uF / onboard MIC coupling | C17: CC0603KRX5R9BB105 | D17: C128624 | E17: 0603 | F17: 1uF / ±10% / 50V / X5R | G17: 0603 1uF ±10% X7R;50V | H17: =HYPERLINK("https://item.taobao.com/item.htm?id=630712731066","打开订单商品") -> 打开订单商品 | I17: =HYPERLINK("https://www.lcsc.com/product-detail/C128624.html","查看工程型号") -> 查看工程型号 | J17: 实际采购：0603 / 1uF / ±10% / 50V / X7R。 | K17: HAT-V5.epro2 / PCB2
A18: C11 | B18: 100nF / onboard MIC | C18: CC0603KRX7R9BB104 | D18: C14663 | E18: 0603 | F18: 100nF / ±10% / 50V / X7R | G18: 0603 100nF ±10% X7R;50V;100个 | H18: =HYPERLINK("https://item.taobao.com/item.htm?id=731471380840","打开订单商品") -> 打开订单商品 | I18: =HYPERLINK("https://item.szlcsc.com/15331.html","查看工程型号") -> 查看工程型号 | J18: 实际采购：0603 / 100nF / ±10% / 50V / X7R。 | K18: HAT-V5.epro2 / PCB2
A19: C12 | B19: 10uF / 1V8 | C19: C1608X5R1A106KT000E | D19: C76608 | E19: 0603 | F19: 10uF / ±10% / 10V / X5R | G19: 0603 10uF ±10% X5R;10V | H19: =HYPERLINK("https://item.taobao.com/item.htm?id=630712731066","打开订单商品") -> 打开订单商品 | I19: =HYPERLINK("https://item.szlcsc.com/77735.html","查看工程型号") -> 查看工程型号 | J19: 实际采购：0603 / 10uF / ±10% / 10V / X5R。 | K19: HAT-V5.epro2 / PCB2
A20: C13 | B20: 10uF / 3V3 | C20: C1608X5R1A106KT000E | D20: C76608 | E20: 0603 | F20: 10uF / ±10% / 10V / X5R | G20: 0603 10uF ±10% X5R;10V | H20: =HYPERLINK("https://item.taobao.com/item.htm?id=630712731066","打开订单商品") -> 打开订单商品 | I20: =HYPERLINK("https://item.szlcsc.com/77735.html","查看工程型号") -> 查看工程型号 | J20: 实际采购：0603 / 10uF / ±10% / 10V / X5R。 | K20: HAT-V5.epro2 / PCB2
A21: C14 | B21: 100nF / oscillator | C21: CC0603KRX7R9BB104 | D21: C14663 | E21: 0603 | F21: 100nF / ±10% / 50V / X7R | G21: 0603 100nF ±10% X7R;50V;100个 | H21: =HYPERLINK("https://item.taobao.com/item.htm?id=731471380840","打开订单商品") -> 打开订单商品 | I21: =HYPERLINK("https://item.szlcsc.com/15331.html","查看工程型号") -> 查看工程型号 | J21: 实际采购：0603 / 100nF / ±10% / 50V / X7R。 | K21: HAT-V5.epro2 / PCB2
A22: C15 | B22: C3216X7R1V106KT000E | C22: C3216X7R1V106KT000E | D22: C76666 | E22: 1206 | F22: 10uF / ±10% / 35V / X7R | G22: 1206 10UF ±10% X7R;35V | H22: =HYPERLINK("https://item.taobao.com/item.htm?id=730407108775","打开订单商品") -> 打开订单商品 | I22: =HYPERLINK("https://item.szlcsc.com/77793.html","查看工程型号") -> 查看工程型号 | J22: C15 使用 1206、10uF、35V、X7R 款式。 | K22: HAT-V5.epro2 / PCB2
A23: C16 | B23: 100nF / U5 | C23: CC0603KRX7R9BB104 | D23: C14663 | E23: 0603 | F23: 100nF / ±10% / 50V / X7R | G23: 0603 100nF ±10% X7R;50V;100个 | H23: =HYPERLINK("https://item.taobao.com/item.htm?id=731471380840","打开订单商品") -> 打开订单商品 | I23: =HYPERLINK("https://item.szlcsc.com/15331.html","查看工程型号") -> 查看工程型号 | J23: 实际采购：0603 / 100nF / ±10% / 50V / X7R。 | K23: HAT-V5.epro2 / PCB2
A24: C17 | B24: 100nF / U6 | C24: CC0603KRX7R9BB104 | D24: C14663 | E24: 0603 | F24: 100nF / ±10% / 50V / X7R | G24: 0603 100nF ±10% X7R;50V;100个 | H24: =HYPERLINK("https://item.taobao.com/item.htm?id=731471380840","打开订单商品") -> 打开订单商品 | I24: =HYPERLINK("https://item.szlcsc.com/15331.html","查看工程型号") -> 查看工程型号 | J24: 实际采购：0603 / 100nF / ±10% / 50V / X7R。 | K24: HAT-V5.epro2 / PCB2
A25: C18 | B25: 100nF / U7 | C25: CC0603KRX7R9BB104 | D25: C14663 | E25: 0603 | F25: 100nF / ±10% / 50V / X7R | G25: 0603 100nF ±10% X7R;50V;100个 | H25: =HYPERLINK("https://item.taobao.com/item.htm?id=731471380840","打开订单商品") -> 打开订单商品 | I25: =HYPERLINK("https://item.szlcsc.com/15331.html","查看工程型号") -> 查看工程型号 | J25: 实际采购：0603 / 100nF / ±10% / 50V / X7R。 | K25: HAT-V5.epro2 / PCB2
A26: C20 | B26: 100nF 50V / bootstrap | C26: CC0603KRX7R9BB104 | D26: C14663 | E26: 0603 | F26: 100nF / ±10% / 50V / X7R | G26: 0603 100nF ±10% X7R;50V;100个 | H26: =HYPERLINK("https://item.taobao.com/item.htm?id=731471380840","打开订单商品") -> 打开订单商品 | I26: =HYPERLINK("https://item.szlcsc.com/15331.html","查看工程型号") -> 查看工程型号 | J26: 实际采购：0603 / 100nF / ±10% / 50V / X7R。 | K26: HAT-V5.epro2 / PCB2
A27: C21 | B27: 22uF 10V X5R | C27: GRM188R61A226ME15D | D27: C84419 | E27: 0603 | F27: 22uF / ±20% / 10V / X5R | G27: 22UF 226K 10% X5R;10V;0603=100个 | H27: =HYPERLINK("https://item.taobao.com/item.htm?id=993202872551","打开订单商品") -> 打开订单商品 | I27: =HYPERLINK("https://item.szlcsc.com/85589.html","查看工程型号") -> 查看工程型号 | J27: 实际采购：0603 / 22uF / ±10% / 10V / X5R。 | K27: HAT-V5.epro2 / PCB2
A28: C22 | B28: 22uF 10V X5R | C28: GRM188R61A226ME15D | D28: C84419 | E28: 0603 | F28: 22uF / ±20% / 10V / X5R | G28: 22UF 226K 10% X5R;10V;0603=100个 | H28: =HYPERLINK("https://item.taobao.com/item.htm?id=993202872551","打开订单商品") -> 打开订单商品 | I28: =HYPERLINK("https://item.szlcsc.com/85589.html","查看工程型号") -> 查看工程型号 | J28: 实际采购：0603 / 22uF / ±10% / 10V / X5R。 | K28: HAT-V5.epro2 / PCB2
A29: C26 | B29: 100nF / 1V8 | C29: CC0603KRX7R9BB104 | D29: C14663 | E29: 0603 | F29: 100nF / ±10% / 50V / X7R | G29: 0603 100nF ±10% X7R;50V;100个 | H29: =HYPERLINK("https://item.taobao.com/item.htm?id=731471380840","打开订单商品") -> 打开订单商品 | I29: =HYPERLINK("https://item.szlcsc.com/15331.html","查看工程型号") -> 查看工程型号 | J29: 实际采购：0603 / 100nF / ±10% / 50V / X7R。 | K29: HAT-V5.epro2 / PCB2
A30: C27 | B30: 1uF | C30: CC0603KRX5R9BB105 | D30: C128624 | E30: 0603 | F30: 1uF / ±10% / 50V / X5R | G30: 0603 1uF ±10% X7R;50V | H30: =HYPERLINK("https://item.taobao.com/item.htm?id=630712731066","打开订单商品") -> 打开订单商品 | I30: =HYPERLINK("https://www.lcsc.com/product-detail/C128624.html","查看工程型号") -> 查看工程型号 | J30: 实际采购：0603 / 1uF / ±10% / 50V / X7R。 | K30: HAT-V5.epro2 / PCB2
A31: C28 | B31: 100nF | C31: CC0603KRX7R9BB104 | D31: C14663 | E31: 0603 | F31: 100nF / ±10% / 50V / X7R | G31: 0603 100nF ±10% X7R;50V;100个 | H31: =HYPERLINK("https://item.taobao.com/item.htm?id=731471380840","打开订单商品") -> 打开订单商品 | I31: =HYPERLINK("https://item.szlcsc.com/15331.html","查看工程型号") -> 查看工程型号 | J31: 实际采购：0603 / 100nF / ±10% / 50V / X7R。 | K31: HAT-V5.epro2 / PCB2
A32: C29 | B32: 1uF | C32: CC0603KRX5R9BB105 | D32: C128624 | E32: 0603 | F32: 1uF / ±10% / 50V / X5R | G32: 0603 1uF ±10% X7R;50V | H32: =HYPERLINK("https://item.taobao.com/item.htm?id=630712731066","打开订单商品") -> 打开订单商品 | I32: =HYPERLINK("https://www.lcsc.com/product-detail/C128624.html","查看工程型号") -> 查看工程型号 | J32: 实际采购：0603 / 1uF / ±10% / 50V / X7R。 | K32: HAT-V5.epro2 / PCB2
A33: C30 | B33: 100nF | C33: CC0603KRX7R9BB104 | D33: C14663 | E33: 0603 | F33: 100nF / ±10% / 50V / X7R | G33: 0603 100nF ±10% X7R;50V;100个 | H33: =HYPERLINK("https://item.taobao.com/item.htm?id=731471380840","打开订单商品") -> 打开订单商品 | I33: =HYPERLINK("https://item.szlcsc.com/15331.html","查看工程型号") -> 查看工程型号 | J33: 实际采购：0603 / 100nF / ±10% / 50V / X7R。 | K33: HAT-V5.epro2 / PCB2
A34: C31 | B34: 1uF | C34: CC0603KRX5R9BB105 | D34: C128624 | E34: 0603 | F34: 1uF / ±10% / 50V / X5R | G34: 0603 1uF ±10% X7R;50V | H34: =HYPERLINK("https://item.taobao.com/item.htm?id=630712731066","打开订单商品") -> 打开订单商品 | I34: =HYPERLINK("https://www.lcsc.com/product-detail/C128624.html","查看工程型号") -> 查看工程型号 | J34: 实际采购：0603 / 1uF / ±10% / 50V / X7R。 | K34: HAT-V5.epro2 / PCB2
A35: C32 | B35: 100nF | C35: CC0603KRX7R9BB104 | D35: C14663 | E35: 0603 | F35: 100nF / ±10% / 50V / X7R | G35: 0603 100nF ±10% X7R;50V;100个 | H35: =HYPERLINK("https://item.taobao.com/item.htm?id=731471380840","打开订单商品") -> 打开订单商品 | I35: =HYPERLINK("https://item.szlcsc.com/15331.html","查看工程型号") -> 查看工程型号 | J35: 实际采购：0603 / 100nF / ±10% / 50V / X7R。 | K35: HAT-V5.epro2 / PCB2
A36: C33 | B36: 1uF | C36: CC0603KRX5R9BB105 | D36: C128624 | E36: 0603 | F36: 1uF / ±10% / 50V / X5R | G36: 0603 1uF ±10% X7R;50V | H36: =HYPERLINK("https://item.taobao.com/item.htm?id=630712731066","打开订单商品") -> 打开订单商品 | I36: =HYPERLINK("https://www.lcsc.com/product-detail/C128624.html","查看工程型号") -> 查看工程型号 | J36: 实际采购：0603 / 1uF / ±10% / 50V / X7R。 | K36: HAT-V5.epro2 / PCB2
A37: C34 | B37: 10nF | C37: CC0603KRX7R9BB103 | D37: C100042 | E37: 0603 | F37: 10nF / ±10% / 50V / X7R | G37: 0603 10NF 50V 10% 100个 | H37: =HYPERLINK("https://item.taobao.com/item.htm?id=610558214623","打开订单商品") -> 打开订单商品 | I37: =HYPERLINK("https://item.szlcsc.com/101256.html","查看工程型号") -> 查看工程型号 | J37: 实际采购：0603 / 10nF / ±10% / 50V / X7R。 | K37: HAT-V5.epro2 / PCB2
A38: C35 | B38: 1uF | C38: CC0603KRX5R9BB105 | D38: C128624 | E38: 0603 | F38: 1uF / ±10% / 50V / X5R | G38: 0603 1uF ±10% X7R;50V | H38: =HYPERLINK("https://item.taobao.com/item.htm?id=630712731066","打开订单商品") -> 打开订单商品 | I38: =HYPERLINK("https://www.lcsc.com/product-detail/C128624.html","查看工程型号") -> 查看工程型号 | J38: 实际采购：0603 / 1uF / ±10% / 50V / X7R。 | K38: HAT-V5.epro2 / PCB2
A39: C36 | B39: 100nF | C39: CC0603KRX7R9BB104 | D39: C14663 | E39: 0603 | F39: 100nF / ±10% / 50V / X7R | G39: 0603 100nF ±10% X7R;50V;100个 | H39: =HYPERLINK("https://item.taobao.com/item.htm?id=731471380840","打开订单商品") -> 打开订单商品 | I39: =HYPERLINK("https://item.szlcsc.com/15331.html","查看工程型号") -> 查看工程型号 | J39: 实际采购：0603 / 100nF / ±10% / 50V / X7R。 | K39: HAT-V5.epro2 / PCB2
A40: C37 | B40: 10uF / 3V3 | C40: C1608X5R1A106KT000E | D40: C76608 | E40: 0603 | F40: 10uF / ±10% / 10V / X5R | G40: 0603 10uF ±10% X5R;10V | H40: =HYPERLINK("https://item.taobao.com/item.htm?id=630712731066","打开订单商品") -> 打开订单商品 | I40: =HYPERLINK("https://item.szlcsc.com/77735.html","查看工程型号") -> 查看工程型号 | J40: 实际采购：0603 / 10uF / ±10% / 10V / X5R。 | K40: HAT-V5.epro2 / PCB2
A41: C38 | B41: 100nF / codec reset | C41: CC0603KRX7R9BB104 | D41: C14663 | E41: 0603 | F41: 100nF / ±10% / 50V / X7R | G41: 0603 100nF ±10% X7R;50V;100个 | H41: =HYPERLINK("https://item.taobao.com/item.htm?id=731471380840","打开订单商品") -> 打开订单商品 | I41: =HYPERLINK("https://item.szlcsc.com/15331.html","查看工程型号") -> 查看工程型号 | J41: 实际采购：0603 / 100nF / ±10% / 50V / X7R。 | K41: HAT-V5.epro2 / PCB2
A42: C39 | B42: 100nF 50V | C42: CC0603KRX7R9BB104 | D42: C14663 | E42: 0603 | F42: 100nF / ±10% / 50V / X7R | G42: 0603 100nF ±10% X7R;50V;100个 | H42: =HYPERLINK("https://item.taobao.com/item.htm?id=731471380840","打开订单商品") -> 打开订单商品 | I42: =HYPERLINK("https://item.szlcsc.com/15331.html","查看工程型号") -> 查看工程型号 | J42: 实际采购：0603 / 100nF / ±10% / 50V / X7R。 | K42: HAT-V5.epro2 / PCB2
A43: C40 | B43: 1uF / MIC R coupling | C43: CC0603KRX5R9BB105 | D43: C128624 | E43: 0603 | F43: 1uF / ±10% / 50V / X5R | G43: 0603 1uF ±10% X7R;50V | H43: =HYPERLINK("https://item.taobao.com/item.htm?id=630712731066","打开订单商品") -> 打开订单商品 | I43: =HYPERLINK("https://www.lcsc.com/product-detail/C128624.html","查看工程型号") -> 查看工程型号 | J43: 实际采购：0603 / 1uF / ±10% / 50V / X7R。 | K43: HAT-V5.epro2 / PCB2
A44: C41 | B44: 1uF / MIC L coupling | C44: CC0603KRX5R9BB105 | D44: C128624 | E44: 0603 | F44: 1uF / ±10% / 50V / X5R | G44: 0603 1uF ±10% X7R;50V | H44: =HYPERLINK("https://item.taobao.com/item.htm?id=630712731066","打开订单商品") -> 打开订单商品 | I44: =HYPERLINK("https://www.lcsc.com/product-detail/C128624.html","查看工程型号") -> 查看工程型号 | J44: 实际采购：0603 / 1uF / ±10% / 50V / X7R。 | K44: HAT-V5.epro2 / PCB2
A45: C42 | B45: 1uF / MIC supply | C45: CC0603KRX5R9BB105 | D45: C128624 | E45: 0603 | F45: 1uF / ±10% / 50V / X5R | G45: 0603 1uF ±10% X7R;50V | H45: =HYPERLINK("https://item.taobao.com/item.htm?id=630712731066","打开订单商品") -> 打开订单商品 | I45: =HYPERLINK("https://www.lcsc.com/product-detail/C128624.html","查看工程型号") -> 查看工程型号 | J45: 实际采购：0603 / 1uF / ±10% / 50V / X7R。 | K45: HAT-V5.epro2 / PCB2
A46: C43 | B46: 1uF / MIC supply | C46: CC0603KRX5R9BB105 | D46: C128624 | E46: 0603 | F46: 1uF / ±10% / 50V / X5R | G46: 0603 1uF ±10% X7R;50V | H46: =HYPERLINK("https://item.taobao.com/item.htm?id=630712731066","打开订单商品") -> 打开订单商品 | I46: =HYPERLINK("https://www.lcsc.com/product-detail/C128624.html","查看工程型号") -> 查看工程型号 | J46: 实际采购：0603 / 1uF / ±10% / 50V / X7R。 | K46: HAT-V5.epro2 / PCB2
A47: D1 | B47: BAT54SW / diode 1 used | C47: BAT54SW,115 | D47: C78606 | E47: SOT-323 | F47: 二极管配置:1对串联式；正向压降(Vf):800mV@100mA；直流反向耐压(Vr):30V；整流电流:200mA | G47: BAT54SW 印字44t（20只） | H47: =HYPERLINK("https://item.taobao.com/item.htm?id=793455311175","打开订单商品") -> 打开订单商品 | I47: =HYPERLINK("https://item.szlcsc.com/79742.html","查看工程型号") -> 查看工程型号 | J47: 选择 BAT54SW / SOT-323 款式。 | K47: HAT-V5.epro2 / PCB2
A48: D4 | B48: 5V1 / bus clamp | C48: BZT52C5V1S-7-F | D48: C151348 | E48: SOD-323 | F48: 二极管配置:1个独立式；稳压值(标称值):5.1V；稳压值(范围值):4.8V~5.4V；耗散功率(Pd):200mW | G48: BZT52C5V1S W8 SOD-323 (50个) | H48: =HYPERLINK("https://item.taobao.com/item.htm?id=943185002457","打开订单商品") -> 打开订单商品 | I48: =HYPERLINK("https://item.szlcsc.com/162688.html","查看工程型号") -> 查看工程型号 | J48: 选择 BZT52C5V1S / 5.1V / SOD-323 款式。 | K48: HAT-V5.epro2 / PCB2
A49: FB1 | B49: 600R@100MHz 1.3A | C49: BLM18KG601SN1D | D49: C85833 | E49: 0603 | F49: ±25% / 600Ω@100MHz / 1.3A | G49: 0603_600R_1.3A_±25%【100只】 | H49: =HYPERLINK("https://item.taobao.com/item.htm?id=931081429973","打开订单商品") -> 打开订单商品 | I49: =HYPERLINK("https://item.szlcsc.com/87009.html","查看工程型号") -> 查看工程型号 | J49: 实际采购：0603 / 600Ω@100MHz / 1.3A / ±25%。 | K49: HAT-V5.epro2 / PCB2
A50: FB2 | B50: 120R@100MHz 2A | C50: PE-0603PFB121ST | D50: C2661472 | E50: 0603 | F50: ±25% / 120Ω@100MHz / 2A | G50: 0603_120R_2A_±25%【100只】 | H50: =HYPERLINK("https://item.taobao.com/item.htm?id=931081429973","打开订单商品") -> 打开订单商品 | I50: =HYPERLINK("https://item.szlcsc.com/2753383.html","查看工程型号") -> 查看工程型号 | J50: 实际采购：0603 / 120Ω@100MHz / 2A / ±25%。 | K50: HAT-V5.epro2 / PCB2
A51: FB3 | B51: 120R@100MHz 2A | C51: PE-0603PFB121ST | D51: C2661472 | E51: 0603 | F51: ±25% / 120Ω@100MHz / 2A | G51: 0603_120R_2A_±25%【100只】 | H51: =HYPERLINK("https://item.taobao.com/item.htm?id=931081429973","打开订单商品") -> 打开订单商品 | I51: =HYPERLINK("https://item.szlcsc.com/2753383.html","查看工程型号") -> 查看工程型号 | J51: 实际采购：0603 / 120Ω@100MHz / 2A / ±25%。 | K51: HAT-V5.epro2 / PCB2
A52: J1 | B52: SPK R / JST-EH 2P | C52: B2B-EH-A(LF)(SN) | D52: C160262 | E52: 插件,P=2.5mm | F52: 250V / 3A | G52: EH2.5MM 2P直针座（50个） | H52: =HYPERLINK("https://item.taobao.com/item.htm?id=832569969546","打开订单商品") -> 打开订单商品 | I52: =HYPERLINK("https://item.szlcsc.com/171642.html","查看工程型号") -> 查看工程型号 | J52: EH 2P 直针座；按 EH2.5MM 2P 直针座选项购买。 | K52: HAT-V5.epro2 / PCB2
A53: J2 | B53: MIC L / JST-EH 2P | C53: B2B-EH-A(LF)(SN) | D53: C160262 | E53: 插件,P=2.5mm | F53: 250V / 3A | G53: EH2.5MM 2P直针座（50个） | H53: =HYPERLINK("https://item.taobao.com/item.htm?id=832569969546","打开订单商品") -> 打开订单商品 | I53: =HYPERLINK("https://item.szlcsc.com/171642.html","查看工程型号") -> 查看工程型号 | J53: EH 2P 直针座；按 EH2.5MM 2P 直针座选项购买。 | K53: HAT-V5.epro2 / PCB2
A54: J4 | B54: FH-00339 stock pins / Zero pair-map / bottom | C54: FH-00339 | D54: C2685112 | E54: SMD,P=2.54mm | F54: 3A | G54: 2*20P 贴片排母【2个】 | H54: =HYPERLINK("https://item.taobao.com/item.htm?id=533725557959","打开订单商品") -> 打开订单商品 | I54: =HYPERLINK("https://item.szlcsc.com/2784386.html","查看工程型号") -> 查看工程型号 | J54: 双排 2×20P、2.54mm、贴片排母，安装在 HAT 底面。 | K54: HAT-V5.epro2 / PCB2
A55: J5 | B55: ToF / Qwiic / pad 0 GND | C55: BM04B-SRSS-TB(LF)(SN) | D55: C160390 | E55: SMD,P=1mm | F55: 50V / 1A | G55: 4P立贴（15个） | H55: =HYPERLINK("https://item.taobao.com/item.htm?id=920058690376","打开订单商品") -> 打开订单商品 | I55: =HYPERLINK("https://item.szlcsc.com/171770.html","查看工程型号") -> 查看工程型号 | J55: SH1.0 / 4P / 立贴，按“4P立贴（15个）”选项购买。 | K55: HAT-V5.epro2 / PCB2
A56: J9 | B56: MIC R / JST-EH 2P | C56: B2B-EH-A(LF)(SN) | D56: C160262 | E56: 插件,P=2.5mm | F56: 250V / 3A | G56: EH2.5MM 2P直针座（50个） | H56: =HYPERLINK("https://item.taobao.com/item.htm?id=832569969546","打开订单商品") -> 打开订单商品 | I56: =HYPERLINK("https://item.szlcsc.com/171642.html","查看工程型号") -> 查看工程型号 | J56: EH 2P 直针座；按 EH2.5MM 2P 直针座选项购买。 | K56: HAT-V5.epro2 / PCB2
A57: J13 | B57: Dynamixel TTL 3P | C57: B3B-EH-A(LF)(SN) | D57: C160259 | E57: 插件,P=2.5mm | F57: 250V / 3A | G57: EH2.5MM 3P直针座（50个） | H57: =HYPERLINK("https://item.taobao.com/item.htm?id=832569969546","打开订单商品") -> 打开订单商品 | I57: =HYPERLINK("https://item.szlcsc.com/171639.html","查看工程型号") -> 查看工程型号 | J57: EH 3P 直针座，HAT 两只、IMU 一只。 | K57: HAT-V5.epro2 / PCB2
A58: J14 | B58: Dynamixel TTL 3P | C58: B3B-EH-A(LF)(SN) | D58: C160259 | E58: 插件,P=2.5mm | F58: 250V / 3A | G58: EH2.5MM 3P直针座（50个） | H58: =HYPERLINK("https://item.taobao.com/item.htm?id=832569969546","打开订单商品") -> 打开订单商品 | I58: =HYPERLINK("https://item.szlcsc.com/171639.html","查看工程型号") -> 查看工程型号 | J58: EH 3P 直针座，HAT 两只、IMU 一只。 | K58: HAT-V5.epro2 / PCB2
A59: L4 | B59: 6.8uH / 3A / Isat 4.3A | C59: SWPA6045S6R8MT | D59: C57254 | E59: SMD,6x6mm | F59: 6.8uH / ±20% / 3A | G59: 合金0630 6.8UH 印6R8 10个 6A 一体 | H59: =HYPERLINK("https://item.taobao.com/item.htm?id=598174251748","打开订单商品") -> 打开订单商品 | I59: =HYPERLINK("https://item.szlcsc.com/58286.html","查看工程型号") -> 查看工程型号 | J59: 实际使用：合金0630、6.8uH、6A一体成型电感（订单标称）。 | K59: HAT-V5.epro2 / PCB2
A60: MK1 | B60: Onboard analog MEMS MIC | C60: LMA2718T421-OA5-2 | D60: C7587901 | E60: SMD-4P,2.8x1.9mm | F60: 指向性:全指向；信噪比:55dB；灵敏度:-42dB；阻抗:300Ω | G60: 2718 上进音 硅麦克风【2个】 | H60: =HYPERLINK("https://item.taobao.com/item.htm?id=996702312391","打开订单商品") -> 打开订单商品 | I60: =HYPERLINK("https://item.szlcsc.com/8705873.html","查看工程型号") -> 查看工程型号 | J60: 实际使用：2718 上进音模拟 MEMS 麦克风，按“2718 上进音 硅麦克风【2个】”购买。 | K60: HAT-V5.epro2 / PCB2
A61: Q1 | B61: MMBT3906 / direction | C61: MMBT3906 | D61: C727128 | E61: SOT-23 | F61: 晶体管类型:PNP；集电极电流(Ic):200mA；集射极击穿电压(Vceo):40V；耗散功率(Pd):200mW；直流电流增益(hFE):100@10mA,1V | G61: MMBT3906 丝印2A SOT-23(50个) | H61: =HYPERLINK("https://item.taobao.com/item.htm?id=944306254140","打开订单商品") -> 打开订单商品 | I61: =HYPERLINK("https://item.szlcsc.com/774233.html","查看工程型号") -> 查看工程型号 | J61: 选择 MMBT3906 / PNP / SOT-23 款式。 | K61: HAT-V5.epro2 / PCB2
A62: Q2 | B62: SI2312 / ideal diode MOS | C62: SI2312CDS-T1-GE3 | D62: C142518 | E62: SOT-23 | F62: 数量:1个N沟道；漏源电压(Vdss):20V；连续漏极电流(Id):6A；导通电阻(RDS(on)):41.4mΩ@1.8V,5.6A；耗散功率(Pd):2.1W；阈值电压(Vgs(th)):1V@250uA | G62: SI2312DS（AE9T）N沟道（20只） | H62: =HYPERLINK("https://item.taobao.com/item.htm?id=909264246006","打开订单商品") -> 打开订单商品 | I62: =HYPERLINK("https://item.szlcsc.com/153849.html","查看工程型号") -> 查看工程型号 | J62: 实际使用：SI2312DS（AE9T）N沟道，20只包装。 | K62: HAT-V5.epro2 / PCB2
A63: R1 | B63: 10k / INL | C63: RC0603FR-0710KL | D63: C98220 | E63: 0603 | F63: 10kΩ / ±1% / ±100ppm/℃ / 100mW | G63: 10K;0603 1%（100个） | H63: =HYPERLINK("https://item.taobao.com/item.htm?id=947267344247","打开订单商品") -> 打开订单商品 | I63: =HYPERLINK("https://item.szlcsc.com/99429.html","查看工程型号") -> 查看工程型号 | J63: 10kΩ / ±1% / 0603；HAT 十二只、IMU 三只。 | K63: HAT-V5.epro2 / PCB2
A64: R2 | B64: 10k / INR | C64: RC0603FR-0710KL | D64: C98220 | E64: 0603 | F64: 10kΩ / ±1% / ±100ppm/℃ / 100mW | G64: 10K;0603 1%（100个） | H64: =HYPERLINK("https://item.taobao.com/item.htm?id=947267344247","打开订单商品") -> 打开订单商品 | I64: =HYPERLINK("https://item.szlcsc.com/99429.html","查看工程型号") -> 查看工程型号 | J64: 10kΩ / ±1% / 0603；HAT 十二只、IMU 三只。 | K64: HAT-V5.epro2 / PCB2
A65: R3 | B65: 0R / SHDN high | C65: 0603WAF0000T5E | D65: C21189 | E65: 0603 | F65: 0Ω / ±1% / - / 100mW | G65: 0R/0欧;0603 1%（100个） | H65: =HYPERLINK("https://item.taobao.com/item.htm?id=947267344247","打开订单商品") -> 打开订单商品 | I65: =HYPERLINK("https://item.szlcsc.com/21903.html","查看工程型号") -> 查看工程型号 | J65: 0Ω / 0603；HAT R33 按后续 0Ω / C21189 补丁计入。 | K65: HAT-V5.epro2 / PCB2
A66: R4 | B66: 0R / MUTE high | C66: 0603WAF0000T5E | D66: C21189 | E66: 0603 | F66: 0Ω / ±1% / - / 100mW | G66: 0R/0欧;0603 1%（100个） | H66: =HYPERLINK("https://item.taobao.com/item.htm?id=947267344247","打开订单商品") -> 打开订单商品 | I66: =HYPERLINK("https://item.szlcsc.com/21903.html","查看工程型号") -> 查看工程型号 | J66: 0Ω / 0603；HAT R33 按后续 0Ω / C21189 补丁计入。 | K66: HAT-V5.epro2 / PCB2
A67: R5 | B67: 0R / MODE high | C67: 0603WAF0000T5E | D67: C21189 | E67: 0603 | F67: 0Ω / ±1% / - / 100mW | G67: 0R/0欧;0603 1%（100个） | H67: =HYPERLINK("https://item.taobao.com/item.htm?id=947267344247","打开订单商品") -> 打开订单商品 | I67: =HYPERLINK("https://item.szlcsc.com/21903.html","查看工程型号") -> 查看工程型号 | J67: 0Ω / 0603；HAT R33 按后续 0Ω / C21189 补丁计入。 | K67: HAT-V5.epro2 / PCB2
A68: R6 | B68: 10k / codec reset | C68: RC0603FR-0710KL | D68: C98220 | E68: 0603 | F68: 10kΩ / ±1% / ±100ppm/℃ / 100mW | G68: 10K;0603 1%（100个） | H68: =HYPERLINK("https://item.taobao.com/item.htm?id=947267344247","打开订单商品") -> 打开订单商品 | I68: =HYPERLINK("https://item.szlcsc.com/99429.html","查看工程型号") -> 查看工程型号 | J68: 10kΩ / ±1% / 0603；HAT 十二只、IMU 三只。 | K68: HAT-V5.epro2 / PCB2
A69: R7 | B69: 0R / MIC2L to GND | C69: 0603WAF0000T5E | D69: C21189 | E69: 0603 | F69: 0Ω / ±1% / - / 100mW | G69: 0R/0欧;0603 1%（100个） | H69: =HYPERLINK("https://item.taobao.com/item.htm?id=947267344247","打开订单商品") -> 打开订单商品 | I69: =HYPERLINK("https://item.szlcsc.com/21903.html","查看工程型号") -> 查看工程型号 | J69: 0Ω / 0603；HAT R33 按后续 0Ω / C21189 补丁计入。 | K69: HAT-V5.epro2 / PCB2
A70: R8 | B70: 100R | C70: 0603WAF1000T5E | D70: C22775 | E70: 0603 | F70: 100Ω / ±1% / ±200ppm/℃ / 100mW | G70: 100R/100欧;0603 1%（100个） | H70: =HYPERLINK("https://item.taobao.com/item.htm?id=947267344247","打开订单商品") -> 打开订单商品 | I70: =HYPERLINK("https://www.lcsc.com/product-detail/C22775.html","查看工程型号") -> 查看工程型号 | J70: 100Ω / ±1% / 0603，用于 HAT R8。 | K70: HAT-V5.epro2 / PCB2
A71: R12 | B71: 10k / SDA pull-up | C71: RC0603FR-0710KL | D71: C98220 | E71: 0603 | F71: 10kΩ / ±1% / ±100ppm/℃ / 100mW | G71: 10K;0603 1%（100个） | H71: =HYPERLINK("https://item.taobao.com/item.htm?id=947267344247","打开订单商品") -> 打开订单商品 | I71: =HYPERLINK("https://item.szlcsc.com/99429.html","查看工程型号") -> 查看工程型号 | J71: 10kΩ / ±1% / 0603；HAT 十二只、IMU 三只。 | K71: HAT-V5.epro2 / PCB2
A72: R13 | B72: 10k / SCL pull-up | C72: RC0603FR-0710KL | D72: C98220 | E72: 0603 | F72: 10kΩ / ±1% / ±100ppm/℃ / 100mW | G72: 10K;0603 1%（100个） | H72: =HYPERLINK("https://item.taobao.com/item.htm?id=947267344247","打开订单商品") -> 打开订单商品 | I72: =HYPERLINK("https://item.szlcsc.com/99429.html","查看工程型号") -> 查看工程型号 | J72: 10kΩ / ±1% / 0603；HAT 十二只、IMU 三只。 | K72: HAT-V5.epro2 / PCB2
A73: R22 | B73: 10k / MIC L bias | C73: RC0603FR-0710KL | D73: C98220 | E73: 0603 | F73: 10kΩ / ±1% / ±100ppm/℃ / 100mW | G73: 10K;0603 1%（100个） | H73: =HYPERLINK("https://item.taobao.com/item.htm?id=947267344247","打开订单商品") -> 打开订单商品 | I73: =HYPERLINK("https://item.szlcsc.com/99429.html","查看工程型号") -> 查看工程型号 | J73: 10kΩ / ±1% / 0603；HAT 十二只、IMU 三只。 | K73: HAT-V5.epro2 / PCB2
A74: R23 | B74: 10k / MIC R bias | C74: RC0603FR-0710KL | D74: C98220 | E74: 0603 | F74: 10kΩ / ±1% / ±100ppm/℃ / 100mW | G74: 10K;0603 1%（100个） | H74: =HYPERLINK("https://item.taobao.com/item.htm?id=947267344247","打开订单商品") -> 打开订单商品 | I74: =HYPERLINK("https://item.szlcsc.com/99429.html","查看工程型号") -> 查看工程型号 | J74: 10kΩ / ±1% / 0603；HAT 十二只、IMU 三只。 | K74: HAT-V5.epro2 / PCB2
A75: R26 | B75: 10k / UART TX pull-up | C75: RC0603FR-0710KL | D75: C98220 | E75: 0603 | F75: 10kΩ / ±1% / ±100ppm/℃ / 100mW | G75: 10K;0603 1%（100个） | H75: =HYPERLINK("https://item.taobao.com/item.htm?id=947267344247","打开订单商品") -> 打开订单商品 | I75: =HYPERLINK("https://item.szlcsc.com/99429.html","查看工程型号") -> 查看工程型号 | J75: 10kΩ / ±1% / 0603；HAT 十二只、IMU 三只。 | K75: HAT-V5.epro2 / PCB2
A76: R27 | B76: 10k / direction base | C76: RC0603FR-0710KL | D76: C98220 | E76: 0603 | F76: 10kΩ / ±1% / ±100ppm/℃ / 100mW | G76: 10K;0603 1%（100个） | H76: =HYPERLINK("https://item.taobao.com/item.htm?id=947267344247","打开订单商品") -> 打开订单商品 | I76: =HYPERLINK("https://item.szlcsc.com/99429.html","查看工程型号") -> 查看工程型号 | J76: 10kΩ / ±1% / 0603；HAT 十二只、IMU 三只。 | K76: HAT-V5.epro2 / PCB2
A77: R28 | B77: 20k / direction pull-down | C77: 0603WAF2002T5E | D77: C4184 | E77: 0603 | F77: 20kΩ / ±1% / ±100ppm/℃ / 100mW | G77: 20K;0603 1%（100个） | H77: =HYPERLINK("https://item.taobao.com/item.htm?id=947267344247","打开订单商品") -> 打开订单商品 | I77: =HYPERLINK("https://item.szlcsc.com/4591.html","查看工程型号") -> 查看工程型号 | J77: 20kΩ / ±1% / 0603。 | K77: HAT-V5.epro2 / PCB2
A78: R29 | B78: 10k / RX gate enable | C78: RC0603FR-0710KL | D78: C98220 | E78: 0603 | F78: 10kΩ / ±1% / ±100ppm/℃ / 100mW | G78: 10K;0603 1%（100个） | H78: =HYPERLINK("https://item.taobao.com/item.htm?id=947267344247","打开订单商品") -> 打开订单商品 | I78: =HYPERLINK("https://item.szlcsc.com/99429.html","查看工程型号") -> 查看工程型号 | J78: 10kΩ / ±1% / 0603；HAT 十二只、IMU 三只。 | K78: HAT-V5.epro2 / PCB2
A79: R31 | B79: 10k / RX pull-up | C79: RC0603FR-0710KL | D79: C98220 | E79: 0603 | F79: 10kΩ / ±1% / ±100ppm/℃ / 100mW | G79: 10K;0603 1%（100个） | H79: =HYPERLINK("https://item.taobao.com/item.htm?id=947267344247","打开订单商品") -> 打开订单商品 | I79: =HYPERLINK("https://item.szlcsc.com/99429.html","查看工程型号") -> 查看工程型号 | J79: 10kΩ / ±1% / 0603；HAT 十二只、IMU 三只。 | K79: HAT-V5.epro2 / PCB2
A80: R32 | B80: 10k / data pull-up | C80: RC0603FR-0710KL | D80: C98220 | E80: 0603 | F80: 10kΩ / ±1% / ±100ppm/℃ / 100mW | G80: 10K;0603 1%（100个） | H80: =HYPERLINK("https://item.taobao.com/item.htm?id=947267344247","打开订单商品") -> 打开订单商品 | I80: =HYPERLINK("https://item.szlcsc.com/99429.html","查看工程型号") -> 查看工程型号 | J80: 10kΩ / ±1% / 0603；HAT 十二只、IMU 三只。 | K80: HAT-V5.epro2 / PCB2
A81: R33 | B81: 150R / bus series | C81: 0603WAF1500T5E | D81: C22808 | E81: 0603 | F81: 150Ω / ±1% / ±100ppm/℃ / 100mW | G81: 0603WAF0000T5E | H81: =HYPERLINK("https://item.taobao.com/item.htm?id=947267344247","打开订单商品") -> 打开订单商品 | I81: =HYPERLINK("https://www.lcsc.com/product-detail/C22808.html","查看工程型号") -> 查看工程型号 | J81: 0Ω / 0603；HAT R33 按后续 0Ω / C21189 补丁计入。 | K81: HAT-V5.epro2 / PCB2
A82: TH1 | B82: 100R PTC | C82: PRG18BB101MB1RB | D82: C913703 | E82: 0603 | F82: 100Ω / PTC / 村田 | G82: 100R PRG18BB101MB1RB | H82: =HYPERLINK("https://item.taobao.com/item.htm?id=582129955778","打开订单商品") -> 打开订单商品 | I82: =HYPERLINK("https://item.szlcsc.com/984022.html","查看工程型号") -> 查看工程型号 | J82: TH1可使用原村田PRG18BB101MB1RB（100Ω PTC，0603），按原订单100R款式采购；R33使用0Ω。 | K82: HAT-V5.epro2 / PCB2
A83: U1 | B83: PAM8406D | C83: PAM8406DR | D83: C86270 | E83: SOIC-16 | F83: 功放类型:AB类功放；D类功放；扬声器通道数:双声道；输出功率:5Wx2@2Ω；静态电流(Iq):10mA | G83: PAM8406DR | H83: =HYPERLINK("https://item.taobao.com/item.htm?id=808484505787","打开订单商品") -> 打开订单商品 | I83: =HYPERLINK("https://item.szlcsc.com/87446.html","查看工程型号") -> 查看工程型号 | J83: 实际使用：PAM8406DR，订单标注 SOP16。 | K83: HAT-V5.epro2 / PCB2
A84: U2 | B84: TLV320AIC3104IRHBR | C84: TLV320AIC3104IRHBR | D84: C181753 | E84: HVQFN-32-EP(5x5) | F84: 类型:编解码器；接口类型:I2S；I2C；采样率:8kHz~96kHz | G84: 商品无选项，按商品标题完整型号购买 | H84: =HYPERLINK("https://item.taobao.com/item.htm?id=908248360601","打开订单商品") -> 打开订单商品 | I84: =HYPERLINK("https://www.lcsc.com/product-detail/C181753.html","查看工程型号") -> 查看工程型号 | J84: TLV320AIC3104IRHBR，按商品完整型号购买。 | K84: HAT-V5.epro2 / PCB2
A85: U3 | B85: XC6206P182 / 1V8 | C85: XC6206P182MR | D85: C347373 | E85: SOT-23 | F85: 输出极性:正极；工作电压:8V；输出电压:1.8V；输出电流:250mA；电源纹波抑制比(PSRR):40dB@(1kHz)；输出类型:固定 | G85: XC6206P182MR 65K5 SOT-23 (20个) | H85: =HYPERLINK("https://item.taobao.com/item.htm?id=762173333947","打开订单商品") -> 打开订单商品 | I85: =HYPERLINK("https://item.szlcsc.com/324033.html","查看工程型号") -> 查看工程型号 | J85: XC6206P182MR / 1.8V / SOT-23，20个包装。 | K85: HAT-V5.epro2 / PCB2
A86: U5 | B86: 74LVC1G08 / RX gate | C86: SN74LVC1G08DBVR | D86: C7666 | E86: SOT-23-5 | F86: 逻辑类型:与门；通道数:1；工作电压:1.65V~5.5V；静态电流(Iq):10uA；传播延迟(tpd):4ns@5V,50pF | G86: SN74LVC1G08DBVR;5个全国包邮 | H86: =HYPERLINK("https://item.taobao.com/item.htm?id=902117985110","打开订单商品") -> 打开订单商品 | I86: =HYPERLINK("https://www.lcsc.com/product-detail/C7666.html","查看工程型号") -> 查看工程型号 | J86: SN74LVC1G08DBVR / SOT-23-5 与门，按同页对应型号选项购买。 | K86: HAT-V5.epro2 / PCB2
A87: U6 | B87: SN74LVC1G125 / RX | C87: SN74LVC1G125DBVR-TP | D87: C3040625 | E87: SOT-23-5 | F87: 输入类型:-；工作电压:1.65V~5.5V；元件数:1；每个元件位数:-；灌电流(IOL):24mA；拉电流(IOH):24mA | G87: SN74LVC1G125DBVR;5个全国包邮 | H87: =HYPERLINK("https://item.taobao.com/item.htm?id=902117985110","打开订单商品") -> 打开订单商品 | I87: =HYPERLINK("https://item.szlcsc.com/3597950.html","查看工程型号") -> 查看工程型号 | J87: 实际使用：SN74LVC1G125DBVR / SOT-23-5，5个包装。 | K87: HAT-V5.epro2 / PCB2
A88: U7 | B88: SN74LVC1G126 / TX | C88: SN74LVC1G126DBVR | D88: C7834 | E88: SOT-23-5 | F88: 输入类型:-；工作电压:1.65V~5.5V；元件数:1；每个元件位数:1；灌电流(IOL):32mA；拉电流(IOH):32mA | G88: SN74LVC1G126DBVR;5个全国包邮 | H88: =HYPERLINK("https://item.taobao.com/item.htm?id=902117985110","打开订单商品") -> 打开订单商品 | I88: =HYPERLINK("https://www.lcsc.com/product-detail/C7834.html","查看工程型号") -> 查看工程型号 | J88: 实际使用：SN74LVC1G126DBVR / SOT-23-5，5个包装。 | K88: HAT-V5.epro2 / PCB2
A89: U9 | B89: AP63205 / 5V buck | C89: AP63205WU-7 | D89: C2071056 | E89: TSOT-23-6 | F89: 功能类型:降压型；工作电压:3.8V~32V；输出电压:5V；输出电流:2A；输出类型:固定 | G89: AP63205WU-7 | H89: =HYPERLINK("https://item.taobao.com/item.htm?id=969642590399","打开订单商品") -> 打开订单商品 | I89: =HYPERLINK("https://item.szlcsc.com/2162639.html","查看工程型号") -> 查看工程型号 | J89: AP63205WU-7，固定5V降压芯片，按对应完整型号购买。 | K89: HAT-V5.epro2 / PCB2
A90: U10 | B90: LM5050-1 | C90: LM5050MKX-1/NOPB | D90: C473393 | E90: TSOT-23-6 | F90: LM5050-1 5V 至 75V、400uA IQ ORing FET 控制器 | G90: SOT-23;LM5050MKX-1/NOPB 原装正品 | H90: =HYPERLINK("https://item.taobao.com/item.htm?id=1013388982214","打开订单商品") -> 打开订单商品 | I90: =HYPERLINK("https://www.lcsc.com/product-detail/C473393.html","查看工程型号") -> 查看工程型号 | J90: LM5050MKX-1/NOPB，按完整型号购买。 | K90: HAT-V5.epro2 / PCB2
A91: Y1 | B91: 12MHz | C91: OT3EL89CJI-111YLC-12M | D91: C7425459 | E91: SMD2520-4P | F91: 12MHz | G91: 12MHZ 1.2V~3.36V宽压[高精度10PPM];SMD2520-4P CMOS输出 | H91: =HYPERLINK("https://item.taobao.com/item.htm?id=944053669860","打开订单商品") -> 打开订单商品 | I91: =HYPERLINK("https://item.szlcsc.com/8414369.html","查看工程型号") -> 查看工程型号 | J91: 实际使用：12MHz、2520-4P、CMOS输出有源晶振，宽压1.2V~3.36V（订单标称）。 | K91: HAT-V5.epro2 / PCB2

Sheet IMU位号BOM
A2: IMU 位号 BOM
A3: 源：IMU-TO-DLX-V2.epro2 / PCB1；25 个器件，工程原始属性保留。
A4: 实际采购款式见 G 列，原工程型号与参数保留备查。
A5: D2 实际采购为0603蓝色LED，原工程器件记录保留。
A6: 器件用量按实际位号统计，采购商品已在作者实机验证可用。
A7: 位号 | B7: 用途 / 位号原文 | C7: 工程完整型号 | D7: 工程立创料号 | E7: 工程封装 | F7: 工程关键参数 | G7: 当前采购规格 / 订单款式 | H7: 订单商品链接 | I7: 工程BOM型号链接 | J7: 用料说明 | K7: 工程来源
A8: C1 | B8: 4.7uF 25V | C8: CL21A475KAQNNNE | D8: C1779 | E8: 0805 | F8: 4.7uF / ±10% / 25V / X5R | G8: 0805 4.7UF ±10% X7R;25V | H8: =HYPERLINK("https://item.taobao.com/item.htm?id=977236759812","打开订单商品") -> 打开订单商品 | I8: =HYPERLINK("https://www.lcsc.com/product-detail/C1779.html","查看工程型号") -> 查看工程型号 | J8: 实际采购：0805 / 4.7uF / ±10% / 25V / X7R。 | K8: IMU-TO-DLX-V2.epro2 / PCB1
A9: C2 | B9: 100nF 50V | C9: CL10B104JB8NNNC | D9: C24452 | E9: 0603 | F9: 100nF / ±5% / 50V / X7R | G9: 0603 100nF ±10% X7R;50V;100个 | H9: =HYPERLINK("https://item.taobao.com/item.htm?id=731471380840","打开订单商品") -> 打开订单商品 | I9: =HYPERLINK("https://item.szlcsc.com/25192.html","查看工程型号") -> 查看工程型号 | J9: 实际采购：0603 / 100nF / ±10% / 50V / X7R。 | K9: IMU-TO-DLX-V2.epro2 / PCB1
A10: C3 | B10: 4.7uF 25V | C10: CL21A475KAQNNNE | D10: C1779 | E10: 0805 | F10: 4.7uF / ±10% / 25V / X5R | G10: 0805 4.7UF ±10% X7R;25V | H10: =HYPERLINK("https://item.taobao.com/item.htm?id=977236759812","打开订单商品") -> 打开订单商品 | I10: =HYPERLINK("https://www.lcsc.com/product-detail/C1779.html","查看工程型号") -> 查看工程型号 | J10: 实际采购：0805 / 4.7uF / ±10% / 25V / X7R。 | K10: IMU-TO-DLX-V2.epro2 / PCB1
A11: C4 | B11: 100nF 50V | C11: CL10B104JB8NNNC | D11: C24452 | E11: 0603 | F11: 100nF / ±5% / 50V / X7R | G11: 0603 100nF ±10% X7R;50V;100个 | H11: =HYPERLINK("https://item.taobao.com/item.htm?id=731471380840","打开订单商品") -> 打开订单商品 | I11: =HYPERLINK("https://item.szlcsc.com/25192.html","查看工程型号") -> 查看工程型号 | J11: 实际采购：0603 / 100nF / ±10% / 50V / X7R。 | K11: IMU-TO-DLX-V2.epro2 / PCB1
A12: C5 | B12: 100nF / MCU | C12: CL10B104JB8NNNC | D12: C24452 | E12: 0603 | F12: 100nF / ±5% / 50V / X7R | G12: 0603 100nF ±10% X7R;50V;100个 | H12: =HYPERLINK("https://item.taobao.com/item.htm?id=731471380840","打开订单商品") -> 打开订单商品 | I12: =HYPERLINK("https://item.szlcsc.com/25192.html","查看工程型号") -> 查看工程型号 | J12: 实际采购：0603 / 100nF / ±10% / 50V / X7R。 | K12: IMU-TO-DLX-V2.epro2 / PCB1
A13: C6 | B13: 1uF / MCU | C13: CL10A105KB8NNNC | D13: C15849 | E13: 0603 | F13: 1uF / ±10% / 50V / X5R | G13: 0603 1uF ±10% X7R;50V | H13: =HYPERLINK("https://item.taobao.com/item.htm?id=630712731066","打开订单商品") -> 打开订单商品 | I13: =HYPERLINK("https://item.szlcsc.com/16531.html","查看工程型号") -> 查看工程型号 | J13: 实际采购：0603 / 1uF / ±10% / 50V / X7R。 | K13: IMU-TO-DLX-V2.epro2 / PCB1
A14: C7 | B14: 100nF / VDD_IO | C14: CL10B104JB8NNNC | D14: C24452 | E14: 0603 | F14: 100nF / ±5% / 50V / X7R | G14: 0603 100nF ±10% X7R;50V;100个 | H14: =HYPERLINK("https://item.taobao.com/item.htm?id=731471380840","打开订单商品") -> 打开订单商品 | I14: =HYPERLINK("https://item.szlcsc.com/25192.html","查看工程型号") -> 查看工程型号 | J14: 实际采购：0603 / 100nF / ±10% / 50V / X7R。 | K14: IMU-TO-DLX-V2.epro2 / PCB1
A15: C8 | B15: 100nF / VDD | C15: CL10B104JB8NNNC | D15: C24452 | E15: 0603 | F15: 100nF / ±5% / 50V / X7R | G15: 0603 100nF ±10% X7R;50V;100个 | H15: =HYPERLINK("https://item.taobao.com/item.htm?id=731471380840","打开订单商品") -> 打开订单商品 | I15: =HYPERLINK("https://item.szlcsc.com/25192.html","查看工程型号") -> 查看工程型号 | J15: 实际采购：0603 / 100nF / ±10% / 50V / X7R。 | K15: IMU-TO-DLX-V2.epro2 / PCB1
A16: C9 | B16: 1uF / IMU local | C16: CL10A105KB8NNNC | D16: C15849 | E16: 0603 | F16: 1uF / ±10% / 50V / X5R | G16: 0603 1uF ±10% X7R;50V | H16: =HYPERLINK("https://item.taobao.com/item.htm?id=630712731066","打开订单商品") -> 打开订单商品 | I16: =HYPERLINK("https://item.szlcsc.com/16531.html","查看工程型号") -> 查看工程型号 | J16: 实际采购：0603 / 1uF / ±10% / 50V / X7R。 | K16: IMU-TO-DLX-V2.epro2 / PCB1
A17: C10 | B17: 100nF / buffer | C17: CL10B104JB8NNNC | D17: C24452 | E17: 0603 | F17: 100nF / ±5% / 50V / X7R | G17: 0603 100nF ±10% X7R;50V;100个 | H17: =HYPERLINK("https://item.taobao.com/item.htm?id=731471380840","打开订单商品") -> 打开订单商品 | I17: =HYPERLINK("https://item.szlcsc.com/25192.html","查看工程型号") -> 查看工程型号 | J17: 实际采购：0603 / 100nF / ±10% / 50V / X7R。 | K17: IMU-TO-DLX-V2.epro2 / PCB1
A18: D1 | B18: PESD5V0S1BA / 5V bidirectional | C18: PESD5V0S1BA | D18: C330094 | E18: SOD-323 | F18: 反向截止电压(Vrwm):5V@Max；最大钳位电压:10V；峰值脉冲电流(Ipp)@10/1000us:5A@8/20us；击穿电压:5.8V | G18: 商品无选项，按商品标题完整型号购买 | H18: =HYPERLINK("https://item.taobao.com/item.htm?id=891785167202","打开订单商品") -> 打开订单商品 | I18: =HYPERLINK("https://www.lcsc.com/product-detail/C330094.html","查看工程型号") -> 查看工程型号 | J18: PESD5V0S1BA / SOD-323 双向TVS，按商品完整型号购买。 | K18: IMU-TO-DLX-V2.epro2 / PCB1
A19: D2 | B19: DEBUG LED | C19: 19-217/GHC-YR1S2/3T | D19: C72043 | E19: 0603 | F19: 110mW | G19: 0603 蓝色=100个 | H19: =HYPERLINK("https://item.taobao.com/item.htm?id=1025817117811","打开订单商品") -> 打开订单商品 | I19: =HYPERLINK("https://www.lcsc.com/product-detail/Light-Emitting-Diodes-LED_Everlight-Elec-19-217-GHC-YR1S2-3T_C72043.html","查看工程型号") -> 查看工程型号 | J19: 实际采购：0603 蓝色LED，100个包装。 | K19: IMU-TO-DLX-V2.epro2 / PCB1
A20: J1 | B20: DXL BUS / JST EH 3P | C20: B3B-EH-A(LF)(SN) | D20: C160259 | E20: 插件,P=2.5mm | F20: 250V / 3A | G20: EH2.5MM 3P直针座（50个） | H20: =HYPERLINK("https://item.taobao.com/item.htm?id=832569969546","打开订单商品") -> 打开订单商品 | I20: =HYPERLINK("https://item.szlcsc.com/171639.html","查看工程型号") -> 查看工程型号 | J20: EH 3P 直针座，HAT 两只、IMU 一只。 | K20: IMU-TO-DLX-V2.epro2 / PCB1
A21: J2 | B21: SWD 1x5 | C21: PZ254V-11-05P | D21: C492404 | E21: 插件,P=2.54mm | F21: 3A | G21: 1*5P直针 铜（30条） | H21: =HYPERLINK("https://item.taobao.com/item.htm?id=606816197525","打开订单商品") -> 打开订单商品 | I21: =HYPERLINK("https://item.szlcsc.com/502960.html","查看工程型号") -> 查看工程型号 | J21: 1×5P / 2.54mm 直排针，用于SWD烧录口。 | K21: IMU-TO-DLX-V2.epro2 / PCB1
A22: R1 | B22: 0R / DXL_VDD link | C22: 0603WAF0000T5E | D22: C21189 | E22: 0603 | F22: 0Ω / ±1% / - / 100mW | G22: 0R/0欧;0603 1%（100个） | H22: =HYPERLINK("https://item.taobao.com/item.htm?id=947267344247","打开订单商品") -> 打开订单商品 | I22: =HYPERLINK("https://item.szlcsc.com/21903.html","查看工程型号") -> 查看工程型号 | J22: 0Ω / 0603；HAT R33 按后续 0Ω / C21189 补丁计入。 | K22: IMU-TO-DLX-V2.epro2 / PCB1
A23: R2 | B23: 10k / NRST pull-up | C23: RC0603FR-0710KL | D23: C98220 | E23: 0603 | F23: 10kΩ / ±1% / ±100ppm/℃ / 100mW | G23: 10K;0603 1%（100个） | H23: =HYPERLINK("https://item.taobao.com/item.htm?id=947267344247","打开订单商品") -> 打开订单商品 | I23: =HYPERLINK("https://item.szlcsc.com/99429.html","查看工程型号") -> 查看工程型号 | J23: 10kΩ / ±1% / 0603；HAT 十二只、IMU 三只。 | K23: IMU-TO-DLX-V2.epro2 / PCB1
A24: R3 | B24: 100k / BOOT0 pull-down | C24: RC0603FR-07100KL | D24: C14675 | E24: 0603 | F24: 100kΩ / ±1% / ±100ppm/℃ / 100mW | G24: 100K;0603 1%（100个） | H24: =HYPERLINK("https://item.taobao.com/item.htm?id=947267344247","打开订单商品") -> 打开订单商品 | I24: =HYPERLINK("https://item.szlcsc.com/15343.html","查看工程型号") -> 查看工程型号 | J24: 100kΩ / ±1% / 0603。 | K24: IMU-TO-DLX-V2.epro2 / PCB1
A25: R4 | B25: 10k / IMU CS pull-up | C25: RC0603FR-0710KL | D25: C98220 | E25: 0603 | F25: 10kΩ / ±1% / ±100ppm/℃ / 100mW | G25: 10K;0603 1%（100个） | H25: =HYPERLINK("https://item.taobao.com/item.htm?id=947267344247","打开订单商品") -> 打开订单商品 | I25: =HYPERLINK("https://item.szlcsc.com/99429.html","查看工程型号") -> 查看工程型号 | J25: 10kΩ / ±1% / 0603；HAT 十二只、IMU 三只。 | K25: IMU-TO-DLX-V2.epro2 / PCB1
A26: R5 | B26: 10k / TX disable pull-up | C26: RC0603FR-0710KL | D26: C98220 | E26: 0603 | F26: 10kΩ / ±1% / ±100ppm/℃ / 100mW | G26: 10K;0603 1%（100个） | H26: =HYPERLINK("https://item.taobao.com/item.htm?id=947267344247","打开订单商品") -> 打开订单商品 | I26: =HYPERLINK("https://item.szlcsc.com/99429.html","查看工程型号") -> 查看工程型号 | J26: 10kΩ / ±1% / 0603；HAT 十二只、IMU 三只。 | K26: IMU-TO-DLX-V2.epro2 / PCB1
A27: R6 | B27: 33R / DXL TX series | C27: 0603WAF330JT5E | D27: C23140 | E27: 0603 | F27: 33Ω / ±1% / ±100ppm/℃ / 100mW | G27: 33R/33欧;0603 1%（100个） | H27: =HYPERLINK("https://item.taobao.com/item.htm?id=947267344247","打开订单商品") -> 打开订单商品 | I27: =HYPERLINK("https://item.szlcsc.com/23867.html","查看工程型号") -> 查看工程型号 | J27: 33Ω / ±1% / 0603，用于IMU R6。 | K27: IMU-TO-DLX-V2.epro2 / PCB1
A28: R7 | B28: 1k / debug LED | C28: 0603WAF1001T5E | D28: C21190 | E28: 0603 | F28: 1kΩ / ±1% / ±100ppm/℃ / 100mW | G28: 1K;0603 1%（100个） | H28: =HYPERLINK("https://item.taobao.com/item.htm?id=947267344247","打开订单商品") -> 打开订单商品 | I28: =HYPERLINK("https://item.szlcsc.com/21904.html","查看工程型号") -> 查看工程型号 | J28: 1kΩ / ±1% / 0603，八月备料订单。 | K28: IMU-TO-DLX-V2.epro2 / PCB1
A29: U1 | B29: STM32G031F8P6 | C29: STM32G031F8P6 | D29: C529334 | E29: TSSOP-20 | F29: CPU内核:ARM Cortex-M0+；CPU最大主频:64MHz；CPU位数:32 Bit | G29: 全新原装 | H29: =HYPERLINK("https://item.taobao.com/item.htm?id=726808419708","打开订单商品") -> 打开订单商品 | I29: =HYPERLINK("https://item.szlcsc.com/549612.html","查看工程型号") -> 查看工程型号 | J29: STM32G031F8P6 / TSSOP-20，按商品完整型号购买。 | K29: IMU-TO-DLX-V2.epro2 / PCB1
A30: U2 | B30: LSM6DSV16XTR | C30: LSM6DSV16XTR | D30: C5267406 | E30: LGA-14(2.5x3) | F30: 传感器类型:IMU(加速度计+陀螺仪)；接口类型:I2C；SPI | G30: LSM6DSV16XTR | H30: =HYPERLINK("https://item.taobao.com/item.htm?id=640391703111","打开订单商品") -> 打开订单商品 | I30: =HYPERLINK("https://item.szlcsc.com/5993815.html","查看工程型号") -> 查看工程型号 | J30: LSM6DSV16XTR / LGA-14，在多型号商品页选择 LSM6DSV16XTR。 | K30: IMU-TO-DLX-V2.epro2 / PCB1
A31: U3 | B31: TLV70433DBVR | C31: TLV70433DBVR | D31: C94917 | E31: SOT-23-5 | F31: 输出极性:正极；工作电压:24V；输出电压:3.3V；输出电流:150mA；电源纹波抑制比(PSRR):60dB@(100kHz)；输出类型:固定 | G31: TLV70433DBVR | H31: =HYPERLINK("https://item.taobao.com/item.htm?id=747094785928","打开订单商品") -> 打开订单商品 | I31: =HYPERLINK("https://www.lcsc.com/product-detail/C94917.html","查看工程型号") -> 查看工程型号 | J31: TLV70433DBVR / 3.3V / SOT-23-5。 | K31: IMU-TO-DLX-V2.epro2 / PCB1
A32: U4 | B32: SN74LVC2G125DCUR | C32: SN74LVC2G125DCUR | D32: C21404 | E32: VSSOP-8 | F32: 输入类型:-；工作电压:1.65V~5.5V；元件数:2；每个元件位数:1；灌电流(IOL):32mA；拉电流(IOH):32mA | G32: 商品无选项，按商品标题完整型号购买 | H32: =HYPERLINK("https://item.taobao.com/item.htm?id=705642638300","打开订单商品") -> 打开订单商品 | I32: =HYPERLINK("https://www.lcsc.com/product-detail/C21404.html","查看工程型号") -> 查看工程型号 | J32: SN74LVC2G125DCUR / VSSOP-8，按商品完整型号购买。 | K32: IMU-TO-DLX-V2.epro2 / PCB1

Sheet 配件与耗材
A2: 鸭子本体用料
A3: 鸭子本体配套材料：HAT/IMU接口使用EH，飞特舵机使用AMP2.0成品线（10cm、20cm）。PCB原器件表不动，工具见独立工作表。
A4: 舵机为HD-1910-C001，整机15只；电池按NP-F550的2电＋标准双充套装选购。
A5: 订单商品金额按一拍记录；包装或购入数量包含备料。金额依据订单数据.xlsx。
A6: 类别 | B6: 商品 / 用品 | C6: 具体规格 | D6: 用量或购买条件 | E6: 订单店铺 | F6: 商品链接 | G6: 订单原款式 | H6: 每拍含量 | I6: 购买说明 | J6: 订单源行 | K6: 订单商品金额 / 拍(元)
A7: 定制PCB | B7: HAT 裸板 | C7: HAT-V5，65×30.9mm，两层板；按对应工程生成生产资料 | D7: 有券免费；无券20元5张（4元/张） | E7: PCB打样平台 | F7: =HYPERLINK("https://www.jlc.com/","PCB打样入口") -> PCB打样入口 | G7: 定制打样入口，不是现成商品 | I7: 裸板需定制；R33按0Ω采购，TH1可用原村田PRG18BB101MB1RB；使用本项目对应工程。 | J7: 未在淘宝订单中记录
A8: 定制PCB | B8: IMU 裸板 | C8: IMU-TO-DLX-V2；按对应工程生成生产资料 | D8: 有券免费；无券20元5张（4元/张） | E8: PCB打样平台 | F8: =HYPERLINK("https://www.jlc.com/","PCB打样入口") -> PCB打样入口 | G8: 定制打样入口，不是现成商品 | I8: 使用对应 IMU 工程，裸板不是可直接购买的标准模块。 | J8: 未在淘宝订单中记录
A9: 配套接插件 | B9: EH 2P 母壳 | C9: EH 2P，配 HAT J1/J2/J9 | D9: 按实际接线；最多3只/板 | E9: 启色数码旗舰店 | F9: =HYPERLINK("https://item.taobao.com/item.htm?id=832569969546","打开订单商品") -> 打开订单商品 | G9: EH2.5MM 2P胶壳（50个） | H9: 50 | I9: 每只母壳配2个EH压接端子；按EH2.5款式购买，与板上的EH接口配套。 | J9: 82 | K9: 2.2
A10: 配套接插件 | B10: EH 3P 母壳 | C10: EH 3P，配 HAT J13/J14、IMU J1 | D10: 按实际接线；最多3只/套 | E10: 启色数码旗舰店 | F10: =HYPERLINK("https://item.taobao.com/item.htm?id=832569969546","打开订单商品") -> 打开订单商品 | G10: EH2.5MM 3P胶壳（50个） | H10: 50 | I10: 每只母壳还需3个压接端子。 | J10: 81 | K10: 2.8
A11: 配套接插件 | B11: EH 压接端子 | C11: EH2.5MM 端子 | D11: 每个使用的插孔1个 | E11: 启色数码旗舰店 | F11: =HYPERLINK("https://item.taobao.com/item.htm?id=832569969546","打开订单商品") -> 打开订单商品 | G11: EH2.5MM 端子（100个） | H11: 100 | I11: 与EH母壳成套使用，按EH2.5MM端子款式购买。 | J11: 83 | K11: 3.5
A12: 信号线 | B12: SH1.0 4P 转杜邦母线 | C12: SH1.0 4P / 20cm / 杜邦母 | D12: 按连接方案选用 | E12: 信容芯旗舰店 | F12: =HYPERLINK("https://item.taobao.com/item.htm?id=895049863252","打开订单商品") -> 打开订单商品 | G12: 0.2m;1.0-4P转杜邦母（5条） | H12: 5 | I12: 用于外部接口转接；每根线的脚序按 HAT J5 与模块核对，不按线色猜。 | J12: 77 | K12: 4.56
A13: 外接模块 | B13: 扬声器 | C13: 3525 腔体 / 4Ω 3W | D13: 按音频方案选用 | E13: 深圳市优信电子科技有限公司 | F13: =HYPERLINK("https://item.taobao.com/item.htm?id=683920556900","打开订单商品") -> 打开订单商品 | G13: 3525腔体-4Ω3W/喇叭 | H13: 1 | I13: 订单自带1.25端子；HAT板座是 EH 2P，需改接或转接，不能直接认为插头相同。 | J13: 103 | K13: 3.08
A14: 外接模块 | B14: 8×8 ToF 测距模块 | C14: VL53L5X V2模块配盖片（商品标题 VL53L5CX） | D14: 按功能需求选用 | E14: 都会明武电子 | F14: =HYPERLINK("https://item.taobao.com/item.htm?id=737603917521","打开订单商品") -> 打开订单商品 | G14: VL53L5X V2模块配盖片 | H14: 1 | I14: 外接模块，不是 PCB 上的裸芯片；模块接线和供电按已验证方案。 | J14: 92 | K14: 49.5
A15: 外接主控 | B15: Radxa ZERO 3W | C15: 2GB RAM / 无eMMC / 带排针 | D15: 1块/HAT（如未已有） | E15: 瑞莎计算机(深圳)有限公司 | F15: =HYPERLINK("https://item.taobao.com/item.htm?id=763812025816","打开订单商品") -> 打开订单商品 | G15: 2GB RAM 无 eMMC 带排针[【Microduck 原版主板】] | H15: 1 | I15: 已完成订单的主板款式；属于配套主控，不计入 HAT 84 个器件。 | J15: 100 | K15: 309
A16: 舵机 | B16: 飞特 HD1910 串口总线舵机 | C16: HD-1910-C001 | D16: 15只/整机 | E16: 深圳飞特舵机工厂店 | F16: =HYPERLINK("https://item.taobao.com/item.htm?id=1078248851201","打开订单商品") -> 打开订单商品 | G16: HD-1910-C001 | H16: 1 | I16: 作者两次订单分别购入13只和2只，共15只；选择 HD-1910-C001 款式。 | J16: 104 | K16: 99
A17: 摄像头 | B17: Radxa 8M 219 摄像头 | C17: IMX219 / 800万像素 / 瑞莎8M 219 | D17: 按摄像头方案选用 | E17: 瑞莎计算机(深圳)有限公司 | F17: =HYPERLINK("https://item.taobao.com/item.htm?id=768918125679","打开订单商品") -> 打开订单商品 | G17: 8M 219 摄像头[【适配3W/3E/3A/3C/CM5/4系列】] | H17: 1 | I17: 按原订单的8M 219摄像头款式购买。 | J17: 180 | K17: 129.99
A18: 电池 | B18: NP-F550 电池与双充套装 | C18: 沣标 NP-F550 / 2200mAh / 2块电池＋标准双充 | D18: 1套含2电＋双充；按NP-F供电安装方案使用 | E18: fb数码旗舰店 | F18: =HYPERLINK("https://item.taobao.com/item.htm?id=585415365001","打开订单商品") -> 打开订单商品 | G18: 【NP-F550补光灯专用▲2200mAh】2电+标准双充套裝 | H18: 1 | I18: 按“NP-F550补光灯专用▲2200mAh，2电+标准双充套裝”原款式购买。 | J18: 22 | K18: 84.59
A19: AMP线材 | B19: AMP2.0 3P 舵机线 20cm | C19: 200mm / 1007 / 24AWG / 3P / AMP2.0 | D19: 按布线长度选择；原订单30条 | E19: 永茂电子 | F19: =HYPERLINK("https://item.taobao.com/item.htm?id=825340808235","打开订单商品") -> 打开订单商品 | G19: 200mm;1007/24#;3P;AMP2.0 | H19: 1 | I19: 用于飞特舵机线束；10cm和20cm按实际走线位置选择。 | J19: 6 | K19: 0.9
A20: AMP线材 | B20: AMP2.0 3P 舵机线 10cm | C20: 100mm / 1007 / 24AWG / 3P / AMP2.0 | D20: 按布线长度选择；原订单30条 | E20: 永茂电子 | F20: =HYPERLINK("https://item.taobao.com/item.htm?id=825340808235","打开订单商品") -> 打开订单商品 | G20: 100mm;1007/24#;3P;AMP2.0 | H20: 1 | I20: 与20cm线是不同长度选项，数量按实际线束方案准备。 | J20: 36 | K20: 0.9
A21: 线材 | B21: 22AWG 三芯硅胶排线 | C21: 黑色 / 3芯 / 22AWG / 1m | D21: 自制线束按长度裁剪 | E21: 萨牛旗舰店 | F21: =HYPERLINK("https://item.taobao.com/item.htm?id=781764816472","打开订单商品") -> 打开订单商品 | G21: 黑色;3芯;22AWG;1m | H21: 1 | I21: 订单共购入3米；此行选用2米订单的商品链接与原款式。 | J21: 29 | K21: 3.63
A22: 线材 | B22: 22AWG 单芯硅胶线 | C22: 黑色 / 22AWG / 0.33mm² / 2m | D22: 按接线需求裁剪 | E22: 渡竹旗舰店 | F22: =HYPERLINK("https://item.taobao.com/item.htm?id=736162720327","打开订单商品") -> 打开订单商品 | G22: 22AWG(0.33平方)黑色 2米 | H22: 1 | I22: 用于自制接线，按22AWG黑色2米款式购买。 | J22: 32 | K22: 3.42
A23: 线束绝缘 | B23: 彩色热缩管套装 | C23: 164片 / 彩色 / 2倍收缩 | D23: 按线束制作需要选用 | E23: 圣佰路旗舰店 | F23: =HYPERLINK("https://item.taobao.com/item.htm?id=945215173380","打开订单商品") -> 打开订单商品 | G23: 袋装 164片 彩色 【2倍收缩】 | H23: 1 | I23: 用于接线处绝缘及整理。 | J23: 37 | K23: 0.99
A24: 轴承 | B24: 6700 开式薄壁轴承 | C24: 6700开式 / 10×15×3mm / 轴承钢精品级 | D24: 按打印模型轴承位；订单共购入5只（含备料） | E24: 优可吉轴承销售店 | F24: =HYPERLINK("https://item.taobao.com/item.htm?id=625390659071","打开订单商品") -> 打开订单商品 | G24: 6700开式【轴承钢·精品级】10*15*3MM | H24: 1 | I24: 尺寸顺序为内径×外径×宽度；两次订单为3只和2只。 | J24: 111 | K24: 1.94
A25: 轴承 | B25: ET2216 薄壁轴承 | C25: ET2216 / 16×22×4mm / 轴承钢精品级 | D25: 按打印模型轴承位；订单共购入12只（含备料） | E25: 优可吉轴承销售店 | F25: =HYPERLINK("https://item.taobao.com/item.htm?id=733598659967","打开订单商品") -> 打开订单商品 | G25: ET2216【精品级】16*22*4MM[轴承钢] | H25: 1 | I25: 尺寸顺序为内径×外径×宽度；两次订单为10只和2只。 | J25: 112 | K25: 2.91
A26: 螺丝 | B26: M2×4 十字盘头平尾自攻螺丝 | C26: 铁镀镍 / 十字圆头 / 平尾自攻 / M2×4 | D26: 按模型对应孔位选用 | E26: 固万基官方旗舰店 | F26: =HYPERLINK("https://item.taobao.com/item.htm?id=534923831046","打开订单商品") -> 打开订单商品 | G26: M2*4[200只]镀镍 | H26: 200 | I26: 按打印模型及对应安装位置选择长度；每包数量是备料数量。 | J26: 88 | K26: 3.03
A27: 螺丝 | B27: M2×5 十字盘头平尾自攻螺丝 | C27: 铁镀镍 / 十字圆头 / 平尾自攻 / M2×5 | D27: 按模型对应孔位选用 | E27: 固万基官方旗舰店 | F27: =HYPERLINK("https://item.taobao.com/item.htm?id=534923831046","打开订单商品") -> 打开订单商品 | G27: M2*5[200只]镀镍 | H27: 200 | I27: 按打印模型及对应安装位置选择长度；每包数量是备料数量。原订单商品金额为0元（订单优惠），不代表常规售价。 | J27: 12 | K27: 0
A28: 螺丝 | B28: M2×6 十字盘头平尾自攻螺丝 | C28: 铁镀镍 / 十字圆头 / 平尾自攻 / M2×6 | D28: 按模型对应孔位选用 | E28: 固万基官方旗舰店 | F28: =HYPERLINK("https://item.taobao.com/item.htm?id=534923831046","打开订单商品") -> 打开订单商品 | G28: M2*6[200只]镀镍 | H28: 200 | I28: 按打印模型及对应安装位置选择长度；每包数量是备料数量。 | J28: 87 | K28: 3.31
A29: 螺丝 | B29: M2×8 十字盘头平尾自攻螺丝 | C29: 铁镀镍 / 十字圆头 / 平尾自攻 / M2×8 | D29: 按模型对应孔位选用 | E29: 固万基官方旗舰店 | F29: =HYPERLINK("https://item.taobao.com/item.htm?id=534923831046","打开订单商品") -> 打开订单商品 | G29: M2*8[200只]镀镍 | H29: 200 | I29: 按打印模型及对应安装位置选择长度；每包数量是备料数量。 | J29: 86 | K29: 3.59
A30: 螺丝 | B30: M2×12 十字盘头平尾自攻螺丝 | C30: 铁镀镍 / 十字圆头 / 平尾自攻 / M2×12 | D30: 按模型对应孔位选用 | E30: 固万基官方旗舰店 | F30: =HYPERLINK("https://item.taobao.com/item.htm?id=534923831046","打开订单商品") -> 打开订单商品 | G30: M2*12[200只]镀镍 | H30: 200 | I30: 按打印模型及对应安装位置选择长度；每包数量是备料数量。 | J30: 85 | K30: 3.88
A31: 螺丝 | B31: M2.6×8 十字盘头平尾自攻螺丝 | C31: 铁镀镍 / 十字圆头 / 平尾自攻 / M2.6×8 | D31: 按模型对应孔位选用 | E31: 固万基官方旗舰店 | F31: =HYPERLINK("https://item.taobao.com/item.htm?id=534923831046","打开订单商品") -> 打开订单商品 | G31: M2.6*8[200只]镀镍 | H31: 200 | I31: 按打印模型及对应安装位置选择长度；每包数量是备料数量。 | J31: 89 | K31: 3.59

Sheet 订单匹配依据
A2: 相关订单匹配依据
A3: 源：订单数据.xlsx；仅保留本次采购相关的103条商品记录。
A4: 数量是订单拍数，不一定等于器件个数。每拍包装数量由商品款式单独解析。
A5: 商品金额按原字段抄录，不作为统一单价，不混算采购总价。重复/旧版购买保留作依据。
A6: 订单源行 | B6: 提交日期 | C6: 订单状态 | D6: 店铺 | E6: 商品名称（原文） | F6: 型号款式（原文） | G6: 商品数量(原值) | H6: 商品金额(元，原字段) | I6: 商品链接 | J6: 对应采购项 / 历史用途
A7: 4 | B7: 46306 | C7: 卖家已发货 | D7: 深圳市RTC电子 | E7: LSM6DSLTR LSM6DSOTR LSM6DSRTR LSM6DS3TR-C LSM6DSV16XTR LGA14 | F7: LSM6DSV16XTR | G7: 2 | H7: 5.75 | I7: =HYPERLINK("https://item.taobao.com/item.htm?id=640391703111","打开商品") -> 打开商品 | J7: 同款或历史购买记录
A8: 6 | B8: 46305 | C8: 卖家已发货 | D8: 永茂电子 | E8: AMP2.0间距2.0 179228 电池端子连接线 舵机线 镍片端子线 | F8: 200mm;1007/24#;3P;AMP2.0 | G8: 30 | H8: 0.9 | I8: =HYPERLINK("https://item.taobao.com/item.htm?id=825340808235","打开商品") -> 打开商品 | J8: 其他接口体系，按对应连接方案使用
A9: 23 | B9: 46293 | C9: 交易成功 | D9: zxin旗舰店 | E9: 2.54MM间距 双排贴片排母 2*3/4/5/6/8/10/15/20/40P | F9: 2*20P=5只 | G9: 1 | H9: 9.1 | I9: =HYPERLINK("https://item.taobao.com/item.htm?id=606745016341","打开商品") -> 打开商品 | J9: 同款或历史购买记录
A10: 24 | B10: 46293 | C10: 交易成功 | D10: 凯特森工具 | E10: 精密清洗套装纳米清洁海绵高效吸附洗板水手机主板芯片维修强去污 | F10: 海绵清洗剂实惠组合 | G10: 1 | H10: 14.16 | I10: =HYPERLINK("https://item.taobao.com/item.htm?id=1049340097483","打开商品") -> 打开商品 | J10: 洗板清洁套装
A11: 35 | B11: 46290 | C11: 交易成功 | D11: 安立信旗舰店 | E11: 安立信锡浆贴片焊接锡膏手机维修环保无铅高中低温焊锡膏针筒锡泥 | F11: 183℃中温有铅锡膏30G/支(常用款) 【送推杆/针头】 | G11: 1 | H11: 13.8 | I11: =HYPERLINK("https://item.taobao.com/item.htm?id=626569273184","打开商品") -> 打开商品 | J11: 183℃ 有铅锡膏针筒
A12: 36 | B12: 46290 | C12: 交易成功 | D12: 永茂电子 | E12: AMP2.0间距2.0 179228 电池端子线 端子连接线 电子线 镍片端子线 | F12: 100mm;1007/24#;3P;AMP2.0 | G12: 30 | H12: 0.9 | I12: =HYPERLINK("https://item.taobao.com/item.htm?id=825340808235","打开商品") -> 打开商品 | J12: 其他接口体系，按对应连接方案使用
A13: 43 | B13: 46282 | C13: 交易成功 | D13: 亚润五金专营店 | E13: 白光BK701D热风枪焊台二合一锡焊电烙铁数显恒温风枪可调温拆焊台 | F13: SBK701D旋钮款（气泵式/收藏送2支烙铁头） | G13: 1 | H13: 268 | I13: =HYPERLINK("https://item.taobao.com/item.htm?id=566089419587","打开商品") -> 打开商品 | J13: 热风枪焊台
A14: 50 | B14: 46282 | C14: 交易成功 | D14: 深圳市宏宸电子 | E14: 0603/1608贴片电容 1u1.5u2.2u3.3u4.7u6.8u10u15u22u33u47uF | F14: 0603 10uF ±10% X5R;10V | G14: 50 | H14: 0.06 | I14: =HYPERLINK("https://item.taobao.com/item.htm?id=630712731066","打开商品") -> 打开商品 | J14: C1608X5R1A106KT000E
A15: 52 | B15: 46282 | C15: 交易成功 | D15: 深圳市永芯泰电子企业店 | E15: 0603 0805 1206贴片电阻 10R 100R 1K 2K 4.7K 10K 100K 1M 欧 1% | F15: 22R/22欧;0603 1%（100个） | G15: 1 | H15: 1.46 | I15: =HYPERLINK("https://item.taobao.com/item.htm?id=947267344247","打开商品") -> 打开商品 | J15: TH1之前调试的22Ω电阻订单，当前采购采用原村田PTC
A16: 53 | B16: 46282 | C16: 交易成功 | D16: 深圳市永芯泰电子企业店 | E16: 0603 0805 1206贴片电阻 10R 100R 1K 2K 4.7K 10K 100K 1M 欧 1% | F16: 10K;0603 1%（100个） | G16: 1 | H16: 1.42 | I16: =HYPERLINK("https://item.taobao.com/item.htm?id=947267344247","打开商品") -> 打开商品 | J16: 同款或历史购买记录
A17: 56 | B17: 46282 | C17: 交易成功 | D17: 深圳市永芯泰电子企业店 | E17: 0603 0805 1206贴片电阻 10R 100R 1K 2K 4.7K 10K 100K 1M 欧 1% | F17: 100K;0603 1%（100个） | G17: 1 | H17: 1.46 | I17: =HYPERLINK("https://item.taobao.com/item.htm?id=947267344247","打开商品") -> 打开商品 | J17: RC0603FR-07100KL
A18: 76 | B18: 46279 | C18: 交易成功 | D18: 凯特森工具 | E18: 无铅环保吸锡带焊盘清洁维修残留除锡渣吸锡线PCB电路板手机主板 | F18: 原装吸锡〖宽1.5mm长1.5米〗[X-100型1515] | G18: 1 | H18: 3.91 | I18: =HYPERLINK("https://item.taobao.com/item.htm?id=972313702890","打开商品") -> 打开商品 | J18: 吸锡带
A19: 77 | B19: 46279 | C19: 交易成功 | D19: 信容芯旗舰店 | E19: 信容芯 SH1.0转杜邦公/杜邦母2P3P4P5P6P7P8P9P10P 28AWG渡锡铜线 | F19: 0.2m;1.0-4P转杜邦母（5条） | G19: 1 | H19: 4.56 | I19: =HYPERLINK("https://item.taobao.com/item.htm?id=895049863252","打开商品") -> 打开商品 | J19: SH1.0 4P 转杜邦母线
A20: 78 | B20: 46279 | C20: 交易成功 | D20: 深圳市宏宸电子 | E20: 0603/1608贴片电容 1u1.5u2.2u3.3u4.7u6.8u10u15u22u33u47uF | F20: 0603 1uF ±10% X7R;50V | G20: 100 | H20: 0.03 | I20: =HYPERLINK("https://item.taobao.com/item.htm?id=630712731066","打开商品") -> 打开商品 | J20: CC0603KRX5R9BB105, CL10A105KB8NNNC
A21: 79 | B21: 46279 | C21: 交易成功 | D21: 深圳市宏宸电子 | E21: 0603/1608贴片电容 100n120n150n180n220n270nF 104 154 224 274K | F21: 0603 100nF ±10% X7R;50V;100个 | G21: 1 | H21: 1.98 | I21: =HYPERLINK("https://item.taobao.com/item.htm?id=731471380840","打开商品") -> 打开商品 | J21: CC0603KRX7R9BB104, CL10B104JB8NNNC
A22: 80 | B22: 46279 | C22: 交易成功 | D22: 深圳市永芯泰电子企业店 | E22: 0603 0805 1206贴片电阻 10R 100R 1K 2K 4.7K 10K 100K 1M 欧 1% | F22: 10K;0603 1%（100个） | G22: 1 | H22: 1.42 | I22: =HYPERLINK("https://item.taobao.com/item.htm?id=947267344247","打开商品") -> 打开商品 | J22: RC0603FR-0710KL
A23: 81 | B23: 46279 | C23: 交易成功 | D23: 启色数码旗舰店 | E23: EH2.5MM直针插座 弯针 胶壳 间距2.54MM接插件 2P 3P 4P 5P 6P | F23: EH2.5MM 3P胶壳（50个） | G23: 1 | H23: 2.8 | I23: =HYPERLINK("https://item.taobao.com/item.htm?id=832569969546","打开商品") -> 打开商品 | J23: EH 3P 母壳
A24: 82 | B24: 46279 | C24: 交易成功 | D24: 启色数码旗舰店 | E24: EH2.5MM直针插座 弯针 胶壳 间距2.54MM接插件 2P 3P 4P 5P 6P | F24: EH2.5MM 2P胶壳（50个） | G24: 1 | H24: 2.2 | I24: =HYPERLINK("https://item.taobao.com/item.htm?id=832569969546","打开商品") -> 打开商品 | J24: EH 2P 母壳
A25: 83 | B25: 46279 | C25: 交易成功 | D25: 启色数码旗舰店 | E25: EH2.5MM直针插座 弯针 胶壳 间距2.54MM接插件 2P 3P 4P 5P 6P | F25: EH2.5MM 端子（100个） | G25: 1 | H25: 3.5 | I25: =HYPERLINK("https://item.taobao.com/item.htm?id=832569969546","打开商品") -> 打开商品 | J25: EH 压接端子
A26: 91 | B26: 46276 | C26: 交易成功 | D26: 深圳市RTC电子 | E26: LSM6DSLTR LSM6DSOTR LSM6DSRTR LSM6DS3TR-C LSM6DSV16XTR LGA14 | F26: LSM6DSV16XTR | G26: 2 | H26: 5.75 | I26: =HYPERLINK("https://item.taobao.com/item.htm?id=640391703111","打开商品") -> 打开商品 | J26: LSM6DSV16XTR
A27: 92 | B27: 46276 | C27: 交易成功 | D27: 都会明武电子 | E27: VL53L5X V2 TOF宽视场飞行时间多区域激光测距传感器模块VL53L5CX | F27: VL53L5X V2模块配盖片 | G27: 1 | H27: 49.5 | I27: =HYPERLINK("https://item.taobao.com/item.htm?id=737603917521","打开商品") -> 打开商品 | J27: 8×8 ToF 测距模块
A28: 93 | B28: 46276 | C28: 交易成功 | D28: 一芯向上电子 | E28: SI2300 2301 2302 2303 2304 2305 2306 2307 2308 2312DS 2309 | F28: SI2312DS（AE9T）N沟道（20只） | G28: 1 | H28: 3 | I28: =HYPERLINK("https://item.taobao.com/item.htm?id=909264246006","打开商品") -> 打开商品 | J28: SI2312CDS-T1-GE3
A29: 94 | B29: 46276 | C29: 交易成功 | D29: 深圳市乐桥微科技 | E29: 全新原装BAT54SW BAT54S SOT-323 丝印44t 肖特基贴片三极管 20只 | F29: BAT54SW 印字44t（20只） | G29: 1 | H29: 4.5 | I29: =HYPERLINK("https://item.taobao.com/item.htm?id=793455311175","打开商品") -> 打开商品 | J29: BAT54SW,115
A30: 95 | B30: 46276 | C30: 交易成功 | D30: 贤辉亿芯 | E30: PTC热敏电阻 0603 100R 47R 33R 220R 470R 过电流热保护RPG18BB | F30: 100R PRG18BB101MB1RB | G30: 10 | H30: 0.7 | I30: =HYPERLINK("https://item.taobao.com/item.htm?id=582129955778","打开商品") -> 打开商品 | J30: TH1原村田PRG18BB101MB1RB，100Ω PTC；当前采购款式
A31: 96 | B31: 46276 | C31: 交易成功 | D31: 优好电子 | E31: 0402 0603 0805 1206 1210贴片电容22UF 226K 226P X5R 10% 50V | F31: 22UF 226K 10% X5R;10V;0603=100个 | G31: 1 | H31: 3.5 | I31: =HYPERLINK("https://item.taobao.com/item.htm?id=993202872551","打开商品") -> 打开商品 | J31: GRM188R61A226ME15D
A32: 100 | B32: 46275 | C32: 交易成功 | D32: 瑞莎计算机(深圳)有限公司 | E32: 瑞莎 Radxa 迷你主板 ZERO 3W RK3566 四核CPU WiFi6 Microduck | F32: 2GB RAM 无 eMMC 带排针[【Microduck 原版主板】] | G32: 1 | H32: 309 | I32: =HYPERLINK("https://item.taobao.com/item.htm?id=763812025816","打开商品") -> 打开商品 | J32: Radxa ZERO 3W
A33: 103 | B33: 46274 | C33: 交易成功 | D33: 深圳市优信电子科技有限公司 | E33: 3525腔体-4Ω3W/8Ω2W BOX蓝牙音响扬声器安防喇叭 带1.25端子 | F33: 3525腔体-4Ω3W/喇叭 | G33: 1 | H33: 3.08 | I33: =HYPERLINK("https://item.taobao.com/item.htm?id=683920556900","打开商品") -> 打开商品 | J33: 扬声器
A34: 105 | B34: 46274 | C34: 交易成功 | D34: 阔筹旗舰店 | E34: 防静电润轴镊子机械键盘短接镊子尖头弯头圆头精密电子元器件焊接 | F34: 防静电ESD-10【短尖头】 | G34: 1 | H34: 1.98 | I34: =HYPERLINK("https://item.taobao.com/item.htm?id=979077591318","打开商品") -> 打开商品 | J34: 防静电镊子
A35: 106 | B35: 46274 | C35: 交易成功 | D35: 中山市宝工电子有限公司 | E35: 厂家直销 有铅锡膏 6337锡膏 SMT贴片锡浆 LED锡膏 焊锡膏183℃ | F35: 手机维修焊锡膏50g | G35: 1 | H35: 20.99 | I35: =HYPERLINK("https://item.taobao.com/item.htm?id=19606507546","打开商品") -> 打开商品 | J35: 183℃ 有铅锡膏
A36: 107 | B36: 46274 | C36: 交易成功 | D36: 皓越科技smt激光钢网 | E36: 手帖打样SMT钢网精密制造PCB模板贴片锡膏红胶LED钢网小钢片 | F36: 10*10cm | G36: 1 | H36: 8.6 | I36: =HYPERLINK("https://item.taobao.com/item.htm?id=851008959999","打开商品") -> 打开商品 | J36: 定制贴片钢网
A37: 117 | B37: 46272 | C37: 交易成功 | D37: 启色数码旗舰店 | E37: EH2.5MM直针插座 弯针 胶壳 间距2.54MM接插件 2P 3P 4P 5P 6P | F37: EH2.5MM 3P直针座（50个） | G37: 1 | H37: 3 | I37: =HYPERLINK("https://item.taobao.com/item.htm?id=832569969546","打开商品") -> 打开商品 | J37: B3B-EH-A(LF)(SN)
A38: 118 | B38: 46272 | C38: 交易成功 | D38: 启色数码旗舰店 | E38: EH2.5MM直针插座 弯针 胶壳 间距2.54MM接插件 2P 3P 4P 5P 6P | F38: EH2.5MM 2P直针座（50个） | G38: 1 | H38: 2.5 | I38: =HYPERLINK("https://item.taobao.com/item.htm?id=832569969546","打开商品") -> 打开商品 | J38: B2B-EH-A(LF)(SN)
A39: 119 | B39: 46272 | C39: 交易成功 | D39: 启色数码旗舰店 | E39: XC6206P182MR 丝印65K5 SOT-23 1.8V 300MA 贴片稳压芯片 (20个) | F39: XC6206P182MR 65K5 SOT-23 (20个) | G39: 1 | H39: 1.8 | I39: =HYPERLINK("https://item.taobao.com/item.htm?id=762173333947","打开商品") -> 打开商品 | J39: XC6206P182MR
A40: 121 | B40: 46272 | C40: 交易成功 | D40: 稳泊仕旗舰店 | E40: MMBT3904 1AM MMBT3906 2A SOT-23贴片晶体功率三极管NPN PNP | F40: MMBT3906 丝印2A SOT-23(50个) | G40: 1 | H40: 1.77 | I40: =HYPERLINK("https://item.taobao.com/item.htm?id=944306254140","打开商品") -> 打开商品 | J40: MMBT3906
A41: 122 | B41: 46272 | C41: 交易成功 | D41: 稳泊仕旗舰店 | E41: SOD-323稳压管BZT52C5V1S 2.4V3.3V4.7V5.1V10V12V15V24V30V33V47 | F41: BZT52C5V1S W8 SOD-323 (50个) | G41: 1 | H41: 1.53 | I41: =HYPERLINK("https://item.taobao.com/item.htm?id=943185002457","打开商品") -> 打开商品 | J41: BZT52C5V1S-7-F
A42: 124 | B42: 46272 | C42: 交易成功 | D42: 欧贝顿旗舰店 | E42: 0603 10NF 50V 100V 250V 10% 103K X7R材质 1608贴片陶瓷电容 | F42: 0603 10NF 50V 10% 100个 | G42: 1 | H42: 2 | I42: =HYPERLINK("https://item.taobao.com/item.htm?id=610558214623","打开商品") -> 打开商品 | J42: CC0603KRX7R9BB103
A43: 125 | B43: 46272 | C43: 交易成功 | D43: 科芯奇旗舰店 | E43: 贴片磁珠 0402 0603 0805 1206 0R/30R/60R/100R/600R/1K 全系列 | F43: 0603_120R_2A_±25%【100只】 | G43: 1 | H43: 4 | I43: =HYPERLINK("https://item.taobao.com/item.htm?id=931081429973","打开商品") -> 打开商品 | J43: PE-0603PFB121ST
A44: 126 | B44: 46272 | C44: 交易成功 | D44: 科芯奇旗舰店 | E44: 贴片磁珠 0402 0603 0805 1206 0R/30R/60R/100R/600R/1K 全系列 | F44: 0603_600R_1.3A_±25%【100只】 | G44: 1 | H44: 5.6 | I44: =HYPERLINK("https://item.taobao.com/item.htm?id=931081429973","打开商品") -> 打开商品 | J44: BLM18KG601SN1D
A45: 127 | B45: 46272 | C45: 交易成功 | D45: 迪林旗舰店 | E45: 一体成型贴片功率电感0420/0520/0630/0650/1040/1265/1770/0850 | F45: 合金0630 6.8UH 印6R8 10个 6A 一体 | G45: 1 | H45: 2 | I45: =HYPERLINK("https://item.taobao.com/item.htm?id=598174251748","打开商品") -> 打开商品 | J45: SWPA6045S6R8MT
A46: 128 | B46: 46272 | C46: 交易成功 | D46: 深圳市德明电子贸易商城 | E46: 全新SN74LVC1G14 17 08 04 02 07 00 32 66 125 126DBVR SOT23-5 | F46: SN74LVC1G125DBVR;5个全国包邮 | G46: 1 | H46: 1.3 | I46: =HYPERLINK("https://item.taobao.com/item.htm?id=902117985110","打开商品") -> 打开商品 | J46: SN74LVC1G125DBVR-TP
A47: 129 | B47: 46272 | C47: 交易成功 | D47: 深圳市德明电子贸易商城 | E47: 全新SN74LVC1G14 17 08 04 02 07 00 32 66 125 126DBVR SOT23-5 | F47: SN74LVC1G126DBVR;5个全国包邮 | G47: 1 | H47: 1.8 | I47: =HYPERLINK("https://item.taobao.com/item.htm?id=902117985110","打开商品") -> 打开商品 | J47: SN74LVC1G126DBVR
A48: 130 | B48: 46272 | C48: 交易成功 | D48: 深圳市德明电子贸易商城 | E48: 全新SN74LVC1G14 17 08 04 02 07 00 32 66 125 126DBVR SOT23-5 | F48: SN74LVC1G08DBVR;5个全国包邮 | G48: 1 | H48: 1.2 | I48: =HYPERLINK("https://item.taobao.com/item.htm?id=902117985110","打开商品") -> 打开商品 | J48: SN74LVC1G08DBVR
A49: 131 | B49: 46272 | C49: 交易成功 | D49: 深圳市晶诺源电子 | E49: SMD322550327050有源晶振4M8M12M16M20M24M25M27M30M32M40M50M | F49: 12MHZ 1.2V~3.36V宽压[高精度10PPM];SMD2520-4P CMOS输出 | G49: 5 | H49: 1.45 | I49: =HYPERLINK("https://item.taobao.com/item.htm?id=944053669860","打开商品") -> 打开商品 | J49: OT3EL89CJI-111YLC-12M
A50: 132 | B50: 46272 | C50: 交易成功 | D50: 深圳市远大芯程科技 | E50: 原装正品 PAM8406DR 封装SOP16 音频放大器芯片 | F50: PAM8406DR | G50: 5 | H50: 1.18 | I50: =HYPERLINK("https://item.taobao.com/item.htm?id=808484505787","打开商品") -> 打开商品 | J50: PAM8406DR
A51: 133 | B51: 46272 | C51: 交易成功 | D51: 深圳优盛电子科技 | E51: 100只包邮贴片电容0402 0603 0805 1206 1210 100NF 104K 1UF-106 | F51: 10UF (106) 精度10%;0603=100个;10V | G51: 1 | H51: 3 | I51: =HYPERLINK("https://item.taobao.com/item.htm?id=857961351344","打开商品") -> 打开商品 | J51: 同款或历史购买记录
A52: 134 | B52: 46272 | C52: 交易成功 | D52: 深圳市永芯泰电子企业店 | E52: 0603 0805 1206贴片电阻 10R 100R 1K 2K 4.7K 10K 100K 1M 欧 1% | F52: 100R/100欧;0603 1%（100个） | G52: 1 | H52: 1.46 | I52: =HYPERLINK("https://item.taobao.com/item.htm?id=947267344247","打开商品") -> 打开商品 | J52: 0603WAF1000T5E
A53: 135 | B53: 46272 | C53: 交易成功 | D53: 深圳市永芯泰电子企业店 | E53: 0603 0805 1206贴片电阻 10R 100R 1K 2K 4.7K 10K 100K 1M 欧 1% | F53: 20K;0603 1%（100个） | G53: 1 | H53: 1.46 | I53: =HYPERLINK("https://item.taobao.com/item.htm?id=947267344247","打开商品") -> 打开商品 | J53: 0603WAF2002T5E
A54: 136 | B54: 46272 | C54: 交易成功 | D54: 深圳市永芯泰电子企业店 | E54: 0603 0805 1206贴片电阻 10R 100R 1K 2K 4.7K 10K 100K 1M 欧 1% | F54: 150R/150欧;0603 1%（100个） | G54: 1 | H54: 1.46 | I54: =HYPERLINK("https://item.taobao.com/item.htm?id=947267344247","打开商品") -> 打开商品 | J54: 旧 HAT R33 的150Ω电阻，当前采购用0Ω
A55: 137 | B55: 46272 | C55: 交易成功 | D55: 深圳市安芯选电子 | E55: 原装正品 LM5050MKX-1/NOPB SOT-23-6 OR-ing FET控制器芯片 | F55: SOT-23;LM5050MKX-1/NOPB 原装正品 | G55: 5 | H55: 2.46 | I55: =HYPERLINK("https://item.taobao.com/item.htm?id=1013388982214","打开商品") -> 打开商品 | J55: LM5050MKX-1/NOPB
A56: 139 | B56: 46272 | C56: 交易成功 | D56: 信容芯旗舰店 | E56: SH1.0mm间距立贴/卧贴2P3P4P5P6P7P8P9P10P12P贴片式插头转接头 | F56: 4P立贴（15个） | G56: 1 | H56: 2.22 | I56: =HYPERLINK("https://item.taobao.com/item.htm?id=920058690376","打开商品") -> 打开商品 | J56: BM04B-SRSS-TB(LF)(SN)
A57: 140 | B57: 46272 | C57: 交易成功 | D57: 海雀数码专营店 | E57: 2.54MM 单排母 双排母 SMT贴片双排母 2/3/4/5/6/7/8/9/10/20-40P | F57: 2*20P 贴片排母【2个】 | G57: 1 | H57: 4.07 | I57: =HYPERLINK("https://item.taobao.com/item.htm?id=533725557959","打开商品") -> 打开商品 | J57: FH-00339
A58: 141 | B58: 46272 | C58: 交易成功 | D58: 深圳市华源芯电子有限公司 电子元器件配单 | E58: 2718/3722/3729上进音降噪硅mini麦克风贴片SMD咪头模拟信号 MEMS | F58: 2718 上进音 硅麦克风【2个】 | G58: 2 | H58: 1.98 | I58: =HYPERLINK("https://item.taobao.com/item.htm?id=996702312391","打开商品") -> 打开商品 | J58: LMA2718T421-OA5-2
A59: 142 | B59: 46272 | C59: 交易成功 | D59: 深圳市宏宸电子 | E59: 0603贴片高频电容 220p240p270p300p330p360p390p430pF NPO/COG | F59: 0603 220pF ±5% NPO/COG;50V;100个 | G59: 1 | H59: 1.49 | I59: =HYPERLINK("https://item.taobao.com/item.htm?id=1005108810412","打开商品") -> 打开商品 | J59: 0603CG221J500NT
A60: 143 | B60: 46272 | C60: 交易成功 | D60: 淼鑫电子科技 | E60: 全新原装 TLV320AIC3104IRHBR 丝印AC3104I VQFN-32 解码器芯片 | F60: 暂无 | G60: 5 | H60: 1.9 | I60: =HYPERLINK("https://item.taobao.com/item.htm?id=908248360601","打开商品") -> 打开商品 | J60: TLV320AIC3104IRHBR
A61: 144 | B61: 46272 | C61: 交易成功 | D61: 深圳市豪芯微电子 只做原装 | E61: 原装正品 SN74LVC1G08DBVR 逻辑芯片 封装SOT23-5 SN74LVC1G08 | F61: 暂无 | G61: 5 | H61: 1.98 | I61: =HYPERLINK("https://item.taobao.com/item.htm?id=708737648760","打开商品") -> 打开商品 | J61: 同款或历史购买记录
A62: 147 | B62: 46269 | C62: 交易成功 | D62: 深圳市RTC电子 | E62: LSM6DSLTR LSM6DSOTR LSM6DSRTR LSM6DS3TR-C LSM6DSV16XTR LGA14 | F62: LSM6DSV16XTR | G62: 1 | H62: 5.5 | I62: =HYPERLINK("https://item.taobao.com/item.htm?id=640391703111","打开商品") -> 打开商品 | J62: 同款或历史购买记录
A63: 148 | B63: 46269 | C63: 交易成功 | D63: 深圳市RTC电子 | E63: 全新原装 LSM6DSV16XTR 丝印S6 姿态传感器芯片IC 贴片 LGA-14 | F63: LSM6DSV16XTR | G63: 1 | H63: 5.5 | I63: =HYPERLINK("https://item.taobao.com/item.htm?id=1062189210190","打开商品") -> 打开商品 | J63: 同款或历史购买记录
A64: 149 | B64: 46269 | C64: 交易成功 | D64: 深圳市新纶电子 | E64: 原装LSM6DSV16XTR LGA-14 6DoF惯性测量3D加速度陀螺仪传感器芯片 | F64: LSM6DSV16XTR | G64: 1 | H64: 10.65 | I64: =HYPERLINK("https://item.taobao.com/item.htm?id=1028742717053","打开商品") -> 打开商品 | J64: 同款或历史购买记录
A65: 150 | B65: 46269 | C65: 交易成功 | D65: 深圳市新纶电子 | E65: 原装 STM32G031F8P6 TSSOP-20 ARM Cortex-M0+ 32位微控制器-MCU | F65: 全新原装 | G65: 5 | H65: 4.83 | I65: =HYPERLINK("https://item.taobao.com/item.htm?id=726808419708","打开商品") -> 打开商品 | J65: STM32G031F8P6
A66: 151 | B66: 46269 | C66: 交易成功 | D66: 安佑卓旗舰店 | E66: 5264直针座2.5mm间距2 3 4 5 6 7 8 9 10 11 12P插座连接器接插件 | F66: （50个）直针座5264-3P | G66: 1 | H66: 2.3 | I66: =HYPERLINK("https://item.taobao.com/item.htm?id=602152415662","打开商品") -> 打开商品 | J66: 其他接口体系，按对应连接方案使用
A67: 152 | B67: 46269 | C67: 交易成功 | D67: zxin旗舰店 | E67: 2.54mm 单排排针 1*2P/3/4/5/6/7/8/9/10/11/12/40P 针总长11.3mm | F67: 1*5P直针 铜（30条） | G67: 1 | H67: 1.41 | I67: =HYPERLINK("https://item.taobao.com/item.htm?id=606816197525","打开商品") -> 打开商品 | J67: PZ254V-11-05P
A68: 153 | B68: 46269 | C68: 交易成功 | D68: 深圳市宏宸电子 | E68: 0805贴片电容 1U1.5U2.2U3.3U4.7U6.8U10UF15UF22U33U47U68U100UF | F68: 0805 4.7UF ±10% X7R;25V | G68: 100 | H68: 0.06 | I68: =HYPERLINK("https://item.taobao.com/item.htm?id=977236759812","打开商品") -> 打开商品 | J68: CL21A475KAQNNNE
A69: 154 | B69: 46269 | C69: 交易成功 | D69: zazr旗舰店 | E69: ST-LINK V2 STM8/STM32仿真器编程stlink下载器线烧录调试单片机 | F69: ST-LINK V2 仿真器 进口芯片软件可升级版本（颜色随机发）1个 | G69: 1 | H69: 9.84 | I69: =HYPERLINK("https://item.taobao.com/item.htm?id=581798084270","打开商品") -> 打开商品 | J69: ST-LINK V2
A70: 155 | B70: 46269 | C70: 交易成功 | D70: 深圳市永芯泰电子企业店 | E70: 0603 0805 1206贴片电阻 10R 100R 1K 2K 4.7K 10K 100K 1M 欧 1% | F70: 0R/0欧;0603 1%（100个） | G70: 1 | H70: 1.46 | I70: =HYPERLINK("https://item.taobao.com/item.htm?id=947267344247","打开商品") -> 打开商品 | J70: 0603WAF0000T5E
A71: 156 | B71: 46269 | C71: 交易成功 | D71: 深圳市永芯泰电子企业店 | E71: 0603 0805 1206贴片电阻 10R 100R 1K 2K 4.7K 10K 100K 1M 欧 1% | F71: 10K;0603 1%（100个） | G71: 1 | H71: 1.42 | I71: =HYPERLINK("https://item.taobao.com/item.htm?id=947267344247","打开商品") -> 打开商品 | J71: 同款或历史购买记录
A72: 157 | B72: 46269 | C72: 交易成功 | D72: 深圳市永芯泰电子企业店 | E72: 0603 0805 1206贴片电阻 10R 100R 1K 2K 4.7K 10K 100K 1M 欧 1% | F72: 33R/33欧;0603 1%（100个） | G72: 1 | H72: 1.46 | I72: =HYPERLINK("https://item.taobao.com/item.htm?id=947267344247","打开商品") -> 打开商品 | J72: 0603WAF330JT5E
A73: 158 | B73: 46269 | C73: 交易成功 | D73: 泰辰电子 | E73: 0402 0603 0805 1206贴片LED发光二极管 红黄冰蓝翠绿白橙粉紫色 | F73: 0603 蓝色=100个 | G73: 1 | H73: 1.8 | I73: =HYPERLINK("https://item.taobao.com/item.htm?id=1025817117811","打开商品") -> 打开商品 | J73: 19-217/GHC-YR1S2/3T
A74: 159 | B74: 46269 | C74: 交易成功 | D74: 泰辰电子 | E74: 0402 0603 0805 1206贴片LED发光二极管 红黄冰蓝翠绿白橙粉紫色 | F74: 0603红色=100个 | G74: 1 | H74: 1.8 | I74: =HYPERLINK("https://item.taobao.com/item.htm?id=1025817117811","打开商品") -> 打开商品 | J74: 同款或历史购买记录
A75: 160 | B75: 46269 | C75: 交易成功 | D75: 深圳市优信电子科技有限公司 | E75: 原装正品 PESD5V0S1BA SOD-323 双向ESD静电防护二极管 | F75: 暂无 | G75: 50 | H75: 0.06 | I75: =HYPERLINK("https://item.taobao.com/item.htm?id=891785167202","打开商品") -> 打开商品 | J75: PESD5V0S1BA
A76: 161 | B76: 46269 | C76: 交易成功 | D76: 深圳市垚鑫电子科技 | E76: 原装正品 SN74LVC2G125DCUR VSSOP-8 三态输出双总线缓冲器闸芯片 | F76: 暂无 | G76: 10 | H76: 0.43 | I76: =HYPERLINK("https://item.taobao.com/item.htm?id=705642638300","打开商品") -> 打开商品 | J76: SN74LVC2G125DCUR
A77: 162 | B77: 46269 | C77: 交易成功 | D77: 深圳市恒芯科创电子 | E77: 原装正品 TLV70433DBVR SOT-23-5 低压降稳压器(LDO)芯片 | F77: TLV70433DBVR | G77: 10 | H77: 0.47 | I77: =HYPERLINK("https://item.taobao.com/item.htm?id=747094785928","打开商品") -> 打开商品 | J77: TLV70433DBVR
A78: 178 | B78: 46266 | C78: 交易成功 | D78: 深圳市优信电子科技有限公司 | E78: 原装LSM6DSV16XTR LGA-14 6DoF惯性测量3D加速度陀螺仪传感器芯片 | F78: 暂无 | G78: 1 | H78: 21.17 | I78: =HYPERLINK("https://item.taobao.com/item.htm?id=1027587805193","打开商品") -> 打开商品 | J78: 同款或历史购买记录
A79: 196 | B79: 46258 | C79: 交易成功 | D79: 深圳市宏宸电子 | E79: 0603/1608贴片电容 1u1.5u2.2u3.3u4.7u6.8u10u15u22u33u47uF | F79: 0603 1uF ±10% X7R;50V | G79: 50 | H79: 0.03 | I79: =HYPERLINK("https://item.taobao.com/item.htm?id=630712731066","打开商品") -> 打开商品 | J79: 同款或历史购买记录
A80: 203 | B80: 46258 | C80: 交易成功 | D80: 深圳市远大芯程科技 | E80: 全新原装正品 AP63205WU-7 封装TSOT-26 丝印T5 DC-DC电源芯片 | F80: AP63205WU-7 | G80: 5 | H80: 1.28 | I80: =HYPERLINK("https://item.taobao.com/item.htm?id=969642590399","打开商品") -> 打开商品 | J80: AP63205WU-7
A81: 205 | B81: 46258 | C81: 交易成功 | D81: 深圳市宏宸电子 | E81: 0603/1608贴片电容 100n120n150n180n220n270nF 104 154 224 274K | F81: 0603 100nF ±10% X7R;50V;100个 | G81: 1 | H81: 1.98 | I81: =HYPERLINK("https://item.taobao.com/item.htm?id=731471380840","打开商品") -> 打开商品 | J81: 同款或历史购买记录
A82: 206 | B82: 46258 | C82: 交易成功 | D82: 深圳市宏宸电子 | E82: 1206贴片电容 1UF2.2U3.3U4.7U6.8U10U15U22U33U47U68U100UF220UF | F82: 1206 10UF ±10% X7R;35V | G82: 10 | H82: 0.12 | I82: =HYPERLINK("https://item.taobao.com/item.htm?id=730407108775","打开商品") -> 打开商品 | J82: C3216X7R1V106KT000E
A83: 209 | B83: 46256 | C83: 交易关闭 | D83: 汉邦电子 | E83: 擎威恒温加热台智能定时可调温加热板回流焊接实验室手机拆屏焊台 | F83: 【150*100mm】智能定时/3组温度预设 | G83: 1 | H83: 169 | I83: =HYPERLINK("https://item.taobao.com/item.htm?id=956985590887","打开商品") -> 打开商品 | J83: 恒温加热台
A84: 213 | B84: 46254 | C84: 交易成功 | D84: 深圳市永芯泰电子企业店 | E84: 0603 0805 1206贴片电阻 10R 100R 1K 2K 4.7K 10K 100K 1M 欧 1% | F84: 1K;0603 1%（100个） | G84: 1 | H84: 1.44 | I84: =HYPERLINK("https://item.taobao.com/item.htm?id=947267344247","打开商品") -> 打开商品 | J84: 0603WAF1001T5E
A85: 220 | B85: 46253 | C85: 交易成功 | D85: YGTCTECH永冠同创 | E85: BGA手机维修焊接助焊膏焊油焊剂无铅无卤助焊剂免洗焊锡膏针筒装 | F85: YG-336环保无铅BGA针筒助焊膏10g | G85: 1 | H85: 3.28 | I85: =HYPERLINK("https://item.taobao.com/item.htm?id=744370287305","打开商品") -> 打开商品 | J85: 助焊膏
A86: 12 | B86: 46300.484 | C86: 卖家已发货 | D86: 固万基官方旗舰店 | E86: 铁镀镍十字圆头平尾自攻螺丝PB盘头小螺钉M2/M2.3/M2.6/M3/M3.5M4 | F86: M2*5[200只]镀镍 | G86: 1 | H86: 0 | I86: =HYPERLINK("https://item.taobao.com/item.htm?id=534923831046","打开订单商品") -> 打开订单商品 | J86: 鸭子本体用料：M2×5 十字盘头平尾自攻螺丝
A87: 22 | B87: 46294.953 | C87: 交易成功 | D87: fb数码旗舰店 | E87: 沣标NP-F550/F750补光灯电池适用LED补光灯监视器摄影灯通用 F770 f960 f970内置type-c | F87: 【NP-F550补光灯专用▲2200mAh】2电+标准双充套裝 | G87: 1 | H87: 84.59 | I87: =HYPERLINK("https://item.taobao.com/item.htm?id=585415365001","打开订单商品") -> 打开订单商品 | J87: 鸭子本体用料：NP-F550 电池与双充套装
A88: 29 | B88: 46291.798 | C88: 交易成功 | D88: 萨牛旗舰店 | E88: 特软硅胶排线平行线耐高温柔软多芯并线2/3/4/5/6/8/10/12/14pin | F88: 黑色;3芯;22AWG;1m | G88: 2 | H88: 3.63 | I88: =HYPERLINK("https://item.taobao.com/item.htm?id=781764816472","打开订单商品") -> 打开订单商品 | J88: 鸭子本体用料：22AWG 三芯硅胶排线
A89: 30 | B89: 46291.798 | C89: 交易成功 | D89: 萨牛旗舰店 | E89: 特软硅胶排线平行线耐高温柔软多芯并线2/3/4/5/6/8/10/12/14pin | F89: 黑色;3芯;22AWG;1m | G89: 1 | H89: 3.52 | I89: =HYPERLINK("https://item.taobao.com/item.htm?id=781764816472","打开订单商品") -> 打开订单商品 | J89: 22AWG三芯硅胶排线，补充1米
A90: 32 | B90: 46291.048 | C90: 交易成功 | D90: 渡竹旗舰店 | E90: 美标特软耐高温硅胶线17 18 20 22 24 26 30AWG新能源软线航模线 | F90: 22AWG(0.33平方)黑色 2米 | G90: 1 | H90: 3.42 | I90: =HYPERLINK("https://item.taobao.com/item.htm?id=736162720327","打开订单商品") -> 打开订单商品 | J90: 鸭子本体用料：22AWG 单芯硅胶线
A91: 37 | B91: 46289.014 | C91: 交易成功 | D91: 圣佰路旗舰店 | E91: 两倍热缩管家用接线套管组合热缩套装绝缘电工用电线保护套彩色 | F91: 袋装 164片 彩色 【2倍收缩】 | G91: 1 | H91: 0.99 | I91: =HYPERLINK("https://item.taobao.com/item.htm?id=945215173380","打开订单商品") -> 打开订单商品 | J91: 鸭子本体用料：彩色热缩管套装
A92: 39 | B92: 46286.438 | C92: 交易成功 | D92: 白光安泰信品牌经营店 | E92: 白光900M烙铁头936电烙铁恒温焊台刀头弯尖马蹄一字嘴937电焊接咀 | F92: 900M-T-LI长尖头 | G92: 1 | H92: 3.63 | I92: =HYPERLINK("https://item.taobao.com/item.htm?id=567201709691","打开订单商品") -> 打开订单商品 | J92: 制作工具与耗材：900M-T-LI 长尖头
A93: 40 | B93: 46286.438 | C93: 交易成功 | D93: 白光安泰信品牌经营店 | E93: 白光900M烙铁头936电烙铁恒温焊台刀头弯尖马蹄一字嘴937电焊接咀 | F93: 900M-T-SK小刀头 | G93: 1 | H93: 3.3 | I93: =HYPERLINK("https://item.taobao.com/item.htm?id=567201709691","打开订单商品") -> 打开订单商品 | J93: 制作工具与耗材：900M-T-SK 小刀头
A94: 85 | B94: 46277.82 | C94: 交易成功 | D94: 固万基官方旗舰店 | E94: 铁镀镍十字圆头平尾自攻螺丝PB盘头小螺钉M2/M2.3/M2.6/M3/M3.5M4 | F94: M2*12[200只]镀镍 | G94: 1 | H94: 3.88 | I94: =HYPERLINK("https://item.taobao.com/item.htm?id=534923831046","打开订单商品") -> 打开订单商品 | J94: 鸭子本体用料：M2×12 十字盘头平尾自攻螺丝
A95: 86 | B95: 46277.82 | C95: 交易成功 | D95: 固万基官方旗舰店 | E95: 铁镀镍十字圆头平尾自攻螺丝PB盘头小螺钉M2/M2.3/M2.6/M3/M3.5M4 | F95: M2*8[200只]镀镍 | G95: 1 | H95: 3.59 | I95: =HYPERLINK("https://item.taobao.com/item.htm?id=534923831046","打开订单商品") -> 打开订单商品 | J95: 鸭子本体用料：M2×8 十字盘头平尾自攻螺丝
A96: 87 | B96: 46277.82 | C96: 交易成功 | D96: 固万基官方旗舰店 | E96: 铁镀镍十字圆头平尾自攻螺丝PB盘头小螺钉M2/M2.3/M2.6/M3/M3.5M4 | F96: M2*6[200只]镀镍 | G96: 1 | H96: 3.31 | I96: =HYPERLINK("https://item.taobao.com/item.htm?id=534923831046","打开订单商品") -> 打开订单商品 | J96: 鸭子本体用料：M2×6 十字盘头平尾自攻螺丝
A97: 88 | B97: 46277.82 | C97: 交易成功 | D97: 固万基官方旗舰店 | E97: 铁镀镍十字圆头平尾自攻螺丝PB盘头小螺钉M2/M2.3/M2.6/M3/M3.5M4 | F97: M2*4[200只]镀镍 | G97: 1 | H97: 3.03 | I97: =HYPERLINK("https://item.taobao.com/item.htm?id=534923831046","打开订单商品") -> 打开订单商品 | J97: 鸭子本体用料：M2×4 十字盘头平尾自攻螺丝
A98: 89 | B98: 46277.82 | C98: 交易成功 | D98: 固万基官方旗舰店 | E98: 铁镀镍十字圆头平尾自攻螺丝PB盘头小螺钉M2/M2.3/M2.6/M3/M3.5M4 | F98: M2.6*8[200只]镀镍 | G98: 1 | H98: 3.59 | I98: =HYPERLINK("https://item.taobao.com/item.htm?id=534923831046","打开订单商品") -> 打开订单商品 | J98: 鸭子本体用料：M2.6×8 十字盘头平尾自攻螺丝
A99: 104 | B99: 46274.882 | C99: 交易成功 | D99: 深圳飞特舵机工厂店 | E99: 【预售30天】飞特金属齿机器鸭具身智能开源AI专用串口总线舵机 | F99: HD-1910-C001 | G99: 13 | H99: 99 | I99: =HYPERLINK("https://item.taobao.com/item.htm?id=1078248851201","打开订单商品") -> 打开订单商品 | J99: 鸭子本体用料：飞特 HD1910 串口总线舵机
A100: 111 | B100: 46272.896 | C100: 交易成功 | D100: 优可吉轴承销售店 | E100: 高速不锈钢薄壁轴承61700ZZ S6700-2RS 尺寸10*15*4*3mm 6700开式 | F100: 6700开式【轴承钢·精品级】10*15*3MM | G100: 3 | H100: 1.94 | I100: =HYPERLINK("https://item.taobao.com/item.htm?id=625390659071","打开订单商品") -> 打开订单商品 | J100: 鸭子本体用料：6700 开式薄壁轴承
A101: 112 | B101: 46272.896 | C101: 交易成功 | D101: 优可吉轴承销售店 | E101: 英制不锈钢超薄壁轴承SET2216 DDA2216 MR1622 16224 尺寸16*22*4 | F101: ET2216【精品级】16*22*4MM[轴承钢] | G101: 10 | H101: 2.91 | I101: =HYPERLINK("https://item.taobao.com/item.htm?id=733598659967","打开订单商品") -> 打开订单商品 | J101: 鸭子本体用料：ET2216 薄壁轴承
...

Sheet 制作工具与耗材
A2: 制作工具与耗材
A3: 焊接、回流、贴装、清洁和调试用品。已有工具可继续使用。
A4: 钢网按对应Gerber定制；锡膏包装按习惯选择。
A5: 订单商品金额按一拍记录；包装或购入数量包含备料。金额依据订单数据.xlsx。
A6: 类别 | B6: 商品 / 用品 | C6: 具体规格 | D6: 用量或购买条件 | E6: 订单店铺 | F6: 商品链接 | G6: 订单原款式 | H6: 每拍含量 | I6: 购买说明 | J6: 订单源行 | K6: 订单商品金额 / 拍(元)
A7: 烧录工具 | B7: ST-LINK V2 | C7: STM32 仿真器，订单进口芯片版本 | D7: 已有可不买 | E7: zazr旗舰店 | F7: =HYPERLINK("https://item.taobao.com/item.htm?id=581798084270","打开订单商品") -> 打开订单商品 | G7: ST-LINK V2 仿真器 进口芯片软件可升级版本（颜色随机发）1个 | H7: 1 | I7: 用于 IMU STM32 的 SWD 烧录。 | J7: 154 | K7: 9.84
A8: 制作耗材 | B8: 定制贴片钢网 | C8: 10×10cm 规格 | D8: HAT、IMU按各自Gerber定制 | E8: 皓越科技smt激光钢网 | F8: =HYPERLINK("https://item.taobao.com/item.htm?id=851008959999","打开订单商品") -> 打开订单商品 | G8: 10*10cm | H8: 1 | I8: 这是定制商品链接，付款后需提供对应钢网文件；订单没有保存具体开孔内容。 | J8: 107 | K8: 8.6
A9: 制作耗材 | B9: 183℃ 有铅锡膏 | C9: 63/37，订单50g罐装 | D9: 已有可不买 | E9: 中山市宝工电子有限公司 | F9: =HYPERLINK("https://item.taobao.com/item.htm?id=19606507546","打开订单商品") -> 打开订单商品 | G9: 手机维修焊锡膏50g | H9: 1 | I9: 与家庭回流工艺对应；按实际工具和温度流程使用。 | J9: 106 | K9: 20.99
A10: 制作耗材 | B10: 183℃ 有铅锡膏针筒 | C10: 30g / 针筒 / 含推杆针头 | D10: 与上一条按习惯选用 | E10: 安立信旗舰店 | F10: =HYPERLINK("https://item.taobao.com/item.htm?id=626569273184","打开订单商品") -> 打开订单商品 | G10: 183℃中温有铅锡膏30G/支(常用款) 【送推杆/针头】 | H10: 1 | I10: 与罐装锡膏是另一包装方案，不需要两种都买。 | J10: 35 | K10: 13.8
A11: 制作工具 | B11: 防静电镊子 | C11: ESD-10 短尖头 | D11: 已有可不买 | E11: 阔筹旗舰店 | F11: =HYPERLINK("https://item.taobao.com/item.htm?id=979077591318","打开订单商品") -> 打开订单商品 | G11: 防静电ESD-10【短尖头】 | H11: 1 | I11: 用于贴装。 | J11: 105 | K11: 1.98
A12: 制作工具 | B12: 恒温加热台 | C12: 150×100mm / 定时 / 3组温度预设 | D12: 已有可不买 | E12: 汉邦电子 | F12: =HYPERLINK("https://item.taobao.com/item.htm?id=956985590887","打开订单商品") -> 打开订单商品 | G12: 【150*100mm】智能定时/3组温度预设 | H12: 1 | I12: 订单记录对应家庭回流工具。 | J12: 211 | K12: 188
A13: 返修工具 | B13: 热风枪焊台 | C13: SBK701D旋钮款（气泵式） | D13: 按返修需求选用 | E13: 亚润五金专营店 | F13: =HYPERLINK("https://item.taobao.com/item.htm?id=566089419587","打开订单商品") -> 打开订单商品 | G13: SBK701D旋钮款（气泵式/收藏送2支烙铁头） | H13: 1 | I13: 可用于返修；不计入 PCB BOM。 | J13: 43 | K13: 268
A14: 返修耗材 | B14: 吸锡带 | C14: 1.5mm宽 / 1.5m / X-100型1515 | D14: 按返修需求选用 | E14: 凯特森工具 | F14: =HYPERLINK("https://item.taobao.com/item.htm?id=972313702890","打开订单商品") -> 打开订单商品 | G14: 原装吸锡〖宽1.5mm长1.5米〗[X-100型1515] | H14: 1 | I14: 用于焊盘清理。 | J14: 76 | K14: 3.91
A15: 制作耗材 | B15: 助焊膏 | C15: YG-336 / 10g 针筒 | D15: 已有可不买 | E15: YGTCTECH永冠同创 | F15: =HYPERLINK("https://item.taobao.com/item.htm?id=744370287305","打开订单商品") -> 打开订单商品 | G15: YG-336环保无铅BGA针筒助焊膏10g | H15: 1 | I15: 原订单款式；不计入 PCB BOM。 | J15: 220 | K15: 3.28
A16: 清洁耗材 | B16: 洗板清洁套装 | C16: 海绵清洗剂组合 | D16: 已有可不买 | E16: 凯特森工具 | F16: =HYPERLINK("https://item.taobao.com/item.htm?id=1049340097483","打开订单商品") -> 打开订单商品 | G16: 海绵清洗剂实惠组合 | H16: 1 | I16: 原订单未提供清洗剂成分，不将其列为电气材料。 | J16: 24 | K16: 14.16
A17: 舵机调试工具 | B17: 飞特 USB 调试转接板 | C17: FE-URT2-C001 | D17: 烧录、配置及调试时选用 | E17: 深圳飞特舵机工厂店 | F17: =HYPERLINK("https://item.taobao.com/item.htm?id=1078248851201","打开订单商品") -> 打开订单商品 | G17: FE-URT2-C001 | H17: 1 | I17: 调试工具，按FE-URT2-C001选项购买。 | J17: 169 | K17: 45
A18: 焊接工具 | B18: 安立信937A 数显焊台 | C18: 937A升级数显 / 套餐二 | D18: 已有可省 | E18: 安立信旗舰店 | F18: =HYPERLINK("https://item.taobao.com/item.htm?id=588102758150","打开订单商品") -> 打开订单商品 | G18: 安立信937A升级数显（套餐二） | H18: 1 | I18: 订单购买的电烙铁焊台，用于手工焊接。 | J18: 189 | K18: 106.68
A19: 烙铁头 | B19: 900M-T-LI 长尖头 | C19: 900M-T-LI | D19: 按焊接习惯选用 | E19: 白光安泰信品牌经营店 | F19: =HYPERLINK("https://item.taobao.com/item.htm?id=567201709691","打开订单商品") -> 打开订单商品 | G19: 900M-T-LI长尖头 | H19: 1 | I19: 按900M-T-LI长尖头款式购买。 | J19: 39 | K19: 3.63
A20: 烙铁头 | B20: 900M-T-SK 小刀头 | C20: 900M-T-SK | D20: 按焊接习惯选用 | E20: 白光安泰信品牌经营店 | F20: =HYPERLINK("https://item.taobao.com/item.htm?id=567201709691","打开订单商品") -> 打开订单商品 | G20: 900M-T-SK小刀头 | H20: 1 | I20: 按900M-T-SK小刀头款式购买。 | J20: 40 | K20: 3.3
A21: 制作耗材 | B21: 183℃ 有铅锡膏 10g 针筒 | C21: 183℃熔点 / 有铅 / 10g / 配杆针 | D21: 按包装习惯选购 | E21: OLK唐宏五金工具店 | F21: =HYPERLINK("https://item.taobao.com/item.htm?id=621018369847","打开订单商品") -> 打开订单商品 | G21: 183℃熔点有铅锡浆10g+杆针 | H21: 1 | I21: 与50g罐装、30g针筒是不同包装选择。 | J21: 214 | K21: 4.69

Sheet 制作成本
A2: HAT 与 IMU 制作成本
A3: 按历史订单实付（含原运费）分摊，单板材料与整包采购分别计算。配件、舵机和工具另见采购表。
A4: HAT块数 | B4: =合并采购清单!B4 -> 1 | C4: IMU块数 | D4: =合并采购清单!D4 -> 1
A5: PCB每批金额(元) | B5: 20 | C5: PCB每批张数 | D5: 5 | E5: 钢网每张(元) | F5: 12
A7: 单板材料成本 | B7: HAT | C7: IMU | D7: 合计
A8: 板上元器件（含历史运费分摊） | B8: =SUM(I29:I72) -> 16.724905 | C8: =SUM(J29:J72) -> 12.333632 | D8: =SUM(B8:C8) -> 29.058537
A9: PCB：有免费券 | B9: 0 | C9: 0 | D9: =SUM(B9:C9) -> 0
A10: 有券：材料成本 | B10: =B8+B9 -> 16.724905 | C10: =C8+C9 -> 12.333632 | D10: =D8+D9 -> 29.058537
A11: PCB：无券，折算单板 | B11: =$B$5/$D$5*$B$4 -> 4 | C11: =$B$5/$D$5*$D$4 -> 4 | D11: =SUM(B11:C11) -> 8
A12: 无券：材料成本 | B12: =B8+B11 -> 20.724905 | C12: =C8+C11 -> 16.333632 | D12: =D8+D11 -> 37.058537
A14: 首次按包装采购（商品金额，运费另计）
A15: 项目 | B15: 仅HAT | C15: 仅IMU | D15: 两板合并采购
A16: 按包装采购元器件商品金额 | B16: =SUM(L29:L72) -> 66.88 | C16: =SUM(M29:M72) -> 27.15 | D16: =SUM(K29:K72) -> 86.17
A17: 有券：首批商品预算 | B17: =B16 -> 66.88 | C17: =C16 -> 27.15 | D17: =D16 -> 86.17
A18: 无券PCB首批：每种5张 | B18: =ROUNDUP($B$4/$D$5,0)*$B$5 -> 20 | C18: =ROUNDUP($D$4/$D$5,0)*$B$5 -> 20 | D18: =SUM(B18:C18) -> 40
A19: 无券：首批商品预算 | B19: =B16+B18 -> 86.88 | C19: =C16+C18 -> 47.15 | D19: =D16+D18 -> 126.17
A21: 钢网可重复使用。各做1张时另加24元；锡膏、工具、主控、舵机和外接模块另计。
A22: NP-F550：2电＋标准双充，1套商品金额 | B22: =配件与耗材!K18 -> 84.59
A23: 本次板卡＋1套NP-F550：PCB有券 | B23: =D10+B22 -> 113.64854
A24: 本次板卡＋1套NP-F550：PCB无券 | B24: =D12+B22 -> 121.64854
A26: 元器件计算明细：按商品金额占比分摊订单实付；来源为订单数据.xlsx，对应源行见O列。
A28: 型号 / 指定款式 | B28: 每拍含量 | C28: 订单商品金额/拍 | D28: 该订单商品金额合计 | E28: 该订单实付金额 | F28: 单个实付分摊成本 | G28: HAT单板数量 | H28: IMU单板数量 | I28: 本次HAT用料成本 | J28: 本次IMU用料成本 | K28: 合并整包商品金额 | L28: 仅HAT整包商品金额 | M28: 仅IMU整包商品金额 | N28: 商品链接 | O28: 订单源行
A29: CC0603KRX5R9BB105 / CL10A105KB8NNNC 0603 1uF ±10% X7R;50V | B29: 1 | C29: 0.03 | D29: 4.98 | E29: 5.95 | F29: =C29/D29*E29/B29 -> 0.035843373 | G29: =SUM(合并采购清单!D9,合并采购清单!D44) -> 15 | H29: =SUM(合并采购清单!E9,合并采购清单!E44) -> 2 | I29: =F29*G29*$B$4 -> 0.5376506 | J29: =F29*H29*$D$4 -> 0.071686747 | K29: =ROUNDUP((G29*$B$4+H29*$D$4)/B29,0)*C29 -> 0.51 | L29: =ROUNDUP(G29*$B$4/B29,0)*C29 -> 0.45 | M29: =ROUNDUP(H29*$D$4/B29,0)*C29 -> 0.06 | N29: =HYPERLINK("https://item.taobao.com/item.htm?id=630712731066","打开订单商品") -> 打开订单商品 | O29: 78
A30: C1608X5R1A106KT000E 0603 10uF ±10% X5R;10V | B30: 1 | C30: 0.06 | D30: 9.47 | E30: 10.42 | F30: =C30/D30*E30/B30 -> 0.066019007 | G30: =SUM(合并采购清单!D10) -> 5 | H30: =SUM(合并采购清单!E10) -> 0 | I30: =F30*G30*$B$4 -> 0.33009504 | J30: =F30*H30*$D$4 -> 0 | K30: =ROUNDUP((G30*$B$4+H30*$D$4)/B30,0)*C30 -> 0.3 | L30: =ROUNDUP(G30*$B$4/B30,0)*C30 -> 0.3 | M30: =ROUNDUP(H30*$D$4/B30,0)*C30 -> 0 | N30: =HYPERLINK("https://item.taobao.com/item.htm?id=630712731066","打开订单商品") -> 打开订单商品 | O30: 50
A31: 0603CG221J500NT 0603 220pF ±5% NPO/COG;50V;100个 | B31: 100 | C31: 1.49 | D31: 1.49 | E31: 1.49 | F31: =C31/D31*E31/B31 -> 0.0149 | G31: =SUM(合并采购清单!D11) -> 2 | H31: =SUM(合并采购清单!E11) -> 0 | I31: =F31*G31*$B$4 -> 0.0298 | J31: =F31*H31*$D$4 -> 0 | K31: =ROUNDUP((G31*$B$4+H31*$D$4)/B31,0)*C31 -> 1.49 | L31: =ROUNDUP(G31*$B$4/B31,0)*C31 -> 1.49 | M31: =ROUNDUP(H31*$D$4/B31,0)*C31 -> 0 | N31: =HYPERLINK("https://item.taobao.com/item.htm?id=1005108810412","打开订单商品") -> 打开订单商品 | O31: 142
A32: CC0603KRX7R9BB104 / CL10B104JB8NNNC 0603 100nF ±10% X7R;50V;100个 | B32: 100 | C32: 1.98 | D32: 4.98 | E32: 5.95 | F32: =C32/D32*E32/B32 -> 0.023656627 | G32: =SUM(合并采购清单!D12,合并采购清单!D43) -> 13 | H32: =SUM(合并采购清单!E12,合并采购清单!E43) -> 6 | I32: =F32*G32*$B$4 -> 0.30753614 | J32: =F32*H32*$D$4 -> 0.14193976 | K32: =ROUNDUP((G32*$B$4+H32*$D$4)/B32,0)*C32 -> 1.98 | L32: =ROUNDUP(G32*$B$4/B32,0)*C32 -> 1.98 | M32: =ROUNDUP(H32*$D$4/B32,0)*C32 -> 1.98 | N32: =HYPERLINK("https://item.taobao.com/item.htm?id=731471380840","打开订单商品") -> 打开订单商品 | O32: 79
A33: C3216X7R1V106KT000E 1206 10UF ±10% X7R;35V | B33: 1 | C33: 0.12 | D33: 6.18 | E33: 6.14 | F33: =C33/D33*E33/B33 -> 0.1192233 | G33: =SUM(合并采购清单!D13) -> 1 | H33: =SUM(合并采购清单!E13) -> 0 | I33: =F33*G33*$B$4 -> 0.1192233 | J33: =F33*H33*$D$4 -> 0 | K33: =ROUNDUP((G33*$B$4+H33*$D$4)/B33,0)*C33 -> 0.12 | L33: =ROUNDUP(G33*$B$4/B33,0)*C33 -> 0.12 | M33: =ROUNDUP(H33*$D$4/B33,0)*C33 -> 0 | N33: =HYPERLINK("https://item.taobao.com/item.htm?id=730407108775","打开订单商品") -> 打开订单商品 | O33: 206
A34: GRM188R61A226ME15D 22UF 226K 10% X5R;10V;0603=100个 | B34: 100 | C34: 3.5 | D34: 3.5 | E34: 3.5 | F34: =C34/D34*E34/B34 -> 0.035 | G34: =SUM(合并采购清单!D14) -> 2 | H34: =SUM(合并采购清单!E14) -> 0 | I34: =F34*G34*$B$4 -> 0.07 | J34: =F34*H34*$D$4 -> 0 | K34: =ROUNDUP((G34*$B$4+H34*$D$4)/B34,0)*C34 -> 3.5 | L34: =ROUNDUP(G34*$B$4/B34,0)*C34 -> 3.5 | M34: =ROUNDUP(H34*$D$4/B34,0)*C34 -> 0 | N34: =HYPERLINK("https://item.taobao.com/item.htm?id=993202872551","打开订单商品") -> 打开订单商品 | O34: 96
A35: CC0603KRX7R9BB103 0603 10NF 50V 10% 100个 | B35: 100 | C35: 2 | D35: 2 | E35: 2 | F35: =C35/D35*E35/B35 -> 0.02 | G35: =SUM(合并采购清单!D15) -> 1 | H35: =SUM(合并采购清单!E15) -> 0 | I35: =F35*G35*$B$4 -> 0.02 | J35: =F35*H35*$D$4 -> 0 | K35: =ROUNDUP((G35*$B$4+H35*$D$4)/B35,0)*C35 -> 2 | L35: =ROUNDUP(G35*$B$4/B35,0)*C35 -> 2 | M35: =ROUNDUP(H35*$D$4/B35,0)*C35 -> 0 | N35: =HYPERLINK("https://item.taobao.com/item.htm?id=610558214623","打开订单商品") -> 打开订单商品 | O35: 124
A36: BAT54SW,115 BAT54SW 印字44t（20只） | B36: 20 | C36: 4.5 | D36: 4.5 | E36: 4.5 | F36: =C36/D36*E36/B36 -> 0.225 | G36: =SUM(合并采购清单!D16) -> 1 | H36: =SUM(合并采购清单!E16) -> 0 | I36: =F36*G36*$B$4 -> 0.225 | J36: =F36*H36*$D$4 -> 0 | K36: =ROUNDUP((G36*$B$4+H36*$D$4)/B36,0)*C36 -> 4.5 | L36: =ROUNDUP(G36*$B$4/B36,0)*C36 -> 4.5 | M36: =ROUNDUP(H36*$D$4/B36,0)*C36 -> 0 | N36: =HYPERLINK("https://item.taobao.com/item.htm?id=793455311175","打开订单商品") -> 打开订单商品 | O36: 94
A37: BZT52C5V1S-7-F BZT52C5V1S W8 SOD-323 (50个) | B37: 50 | C37: 1.53 | D37: 3.3 | E37: 3.3 | F37: =C37/D37*E37/B37 -> 0.0306 | G37: =SUM(合并采购清单!D17) -> 1 | H37: =SUM(合并采购清单!E17) -> 0 | I37: =F37*G37*$B$4 -> 0.0306 | J37: =F37*H37*$D$4 -> 0 | K37: =ROUNDUP((G37*$B$4+H37*$D$4)/B37,0)*C37 -> 1.53 | L37: =ROUNDUP(G37*$B$4/B37,0)*C37 -> 1.53 | M37: =ROUNDUP(H37*$D$4/B37,0)*C37 -> 0 | N37: =HYPERLINK("https://item.taobao.com/item.htm?id=943185002457","打开订单商品") -> 打开订单商品 | O37: 122
A38: BLM18KG601SN1D 0603_600R_1.3A_±25%【100只】 | B38: 100 | C38: 5.6 | D38: 9.6 | E38: 9.6 | F38: =C38/D38*E38/B38 -> 0.056 | G38: =SUM(合并采购清单!D18) -> 1 | H38: =SUM(合并采购清单!E18) -> 0 | I38: =F38*G38*$B$4 -> 0.056 | J38: =F38*H38*$D$4 -> 0 | K38: =ROUNDUP((G38*$B$4+H38*$D$4)/B38,0)*C38 -> 5.6 | L38: =ROUNDUP(G38*$B$4/B38,0)*C38 -> 5.6 | M38: =ROUNDUP(H38*$D$4/B38,0)*C38 -> 0 | N38: =HYPERLINK("https://item.taobao.com/item.htm?id=931081429973","打开订单商品") -> 打开订单商品 | O38: 126
A39: PE-0603PFB121ST 0603_120R_2A_±25%【100只】 | B39: 100 | C39: 4 | D39: 9.6 | E39: 9.6 | F39: =C39/D39*E39/B39 -> 0.04 | G39: =SUM(合并采购清单!D19) -> 2 | H39: =SUM(合并采购清单!E19) -> 0 | I39: =F39*G39*$B$4 -> 0.08 | J39: =F39*H39*$D$4 -> 0 | K39: =ROUNDUP((G39*$B$4+H39*$D$4)/B39,0)*C39 -> 4 | L39: =ROUNDUP(G39*$B$4/B39,0)*C39 -> 4 | M39: =ROUNDUP(H39*$D$4/B39,0)*C39 -> 0 | N39: =HYPERLINK("https://item.taobao.com/item.htm?id=931081429973","打开订单商品") -> 打开订单商品 | O39: 125
A40: B2B-EH-A(LF)(SN) EH2.5MM 2P直针座（50个） | B40: 50 | C40: 2.5 | D40: 9.3 | E40: 9.3 | F40: =C40/D40*E40/B40 -> 0.05 | G40: =SUM(合并采购清单!D20) -> 3 | H40: =SUM(合并采购清单!E20) -> 0 | I40: =F40*G40*$B$4 -> 0.15 | J40: =F40*H40*$D$4 -> 0 | K40: =ROUNDUP((G40*$B$4+H40*$D$4)/B40,0)*C40 -> 2.5 | L40: =ROUNDUP(G40*$B$4/B40,0)*C40 -> 2.5 | M40: =ROUNDUP(H40*$D$4/B40,0)*C40 -> 0 | N40: =HYPERLINK("https://item.taobao.com/item.htm?id=832569969546","打开订单商品") -> 打开订单商品 | O40: 118
A41: FH-00339 2*20P 贴片排母【2个】 | B41: 2 | C41: 4.07 | D41: 4.07 | E41: 4.07 | F41: =C41/D41*E41/B41 -> 2.035 | G41: =SUM(合并采购清单!D21) -> 1 | H41: =SUM(合并采购清单!E21) -> 0 | I41: =F41*G41*$B$4 -> 2.035 | J41: =F41*H41*$D$4 -> 0 | K41: =ROUNDUP((G41*$B$4+H41*$D$4)/B41,0)*C41 -> 4.07 | L41: =ROUNDUP(G41*$B$4/B41,0)*C41 -> 4.07 | M41: =ROUNDUP(H41*$D$4/B41,0)*C41 -> 0 | N41: =HYPERLINK("https://item.taobao.com/item.htm?id=533725557959","打开订单商品") -> 打开订单商品 | O41: 140
A42: BM04B-SRSS-TB(LF)(SN) 4P立贴（15个） | B42: 15 | C42: 2.22 | D42: 2.22 | E42: 2.22 | F42: =C42/D42*E42/B42 -> 0.148 | G42: =SUM(合并采购清单!D22) -> 1 | H42: =SUM(合并采购清单!E22) -> 0 | I42: =F42*G42*$B$4 -> 0.148 | J42: =F42*H42*$D$4 -> 0 | K42: =ROUNDUP((G42*$B$4+H42*$D$4)/B42,0)*C42 -> 2.22 | L42: =ROUNDUP(G42*$B$4/B42,0)*C42 -> 2.22 | M42: =ROUNDUP(H42*$D$4/B42,0)*C42 -> 0 | N42: =HYPERLINK("https://item.taobao.com/item.htm?id=920058690376","打开订单商品") -> 打开订单商品 | O42: 139
A43: B3B-EH-A(LF)(SN) EH2.5MM 3P直针座（50个） | B43: 50 | C43: 3 | D43: 9.3 | E43: 9.3 | F43: =C43/D43*E43/B43 -> 0.06 | G43: =SUM(合并采购清单!D23) -> 2 | H43: =SUM(合并采购清单!E23) -> 1 | I43: =F43*G43*$B$4 -> 0.12 | J43: =F43*H43*$D$4 -> 0.06 | K43: =ROUNDUP((G43*$B$4+H43*$D$4)/B43,0)*C43 -> 3 | L43: =ROUNDUP(G43*$B$4/B43,0)*C43 -> 3 | M43: =ROUNDUP(H43*$D$4/B43,0)*C43 -> 3 | N43: =HYPERLINK("https://item.taobao.com/item.htm?id=832569969546","打开订单商品") -> 打开订单商品 | O43: 117
A44: SWPA6045S6R8MT 合金0630 6.8UH 印6R8 10个 6A 一体 | B44: 10 | C44: 2 | D44: 2 | E44: 2 | F44: =C44/D44*E44/B44 -> 0.2 | G44: =SUM(合并采购清单!D24) -> 1 | H44: =SUM(合并采购清单!E24) -> 0 | I44: =F44*G44*$B$4 -> 0.2 | J44: =F44*H44*$D$4 -> 0 | K44: =ROUNDUP((G44*$B$4+H44*$D$4)/B44,0)*C44 -> 2 | L44: =ROUNDUP(G44*$B$4/B44,0)*C44 -> 2 | M44: =ROUNDUP(H44*$D$4/B44,0)*C44 -> 0 | N44: =HYPERLINK("https://item.taobao.com/item.htm?id=598174251748","打开订单商品") -> 打开订单商品 | O44: 127
A45: LMA2718T421-OA5-2 2718 上进音 硅麦克风【2个】 | B45: 2 | C45: 1.98 | D45: 3.96 | E45: 3.96 | F45: =C45/D45*E45/B45 -> 0.99 | G45: =SUM(合并采购清单!D25) -> 1 | H45: =SUM(合并采购清单!E25) -> 0 | I45: =F45*G45*$B$4 -> 0.99 | J45: =F45*H45*$D$4 -> 0 | K45: =ROUNDUP((G45*$B$4+H45*$D$4)/B45,0)*C45 -> 1.98 | L45: =ROUNDUP(G45*$B$4/B45,0)*C45 -> 1.98 | M45: =ROUNDUP(H45*$D$4/B45,0)*C45 -> 0 | N45: =HYPERLINK("https://item.taobao.com/item.htm?id=996702312391","打开订单商品") -> 打开订单商品 | O45: 141
A46: MMBT3906 MMBT3906 丝印2A SOT-23(50个) | B46: 50 | C46: 1.77 | D46: 3.3 | E46: 3.3 | F46: =C46/D46*E46/B46 -> 0.0354 | G46: =SUM(合并采购清单!D26) -> 1 | H46: =SUM(合并采购清单!E26) -> 0 | I46: =F46*G46*$B$4 -> 0.0354 | J46: =F46*H46*$D$4 -> 0 | K46: =ROUNDUP((G46*$B$4+H46*$D$4)/B46,0)*C46 -> 1.77 | L46: =ROUNDUP(G46*$B$4/B46,0)*C46 -> 1.77 | M46: =ROUNDUP(H46*$D$4/B46,0)*C46 -> 0 | N46: =HYPERLINK("https://item.taobao.com/item.htm?id=944306254140","打开订单商品") -> 打开订单商品 | O46: 121
A47: SI2312CDS-T1-GE3 SI2312DS（AE9T）N沟道（20只） | B47: 20 | C47: 3 | D47: 3 | E47: 3 | F47: =C47/D47*E47/B47 -> 0.15 | G47: =SUM(合并采购清单!D27) -> 1 | H47: =SUM(合并采购清单!E27) -> 0 | I47: =F47*G47*$B$4 -> 0.15 | J47: =F47*H47*$D$4 -> 0 | K47: =ROUNDUP((G47*$B$4+H47*$D$4)/B47,0)*C47 -> 3 | L47: =ROUNDUP(G47*$B$4/B47,0)*C47 -> 3 | M47: =ROUNDUP(H47*$D$4/B47,0)*C47 -> 0 | N47: =HYPERLINK("https://item.taobao.com/item.htm?id=909264246006","打开订单商品") -> 打开订单商品 | O47: 93
A48: RC0603FR-0710KL 10K;0603 1%（100个） | B48: 100 | C48: 1.42 | D48: 1.42 | E48: 1.42 | F48: =C48/D48*E48/B48 -> 0.0142 | G48: =SUM(合并采购清单!D28) -> 12 | H48: =SUM(合并采购清单!E28) -> 3 | I48: =F48*G48*$B$4 -> 0.1704 | J48: =F48*H48*$D$4 -> 0.0426 | K48: =ROUNDUP((G48*$B$4+H48*$D$4)/B48,0)*C48 -> 1.42 | L48: =ROUNDUP(G48*$B$4/B48,0)*C48 -> 1.42 | M48: =ROUNDUP(H48*$D$4/B48,0)*C48 -> 1.42 | N48: =HYPERLINK("https://item.taobao.com/item.htm?id=947267344247","打开订单商品") -> 打开订单商品 | O48: 80
A49: 0603WAF0000T5E 0R/0欧;0603 1%（100个） | B49: 100 | C49: 1.46 | D49: 4.34 | E49: 4.34 | F49: =C49/D49*E49/B49 -> 0.0146 | G49: =SUM(合并采购清单!D29) -> 5 | H49: =SUM(合并采购清单!E29) -> 1 | I49: =F49*G49*$B$4 -> 0.073 | J49: =F49*H49*$D$4 -> 0.0146 | K49: =ROUNDUP((G49*$B$4+H49*$D$4)/B49,0)*C49 -> 1.46 | L49: =ROUNDUP(G49*$B$4/B49,0)*C49 -> 1.46 | M49: =ROUNDUP(H49*$D$4/B49,0)*C49 -> 1.46 | N49: =HYPERLINK("https://item.taobao.com/item.htm?id=947267344247","打开订单商品") -> 打开订单商品 | O49: 155
A50: 0603WAF1000T5E 100R/100欧;0603 1%（100个） | B50: 100 | C50: 1.46 | D50: 4.38 | E50: 4.38 | F50: =C50/D50*E50/B50 -> 0.0146 | G50: =SUM(合并采购清单!D30) -> 1 | H50: =SUM(合并采购清单!E30) -> 0 | I50: =F50*G50*$B$4 -> 0.0146 | J50: =F50*H50*$D$4 -> 0 | K50: =ROUNDUP((G50*$B$4+H50*$D$4)/B50,0)*C50 -> 1.46 | L50: =ROUNDUP(G50*$B$4/B50,0)*C50 -> 1.46 | M50: =ROUNDUP(H50*$D$4/B50,0)*C50 -> 0 | N50: =HYPERLINK("https://item.taobao.com/item.htm?id=947267344247","打开订单商品") -> 打开订单商品 | O50: 134
A51: 0603WAF2002T5E 20K;0603 1%（100个） | B51: 100 | C51: 1.46 | D51: 4.38 | E51: 4.38 | F51: =C51/D51*E51/B51 -> 0.0146 | G51: =SUM(合并采购清单!D31) -> 1 | H51: =SUM(合并采购清单!E31) -> 0 | I51: =F51*G51*$B$4 -> 0.0146 | J51: =F51*H51*$D$4 -> 0 | K51: =ROUNDUP((G51*$B$4+H51*$D$4)/B51,0)*C51 -> 1.46 | L51: =ROUNDUP(G51*$B$4/B51,0)*C51 -> 1.46 | M51: =ROUNDUP(H51*$D$4/B51,0)*C51 -> 0 | N51: =HYPERLINK("https://item.taobao.com/item.htm?id=947267344247","打开订单商品") -> 打开订单商品 | O51: 135
A52: PRG18BB101MB1RB 100R PRG18BB101MB1RB | B52: 1 | C52: 0.7 | D52: 7 | E52: 12 | F52: =C52/D52*E52/B52 -> 1.2 | G52: =SUM(合并采购清单!D32) -> 1 | H52: =SUM(合并采购清单!E32) -> 0 | I52: =F52*G52*$B$4 -> 1.2 | J52: =F52*H52*$D$4 -> 0 | K52: =ROUNDUP((G52*$B$4+H52*$D$4)/B52,0)*C52 -> 0.7 | L52: =ROUNDUP(G52*$B$4/B52,0)*C52 -> 0.7 | M52: =ROUNDUP(H52*$D$4/B52,0)*C52 -> 0 | N52: =HYPERLINK("https://item.taobao.com/item.htm?id=582129955778","打开订单商品") -> 打开订单商品 | O52: 95
A53: PAM8406DR PAM8406DR | B53: 1 | C53: 1.18 | D53: 5.9 | E53: 5.89 | F53: =C53/D53*E53/B53 -> 1.178 | G53: =SUM(合并采购清单!D33) -> 1 | H53: =SUM(合并采购清单!E33) -> 0 | I53: =F53*G53*$B$4 -> 1.178 | J53: =F53*H53*$D$4 -> 0 | K53: =ROUNDUP((G53*$B$4+H53*$D$4)/B53,0)*C53 -> 1.18 | L53: =ROUNDUP(G53*$B$4/B53,0)*C53 -> 1.18 | M53: =ROUNDUP(H53*$D$4/B53,0)*C53 -> 0 | N53: =HYPERLINK("https://item.taobao.com/item.htm?id=808484505787","打开订单商品") -> 打开订单商品 | O53: 132
A54: TLV320AIC3104IRHBR 商品无选项，按商品标题完整型号购买 | B54: 1 | C54: 1.9 | D54: 9.5 | E54: 11.52 | F54: =C54/D54*E54/B54 -> 2.304 | G54: =SUM(合并采购清单!D34) -> 1 | H54: =SUM(合并采购清单!E34) -> 0 | I54: =F54*G54*$B$4 -> 2.304 | J54: =F54*H54*$D$4 -> 0 | K54: =ROUNDUP((G54*$B$4+H54*$D$4)/B54,0)*C54 -> 1.9 | L54: =ROUNDUP(G54*$B$4/B54,0)*C54 -> 1.9 | M54: =ROUNDUP(H54*$D$4/B54,0)*C54 -> 0 | N54: =HYPERLINK("https://item.taobao.com/item.htm?id=908248360601","打开订单商品") -> 打开订单商品 | O54: 143
A55: XC6206P182MR XC6206P182MR 65K5 SOT-23 (20个) | B55: 20 | C55: 1.8 | D55: 9.3 | E55: 9.3 | F55: =C55/D55*E55/B55 -> 0.09 | G55: =SUM(合并采购清单!D35) -> 1 | H55: =SUM(合并采购清单!E35) -> 0 | I55: =F55*G55*$B$4 -> 0.09 | J55: =F55*H55*$D$4 -> 0 | K55: =ROUNDUP((G55*$B$4+H55*$D$4)/B55,0)*C55 -> 1.8 | L55: =ROUNDUP(G55*$B$4/B55,0)*C55 -> 1.8 | M55: =ROUNDUP(H55*$D$4/B55,0)*C55 -> 0 | N55: =HYPERLINK("https://item.taobao.com/item.htm?id=762173333947","打开订单商品") -> 打开订单商品 | O55: 119
A56: SN74LVC1G08DBVR SN74LVC1G08DBVR;5个全国包邮 | B56: 5 | C56: 1.2 | D56: 4.3 | E56: 4.3 | F56: =C56/D56*E56/B56 -> 0.24 | G56: =SUM(合并采购清单!D36) -> 1 | H56: =SUM(合并采购清单!E36) -> 0 | I56: =F56*G56*$B$4 -> 0.24 | J56: =F56*H56*$D$4 -> 0 | K56: =ROUNDUP((G56*$B$4+H56*$D$4)/B56,0)*C56 -> 1.2 | L56: =ROUNDUP(G56*$B$4/B56,0)*C56 -> 1.2 | M56: =ROUNDUP(H56*$D$4/B56,0)*C56 -> 0 | N56: =HYPERLINK("https://item.taobao.com/item.htm?id=902117985110","打开订单商品") -> 打开订单商品 | O56: 130
A57: SN74LVC1G125DBVR-TP SN74LVC1G125DBVR;5个全国包邮 | B57: 5 | C57: 1.3 | D57: 4.3 | E57: 4.3 | F57: =C57/D57*E57/B57 -> 0.26 | G57: =SUM(合并采购清单!D37) -> 1 | H57: =SUM(合并采购清单!E37) -> 0 | I57: =F57*G57*$B$4 -> 0.26 | J57: =F57*H57*$D$4 -> 0 | K57: =ROUNDUP((G57*$B$4+H57*$D$4)/B57,0)*C57 -> 1.3 | L57: =ROUNDUP(G57*$B$4/B57,0)*C57 -> 1.3 | M57: =ROUNDUP(H57*$D$4/B57,0)*C57 -> 0 | N57: =HYPERLINK("https://item.taobao.com/item.htm?id=902117985110","打开订单商品") -> 打开订单商品 | O57: 128
A58: SN74LVC1G126DBVR SN74LVC1G126DBVR;5个全国包邮 | B58: 5 | C58: 1.8 | D58: 4.3 | E58: 4.3 | F58: =C58/D58*E58/B58 -> 0.36 | G58: =SUM(合并采购清单!D38) -> 1 | H58: =SUM(合并采购清单!E38) -> 0 | I58: =F58*G58*$B$4 -> 0.36 | J58: =F58*H58*$D$4 -> 0 | K58: =ROUNDUP((G58*$B$4+H58*$D$4)/B58,0)*C58 -> 1.8 | L58: =ROUNDUP(G58*$B$4/B58,0)*C58 -> 1.8 | M58: =ROUNDUP(H58*$D$4/B58,0)*C58 -> 0 | N58: =HYPERLINK("https://item.taobao.com/item.htm?id=902117985110","打开订单商品") -> 打开订单商品 | O58: 129
A59: AP63205WU-7 AP63205WU-7 | B59: 1 | C59: 1.28 | D59: 6.4 | E59: 6.39 | F59: =C59/D59*E59/B59 -> 1.278 | G59: =SUM(合并采购清单!D39) -> 1 | H59: =SUM(合并采购清单!E39) -> 0 | I59: =F59*G59*$B$4 -> 1.278 | J59: =F59*H59*$D$4 -> 0 | K59: =ROUNDUP((G59*$B$4+H59*$D$4)/B59,0)*C59 -> 1.28 | L59: =ROUNDUP(G59*$B$4/B59,0)*C59 -> 1.28 | M59: =ROUNDUP(H59*$D$4/B59,0)*C59 -> 0 | N59: =HYPERLINK("https://item.taobao.com/item.htm?id=969642590399","打开订单商品") -> 打开订单商品 | O59: 203
A60: LM5050MKX-1/NOPB SOT-23;LM5050MKX-1/NOPB 原装正品 | B60: 1 | C60: 2.46 | D60: 12.3 | E60: 12.28 | F60: =C60/D60*E60/B60 -> 2.456 | G60: =SUM(合并采购清单!D40) -> 1 | H60: =SUM(合并采购清单!E40) -> 0 | I60: =F60*G60*$B$4 -> 2.456 | J60: =F60*H60*$D$4 -> 0 | K60: =ROUNDUP((G60*$B$4+H60*$D$4)/B60,0)*C60 -> 2.46 | L60: =ROUNDUP(G60*$B$4/B60,0)*C60 -> 2.46 | M60: =ROUNDUP(H60*$D$4/B60,0)*C60 -> 0 | N60: =HYPERLINK("https://item.taobao.com/item.htm?id=1013388982214","打开订单商品") -> 打开订单商品 | O60: 137
A61: OT3EL89CJI-111YLC-12M 12MHZ 1.2V~3.36V宽压[高精度10PPM];SMD2520-4P CMOS输出 | B61: 1 | C61: 1.45 | D61: 7.25 | E61: 7.26 | F61: =C61/D61*E61/B61 -> 1.452 | G61: =SUM(合并采购清单!D41) -> 1 | H61: =SUM(合并采购清单!E41) -> 0 | I61: =F61*G61*$B$4 -> 1.452 | J61: =F61*H61*$D$4 -> 0 | K61: =ROUNDUP((G61*$B$4+H61*$D$4)/B61,0)*C61 -> 1.45 | L61: =ROUNDUP(G61*$B$4/B61,0)*C61 -> 1.45 | M61: =ROUNDUP(H61*$D$4/B61,0)*C61 -> 0 | N61: =HYPERLINK("https://item.taobao.com/item.htm?id=944053669860","打开订单商品") -> 打开订单商品 | O61: 131
A62: CL21A475KAQNNNE 0805 4.7UF ±10% X7R;25V | B62: 1 | C62: 0.06 | D62: 6 | E62: 6.94 | F62: =C62/D62*E62/B62 -> 0.0694 | G62: =SUM(合并采购清单!D42) -> 0 | H62: =SUM(合并采购清单!E42) -> 2 | I62: =F62*G62*$B$4 -> 0 | J62: =F62*H62*$D$4 -> 0.1388 | K62: =ROUNDUP((G62*$B$4+H62*$D$4)/B62,0)*C62 -> 0.12 | L62: =ROUNDUP(G62*$B$4/B62,0)*C62 -> 0 | M62: =ROUNDUP(H62*$D$4/B62,0)*C62 -> 0.12 | N62: =HYPERLINK("https://item.taobao.com/item.htm?id=977236759812","打开订单商品") -> 打开订单商品 | O62: 153
A63: PESD5V0S1BA 商品无选项，按商品标题完整型号购买 | B63: 1 | C63: 0.06 | D63: 3 | E63: 4.5 | F63: =C63/D63*E63/B63 -> 0.09 | G63: =SUM(合并采购清单!D45) -> 0 | H63: =SUM(合并采购清单!E45) -> 1 | I63: =F63*G63*$B$4 -> 0 | J63: =F63*H63*$D$4 -> 0.09 | K63: =ROUNDUP((G63*$B$4+H63*$D$4)/B63,0)*C63 -> 0.06 | L63: =ROUNDUP(G63*$B$4/B63,0)*C63 -> 0 | M63: =ROUNDUP(H63*$D$4/B63,0)*C63 -> 0.06 | N63: =HYPERLINK("https://item.taobao.com/item.htm?id=891785167202","打开订单商品") -> 打开订单商品 | O63: 160
A64: 19-217/GHC-YR1S2/3T 0603 蓝色=100个 | B64: 100 | C64: 1.8 | D64: 3.6 | E64: 3.6 | F64: =C64/D64*E64/B64 -> 0.018 | G64: =SUM(合并采购清单!D46) -> 0 | H64: =SUM(合并采购清单!E46) -> 1 | I64: =F64*G64*$B$4 -> 0 | J64: =F64*H64*$D$4 -> 0.018 | K64: =ROUNDUP((G64*$B$4+H64*$D$4)/B64,0)*C64 -> 1.8 | L64: =ROUNDUP(G64*$B$4/B64,0)*C64 -> 0 | M64: =ROUNDUP(H64*$D$4/B64,0)*C64 -> 1.8 | N64: =HYPERLINK("https://item.taobao.com/item.htm?id=1025817117811","打开订单商品") -> 打开订单商品 | O64: 158
A65: PZ254V-11-05P 1*5P直针 铜（30条） | B65: 30 | C65: 1.41 | D65: 1.41 | E65: 1.41 | F65: =C65/D65*E65/B65 -> 0.047 | G65: =SUM(合并采购清单!D47) -> 0 | H65: =SUM(合并采购清单!E47) -> 1 | I65: =F65*G65*$B$4 -> 0 | J65: =F65*H65*$D$4 -> 0.047 | K65: =ROUNDUP((G65*$B$4+H65*$D$4)/B65,0)*C65 -> 1.41 | L65: =ROUNDUP(G65*$B$4/B65,0)*C65 -> 0 | M65: =ROUNDUP(H65*$D$4/B65,0)*C65 -> 1.41 | N65: =HYPERLINK("https://item.taobao.com/item.htm?id=606816197525","打开订单商品") -> 打开订单商品 | O65: 152
A66: RC0603FR-07100KL 100K;0603 1%（100个） | B66: 100 | C66: 1.46 | D66: 14.56 | E66: 14.56 | F66: =C66/D66*E66/B66 -> 0.0146 | G66: =SUM(合并采购清单!D48) -> 0 | H66: =SUM(合并采购清单!E48) -> 1 | I66: =F66*G66*$B$4 -> 0 | J66: =F66*H66*$D$4 -> 0.0146 | K66: =ROUNDUP((G66*$B$4+H66*$D$4)/B66,0)*C66 -> 1.46 | L66: =ROUNDUP(G66*$B$4/B66,0)*C66 -> 0 | M66: =ROUNDUP(H66*$D$4/B66,0)*C66 -> 1.46 | N66: =HYPERLINK("https://item.taobao.com/item.htm?id=947267344247","打开订单商品") -> 打开订单商品 | O66: 56
A67: 0603WAF330JT5E 33R/33欧;0603 1%（100个） | B67: 100 | C67: 1.46 | D67: 4.34 | E67: 4.34 | F67: =C67/D67*E67/B67 -> 0.0146 | G67: =SUM(合并采购清单!D49) -> 0 | H67: =SUM(合并采购清单!E49) -> 1 | I67: =F67*G67*$B$4 -> 0 | J67: =F67*H67*$D$4 -> 0.0146 | K67: =ROUNDUP((G67*$B$4+H67*$D$4)/B67,0)*C67 -> 1.46 | L67: =ROUNDUP(G67*$B$4/B67,0)*C67 -> 0 | M67: =ROUNDUP(H67*$D$4/B67,0)*C67 -> 1.46 | N67: =HYPERLINK("https://item.taobao.com/item.htm?id=947267344247","打开订单商品") -> 打开订单商品 | O67: 157
A68: 0603WAF1001T5E 1K;0603 1%（100个） | B68: 100 | C68: 1.44 | D68: 1.44 | E68: 1.44 | F68: =C68/D68*E68/B68 -> 0.0144 | G68: =SUM(合并采购清单!D50) -> 0 | H68: =SUM(合并采购清单!E50) -> 1 | I68: =F68*G68*$B$4 -> 0 | J68: =F68*H68*$D$4 -> 0.0144 | K68: =ROUNDUP((G68*$B$4+H68*$D$4)/B68,0)*C68 -> 1.44 | L68: =ROUNDUP(G68*$B$4/B68,0)*C68 -> 0 | M68: =ROUNDUP(H68*$D$4/B68,0)*C68 -> 1.44 | N68: =HYPERLINK("https://item.taobao.com/item.htm?id=947267344247","打开订单商品") -> 打开订单商品 | O68: 213
A69: STM32G031F8P6 全新原装 | B69: 1 | C69: 4.83 | D69: 34.8 | E69: 35.79 | F69: =C69/D69*E69/B69 -> 4.9674052 | G69: =SUM(合并采购清单!D51) -> 0 | H69: =SUM(合并采购清单!E51) -> 1 | I69: =F69*G69*$B$4 -> 0 | J69: =F69*H69*$D$4 -> 4.9674052 | K69: =ROUNDUP((G69*$B$4+H69*$D$4)/B69,0)*C69 -> 4.83 | L69: =ROUNDUP(G69*$B$4/B69,0)*C69 -> 0 | M69: =ROUNDUP(H69*$D$4/B69,0)*C69 -> 4.83 | N69: =HYPERLINK("https://item.taobao.com/item.htm?id=726808419708","打开订单商品") -> 打开订单商品 | O69: 150
A70: LSM6DSV16XTR LSM6DSV16XTR | B70: 1 | C70: 5.75 | D70: 11.5 | E70: 11.5 | F70: =C70/D70*E70/B70 -> 5.75 | G70: =SUM(合并采购清单!D52) -> 0 | H70: =SUM(合并采购清单!E52) -> 1 | I70: =F70*G70*$B$4 -> 0 | J70: =F70*H70*$D$4 -> 5.75 | K70: =ROUNDUP((G70*$B$4+H70*$D$4)/B70,0)*C70 -> 5.75 | L70: =ROUNDUP(G70*$B$4/B70,0)*C70 -> 0 | M70: =ROUNDUP(H70*$D$4/B70,0)*C70 -> 5.75 | N70: =HYPERLINK("https://item.taobao.com/item.htm?id=640391703111","打开订单商品") -> 打开订单商品 | O70: 91
A71: TLV70433DBVR TLV70433DBVR | B71: 1 | C71: 0.47 | D71: 4.7 | E71: 4.7 | F71: =C71/D71*E71/B71 -> 0.47 | G71: =SUM(合并采购清单!D53) -> 0 | H71: =SUM(合并采购清单!E53) -> 1 | I71: =F71*G71*$B$4 -> 0 | J71: =F71*H71*$D$4 -> 0.47 | K71: =ROUNDUP((G71*$B$4+H71*$D$4)/B71,0)*C71 -> 0.47 | L71: =ROUNDUP(G71*$B$4/B71,0)*C71 -> 0 | M71: =ROUNDUP(H71*$D$4/B71,0)*C71 -> 0.47 | N71: =HYPERLINK("https://item.taobao.com/item.htm?id=747094785928","打开订单商品") -> 打开订单商品 | O71: 162
A72: SN74LVC2G125DCUR 商品无选项，按商品标题完整型号购买 | B72: 1 | C72: 0.43 | D72: 4.3 | E72: 4.78 | F72: =C72/D72*E72/B72 -> 0.478 | G72: =SUM(合并采购清单!D54) -> 0 | H72: =SUM(合并采购清单!E54) -> 1 | I72: =F72*G72*$B$4 -> 0 | J72: =F72*H72*$D$4 -> 0.478 | K72: =ROUNDUP((G72*$B$4+H72*$D$4)/B72,0)*C72 -> 0.43 | L72: =ROUNDUP(G72*$B$4/B72,0)*C72 -> 0 | M72: =ROUNDUP(H72*$D$4/B72,0)*C72 -> 0.43 | N72: =HYPERLINK("https://item.taobao.com/item.htm?id=705642638300","打开订单商品") -> 打开订单商品 | O72: 161

Sheet 鸭子本体合计
A2: 鸭子本体采购列表与合计
A3: 鸭子本体＋PCB汇总，含参考备料；HAT/IMU各按整板计价，原器件表不动。3D打印、制作工具、焊接清洁耗材不计入。
A4: PCB有免费券：已列商品合计 | B4: =SUM(F11:F35) -> 2234.4885
A5: PCB无券：按单张折算合计 | B5: =B4+(D11+D12)*制作成本!$B$5/制作成本!$D$5 -> 2242.4885
A6: 首次整包整批采购：PCB免费 | B6: =B4-F11-F12+制作成本!D16 -> 2291.6
A7: 首次整包整批采购：PCB无券 | B7: =B6+ROUNDUP(D11/制作成本!$D$5,0)*制作成本!$B$5+ROUNDUP(D12/制作成本!$D$5,0)*制作成本!$B$5 -> 2331.6
A9: HAT/IMU接口使用EH，舵机使用AMP2.0成品线（10cm、20cm）。数量含备料，螺丝按整包；M2×5原订单为0元优惠价。TF卡等未提供价格的项目未计入。
A10: 商品 / 模块 | B10: 型号 / 指定款式 | C10: 计价单位 | D10: 参考采购数量 | E10: 历史单价(元) | F10: 小计(元) | G10: 数量与费用说明 | H10: 商品或BOM链接
A11: HAT 整板 | B11: HAT-V5，84个板上器件，含PCB | C11: 块 | D11: =合并采购清单!B4 -> 1 | E11: =SUMPRODUCT(制作成本!F29:F72,制作成本!G29:G72) -> 16.724905 | F11: =D11*E11 -> 16.724905 | G11: 按单板实际用料分摊，PCB免费券基准；无券每块另加4元。 | H11: =HYPERLINK("https://github.com/kissqy/Microduck-kissqy/blob/main/hardware/README.md#完整位号bom","查看完整BOM") -> 查看完整BOM
A12: IMU 整板 | B12: IMU-TO-DLX-V2，25个板上器件，含PCB | C12: 块 | D12: =合并采购清单!D4 -> 1 | E12: =SUMPRODUCT(制作成本!F29:F72,制作成本!H29:H72) -> 12.333632 | F12: =D12*E12 -> 12.333632 | G12: 按单板实际用料分摊，PCB免费券基准；无券每块另加4元。 | H12: =HYPERLINK("https://github.com/kissqy/Microduck-kissqy/blob/main/hardware/README.md#完整位号bom","查看完整BOM") -> 查看完整BOM
A13: 飞特 HD1910 串口总线舵机 | B13: HD-1910-C001；HD-1910-C001 | C13: 只 | D13: 15 | E13: =配件与耗材!K16 -> 99 | F13: =D13*E13 -> 1485 | G13: 作者两次订单分别购入13只和2只，共15只；选择 HD-1910-C001 款式。 | H13: =HYPERLINK("https://item.taobao.com/item.htm?id=1078248851201","打开订单商品") -> 打开订单商品
A14: Radxa ZERO 3W | B14: 2GB RAM 无 eMMC 带排针[【Microduck 原版主板】]；2GB RAM / 无eMMC / 带排针 | C14: 个 | D14: 1 | E14: =配件与耗材!K15 -> 309 | F14: =D14*E14 -> 309 | G14: 已完成订单的主板款式；属于配套主控，不计入 HAT 84 个器件。 | H14: =HYPERLINK("https://item.taobao.com/item.htm?id=763812025816","打开订单商品") -> 打开订单商品
A15: NP-F550 电池与双充套装 | B15: 【NP-F550补光灯专用▲2200mAh】2电+标准双充套裝；沣标 NP-F550 / 2200mAh / 2块电池＋标准双充 | C15: 套 | D15: 1 | E15: =配件与耗材!K18 -> 84.59 | F15: =D15*E15 -> 84.59 | G15: 按“NP-F550补光灯专用▲2200mAh，2电+标准双充套裝”原款式购买。 | H15: =HYPERLINK("https://item.taobao.com/item.htm?id=585415365001","打开订单商品") -> 打开订单商品
A16: Radxa 8M 219 摄像头 | B16: 8M 219 摄像头[【适配3W/3E/3A/3C/CM5/4系列】]；IMX219 / 800万像素 / 瑞莎8M 219 | C16: 个 | D16: 1 | E16: =配件与耗材!K17 -> 129.99 | F16: =D16*E16 -> 129.99 | G16: 按原订单的8M 219摄像头款式购买。 | H16: =HYPERLINK("https://item.taobao.com/item.htm?id=768918125679","打开订单商品") -> 打开订单商品
A17: 8×8 ToF 测距模块 | B17: VL53L5X V2模块配盖片；VL53L5X V2模块配盖片（商品标题 VL53L5CX） | C17: 个 | D17: 1 | E17: =配件与耗材!K14 -> 49.5 | F17: =D17*E17 -> 49.5 | G17: 外接模块，不是 PCB 上的裸芯片；模块接线和供电按已验证方案。 | H17: =HYPERLINK("https://item.taobao.com/item.htm?id=737603917521","打开订单商品") -> 打开订单商品
A18: 扬声器 | B18: 3525腔体-4Ω3W/喇叭；3525 腔体 / 4Ω 3W | C18: 个 | D18: 1 | E18: =配件与耗材!K13 -> 3.08 | F18: =D18*E18 -> 3.08 | G18: 订单自带1.25端子；HAT板座是 EH 2P，需改接或转接，不能直接认为插头相同。 | H18: =HYPERLINK("https://item.taobao.com/item.htm?id=683920556900","打开订单商品") -> 打开订单商品
A19: 6700 开式薄壁轴承 | B19: 6700开式【轴承钢·精品级】10*15*3MM；6700开式 / 10×15×3mm / 轴承钢精品级 | C19: 只 | D19: 5 | E19: =配件与耗材!K24 -> 1.94 | F19: =D19*E19 -> 9.7 | G19: 按订单参考采购数量计入，包含备料；尺寸顺序为内径×外径×宽度；两次订单为3只和2只。 | H19: =HYPERLINK("https://item.taobao.com/item.htm?id=625390659071","打开订单商品") -> 打开订单商品
A20: ET2216 薄壁轴承 | B20: ET2216【精品级】16*22*4MM[轴承钢]；ET2216 / 16×22×4mm / 轴承钢精品级 | C20: 只 | D20: 12 | E20: =配件与耗材!K25 -> 2.91 | F20: =D20*E20 -> 34.92 | G20: 按订单参考采购数量计入，包含备料；尺寸顺序为内径×外径×宽度；两次订单为10只和2只。 | H20: =HYPERLINK("https://item.taobao.com/item.htm?id=733598659967","打开订单商品") -> 打开订单商品
A21: M2×4 十字盘头平尾自攻螺丝 | B21: M2*4[200只]镀镍；铁镀镍 / 十字圆头 / 平尾自攻 / M2×4 | C21: 包（200个） | D21: 1 | E21: =配件与耗材!K26 -> 3.03 | F21: =D21*E21 -> 3.03 | G21: 每种买1包（200只），包含备料；按打印模型及对应安装位置选择长度；每包数量是备料数量。 | H21: =HYPERLINK("https://item.taobao.com/item.htm?id=534923831046","打开订单商品") -> 打开订单商品
A22: M2×5 十字盘头平尾自攻螺丝 | B22: M2*5[200只]镀镍；铁镀镍 / 十字圆头 / 平尾自攻 / M2×5 | C22: 包（200个） | D22: 1 | E22: =配件与耗材!K27 -> 0 | F22: =D22*E22 -> 0 | G22: 每种买1包（200只），包含备料；按打印模型及对应安装位置选择长度；每包数量是备料数量。原订单商品金额为0元（订单优惠），不代表常规售价。 | H22: =HYPERLINK("https://item.taobao.com/item.htm?id=534923831046","打开订单商品") -> 打开订单商品
A23: M2×6 十字盘头平尾自攻螺丝 | B23: M2*6[200只]镀镍；铁镀镍 / 十字圆头 / 平尾自攻 / M2×6 | C23: 包（200个） | D23: 1 | E23: =配件与耗材!K28 -> 3.31 | F23: =D23*E23 -> 3.31 | G23: 每种买1包（200只），包含备料；按打印模型及对应安装位置选择长度；每包数量是备料数量。 | H23: =HYPERLINK("https://item.taobao.com/item.htm?id=534923831046","打开订单商品") -> 打开订单商品
A24: M2×8 十字盘头平尾自攻螺丝 | B24: M2*8[200只]镀镍；铁镀镍 / 十字圆头 / 平尾自攻 / M2×8 | C24: 包（200个） | D24: 1 | E24: =配件与耗材!K29 -> 3.59 | F24: =D24*E24 -> 3.59 | G24: 每种买1包（200只），包含备料；按打印模型及对应安装位置选择长度；每包数量是备料数量。 | H24: =HYPERLINK("https://item.taobao.com/item.htm?id=534923831046","打开订单商品") -> 打开订单商品
A25: M2×12 十字盘头平尾自攻螺丝 | B25: M2*12[200只]镀镍；铁镀镍 / 十字圆头 / 平尾自攻 / M2×12 | C25: 包（200个） | D25: 1 | E25: =配件与耗材!K30 -> 3.88 | F25: =D25*E25 -> 3.88 | G25: 每种买1包（200只），包含备料；按打印模型及对应安装位置选择长度；每包数量是备料数量。 | H25: =HYPERLINK("https://item.taobao.com/item.htm?id=534923831046","打开订单商品") -> 打开订单商品
A26: M2.6×8 十字盘头平尾自攻螺丝 | B26: M2.6*8[200只]镀镍；铁镀镍 / 十字圆头 / 平尾自攻 / M2.6×8 | C26: 包（200个） | D26: 1 | E26: =配件与耗材!K31 -> 3.59 | F26: =D26*E26 -> 3.59 | G26: 每种买1包（200只），包含备料；按打印模型及对应安装位置选择长度；每包数量是备料数量。 | H26: =HYPERLINK("https://item.taobao.com/item.htm?id=534923831046","打开订单商品") -> 打开订单商品
A27: EH 2P 母壳 | B27: EH2.5MM 2P胶壳（50个）；EH 2P，配 HAT J1/J2/J9 | C27: 包（50个） | D27: 1 | E27: =配件与耗材!K9 -> 2.2 | F27: =D27*E27 -> 2.2 | G27: 每只母壳配2个EH压接端子；按EH2.5款式购买，与板上的EH接口配套。 | H27: =HYPERLINK("https://item.taobao.com/item.htm?id=832569969546","打开订单商品") -> 打开订单商品
A28: EH 3P 母壳 | B28: EH2.5MM 3P胶壳（50个）；EH 3P，配 HAT J13/J14、IMU J1 | C28: 包（50个） | D28: 1 | E28: =配件与耗材!K10 -> 2.8 | F28: =D28*E28 -> 2.8 | G28: 每只母壳还需3个压接端子。 | H28: =HYPERLINK("https://item.taobao.com/item.htm?id=832569969546","打开订单商品") -> 打开订单商品
A29: EH 压接端子 | B29: EH2.5MM 端子（100个）；EH2.5MM 端子 | C29: 包（100个） | D29: 1 | E29: =配件与耗材!K11 -> 3.5 | F29: =D29*E29 -> 3.5 | G29: 与EH母壳成套使用，按EH2.5MM端子款式购买。 | H29: =HYPERLINK("https://item.taobao.com/item.htm?id=832569969546","打开订单商品") -> 打开订单商品
A30: SH1.0 4P 转杜邦母线 | B30: 0.2m;1.0-4P转杜邦母（5条）；SH1.0 4P / 20cm / 杜邦母 | C30: 包（5个） | D30: 1 | E30: =配件与耗材!K12 -> 4.56 | F30: =D30*E30 -> 4.56 | G30: 用于外部接口转接；每根线的脚序按 HAT J5 与模块核对，不按线色猜。 | H30: =HYPERLINK("https://item.taobao.com/item.htm?id=895049863252","打开订单商品") -> 打开订单商品
A31: AMP2.0 3P 舵机线 20cm | B31: 200mm;1007/24#;3P;AMP2.0；200mm / 1007 / 24AWG / 3P / AMP2.0 | C31: 条 | D31: 30 | E31: =配件与耗材!K19 -> 0.9 | F31: =D31*E31 -> 27 | G31: 按订单参考采购数量计入，包含备料；用于飞特舵机线束；10cm和20cm按实际走线位置选择。 | H31: =HYPERLINK("https://item.taobao.com/item.htm?id=825340808235","打开订单商品") -> 打开订单商品
A32: AMP2.0 3P 舵机线 10cm | B32: 100mm;1007/24#;3P;AMP2.0；100mm / 1007 / 24AWG / 3P / AMP2.0 | C32: 条 | D32: 30 | E32: =配件与耗材!K20 -> 0.9 | F32: =D32*E32 -> 27 | G32: 按订单参考采购数量计入，包含备料；与20cm线是不同长度选项，数量按实际线束方案准备。 | H32: =HYPERLINK("https://item.taobao.com/item.htm?id=825340808235","打开订单商品") -> 打开订单商品
A33: 22AWG 三芯硅胶排线 | B33: 黑色;3芯;22AWG;1m；黑色 / 3芯 / 22AWG / 1m | C33: 米 | D33: 3 | E33: =(订单匹配依据!G88*订单匹配依据!H88+订单匹配依据!G89*订单匹配依据!H89)/(订单匹配依据!G88+订单匹配依据!G89) -> 3.5933333 | F33: =D33*E33 -> 10.78 | G33: 原订单2米×3.63元＋1米×3.52元，合计3米10.78元；单价按两次订单均价。 | H33: =HYPERLINK("https://item.taobao.com/item.htm?id=781764816472","打开订单商品") -> 打开订单商品
A34: 22AWG 单芯硅胶线 | B34: 22AWG(0.33平方)黑色 2米；黑色 / 22AWG / 0.33mm² / 2m | C34: 个 | D34: 1 | E34: =配件与耗材!K22 -> 3.42 | F34: =D34*E34 -> 3.42 | G34: 用于自制接线，按22AWG黑色2米款式购买。 | H34: =HYPERLINK("https://item.taobao.com/item.htm?id=736162720327","打开订单商品") -> 打开订单商品
A35: 彩色热缩管套装 | B35: 袋装 164片 彩色 【2倍收缩】；164片 / 彩色 / 2倍收缩 | C35: 个 | D35: 1 | E35: =配件与耗材!K23 -> 0.99 | F35: =D35*E35 -> 0.99 | G35: 用于接线处绝缘及整理。 | H35: =HYPERLINK("https://item.taobao.com/item.htm?id=945215173380","打开订单商品") -> 打开订单商品
